Workbook
Name estrategia_venda: #REF!
Name respons_propostas: #REF!
Name estrategia_diags: #REF!
Name respons_diags: #REF!
Name status_agendamento: #REF!
Name propostas: #REF!
Name produto_propostas: #REF!
Name Data_agendamento: #REF!
Name Diag_Mês: #REF!
Name prop_dw: #REF!
Name vendas: #REF!
Name proposta_Mês: #REF!
Name data_diag: #REF!
Name vendedor_propostas: #REF!
Name responsavel_vendido: #REF!
Name diags: #REF!
Name valor_propostas: #REF!
Name vendedor_vendido: #REF!
Name estrategia_propostas: #REF!
Name data_propostas: #REF!
Name venda_dw: #REF!
Name estrategia_agendamentos: #REF!
Name respons_agendamentos: #REF!
Name data_proposta: #REF!
Name mes_ganho: #REF!
Name valor_vendido: #REF!
Name Agendamento_Mês: #REF!
Name data_ganho: #REF!
Name data_diags: #REF!
Name data_agendamentos: #REF!
Name mês_ganho: #REF!
Name vendedor_diags: #REF!
Name agendamentos: #REF!

Sheet Dados da Operação
B2: DADOS DA OPERAÇÃO | E2: ESTRATÉGIAS DA OPERAÇÃO
B3: Meta semestre | C3: 25000 | E3: Estratégia | F3: Participação na meta | G3: Meta semestral por estratégia | H3: Meta média mensal por estratégia | I3: Qtdd venda semestral | J3: Qntdd de venda mensal
B4: Alcance atual | C4: x | E4: Ativa | F4: 1 | G4: =C3*F4 -> 25000 | H4: =G4/6 -> 4166.6667 | I4: =G4/$C$5 -> 10 | J4: =I4/6 -> 1.6666667
B5: Ticket médio | C5: 2500 | E5: Passiva | F5: 0 | G5: =C3*F5 -> 0 | H5: =G5/6 -> 0 | I5: =G5/$C$5 -> 0 | J5: =I5/6 -> 0
B6: Quantidade de vendas | C6: =C3/C5 -> 10 | E6: Recuperação | F6: 0 | G6: =C3*F6 -> 0 | H6: =G6/6 -> 0 | I6: =G6/$C$5 -> 0 | J6: =I6/6 -> 0
E7: Expansão | F7: 0 | G7: =C3*F7 -> 0 | H7: =G7/6 -> 0 | I7: =G7/$C$5 -> 0 | J7: =I7/6 -> 0
E8: Total da operação | F8: =SUM(F4:F7) -> 1 | G8: =SUM(G4:G7) -> 25000 | H8: =SUM(H4:H7) -> 4166.6667 | I8: =SUM(I4:I7) -> 10 | J8: x
E10: INVESTIMENTOS NA OPERAÇÃO
E11: O que? | F11: Quando? | G11: Porque?
B24: MÊS 1 – JANEIRO | E24: ESTRATÉGIAS – JANEIRO
B25: Meta Janeiro
E26: Estratégia | F26: Participação na meta | G26: Meta Janeiro por estratégia | H26: Qtdd venda mensal
E27: Ativa | F27: 0 | G27: =C25*F27 -> 0 | H27: =G27/$C$5 -> 0
E28: Passiva | F28: 0 | G28: =C25*F28 -> 0 | H28: =G28/$C$5 -> 0
E29: Recuperação | F29: 0 | G29: =C25*F29 -> 0 | H29: =G29/$C$5 -> 0
E30: Expansão | F30: 0 | G30: =C25*F30 -> 0 | H30: =G30/$C$5 -> 0
E31: Total do mês | F31: =SUM(F27:F30) -> 0 | G31: =SUM(G27:G30) -> 0 | H31: =SUM(H27:H30) -> 0
B33: MÊS 2 – FEVEREIRO | E33: ESTRATÉGIAS – FEVEREIRO
B34: Meta Fevereiro
E35: Estratégia | F35: Participação na meta | G35: Meta Fevereiro por estratégia | H35: Qtdd venda mensal
E36: Ativa | F36: 0 | G36: =C34*F36 -> 0 | H36: =G36/$C$5 -> 0
E37: Passiva | F37: 0 | G37: =C34*F37 -> 0 | H37: =G37/$C$5 -> 0
E38: Recuperação | F38: 0 | G38: =C34*F38 -> 0 | H38: =G38/$C$5 -> 0
E39: Expansão | F39: 0 | G39: =C34*F39 -> 0 | H39: =G39/$C$5 -> 0
E40: Total do mês | F40: =SUM(F36:F39) -> 0 | G40: =SUM(G36:G39) -> 0 | H40: =SUM(H36:H39) -> 0
B42: MÊS 3 – MARÇO | E42: ESTRATÉGIAS – MARÇO
B43: Meta Março
E44: Estratégia | F44: Participação na meta | G44: Meta Março por estratégia | H44: Qtdd venda mensal
E45: Ativa | F45: 0 | G45: =C43*F45 -> 0 | H45: =G45/$C$5 -> 0
E46: Passiva | F46: 0 | G46: =C43*F46 -> 0 | H46: =G46/$C$5 -> 0
E47: Recuperação | F47: 0 | G47: =C43*F47 -> 0 | H47: =G47/$C$5 -> 0
E48: Expansão | F48: 0 | G48: =C43*F48 -> 0 | H48: =G48/$C$5 -> 0
E49: Total do mês | F49: =SUM(F45:F48) -> 0 | G49: =SUM(G45:G48) -> 0 | H49: =SUM(H45:H48) -> 0
B51: MÊS 4 – ABRIL | E51: ESTRATÉGIAS – ABRIL
B52: Meta Abril
E53: Estratégia | F53: Participação na meta | G53: Meta Abril por estratégia | H53: Qtdd venda mensal
E54: Ativa | F54: 0 | G54: =C52*F54 -> 0 | H54: =G54/$C$5 -> 0
E55: Passiva | F55: 0 | G55: =C52*F55 -> 0 | H55: =G55/$C$5 -> 0
E56: Recuperação | F56: 0 | G56: =C52*F56 -> 0 | H56: =G56/$C$5 -> 0
E57: Expansão | F57: 0 | G57: =C52*F57 -> 0 | H57: =G57/$C$5 -> 0
E58: Total do mês | F58: =SUM(F54:F57) -> 0 | G58: =SUM(G54:G57) -> 0 | H58: =SUM(H54:H57) -> 0
B60: MÊS 5 – MAIO | E60: ESTRATÉGIAS – MAIO
B61: Meta Maio
E62: Estratégia | F62: Participação na meta | G62: Meta Maio por estratégia | H62: Qtdd venda mensal
E63: Ativa | F63: 0 | G63: =C61*F63 -> 0 | H63: =G63/$C$5 -> 0
E64: Passiva | F64: 0 | G64: =C61*F64 -> 0 | H64: =G64/$C$5 -> 0
E65: Recuperação | F65: 0 | G65: =C61*F65 -> 0 | H65: =G65/$C$5 -> 0
E66: Expansão | F66: 0 | G66: =C61*F66 -> 0 | H66: =G66/$C$5 -> 0
E67: Total do mês | F67: =SUM(F63:F66) -> 0 | G67: =SUM(G63:G66) -> 0 | H67: =SUM(H63:H66) -> 0
B69: MÊS 6 – JUNHO | E69: ESTRATÉGIAS – JUNHO
B70: Meta Junho
E71: Estratégia | F71: Participação na meta | G71: Meta Junho por estratégia | H71: Qtdd venda mensal
E72: Ativa | F72: 1 | G72: =C70*F72 -> 0 | H72: =G72/$C$5 -> 0
E73: Passiva | F73: 0 | G73: =C70*F73 -> 0 | H73: =G73/$C$5 -> 0
E74: Recuperação | F74: 0 | G74: =C70*F74 -> 0 | H74: =G74/$C$5 -> 0
E75: Expansão | F75: 0 | G75: =C70*F75 -> 0 | H75: =G75/$C$5 -> 0
E76: Total do mês | F76: =SUM(F72:F75) -> 1 | G76: =SUM(G72:G75) -> 0 | H76: =SUM(H72:H75) -> 0
B78: MÊS 7 – JULHO | E78: ESTRATÉGIAS – JULHO
B79: Meta Julho
E80: Estratégia | F80: Participação na meta | G80: Meta Julho por estratégia | H80: Qtdd venda mensal
E81: Ativa | F81: 1 | G81: =C79*F81 -> 0 | H81: =G81/$C$5 -> 0
E82: Passiva | F82: 0 | G82: =C79*F82 -> 0 | H82: =G82/$C$5 -> 0
E83: Recuperação | F83: 0 | G83: =C79*F83 -> 0 | H83: =G83/$C$5 -> 0
E84: Expansão | F84: 0 | G84: =C79*F84 -> 0 | H84: =G84/$C$5 -> 0
E85: Total do mês | F85: =SUM(F81:F84) -> 1 | G85: =SUM(G81:G84) -> 0 | H85: =SUM(H81:H84) -> 0
B87: MÊS 8 – AGOSTO | E87: ESTRATÉGIAS – AGOSTO
B88: Meta Agosto
E89: Estratégia | F89: Participação na meta | G89: Meta Agosto por estratégia | H89: Qtdd venda mensal
E90: Ativa | F90: 1 | G90: =C88*F90 -> 0 | H90: =G90/$C$5 -> 0
E91: Passiva | F91: 0 | G91: =C88*F91 -> 0 | H91: =G91/$C$5 -> 0
E92: Recuperação | F92: 0 | G92: =C88*F92 -> 0 | H92: =G92/$C$5 -> 0
E93: Expansão | F93: 0 | G93: =C88*F93 -> 0 | H93: =G93/$C$5 -> 0
E94: Total do mês | F94: =SUM(F90:F93) -> 1 | G94: =SUM(G90:G93) -> 0 | H94: =SUM(H90:H93) -> 0
B96: MÊS 9 – SETEMBRO | E96: ESTRATÉGIAS – SETEMBRO
B97: Meta Setembro
E98: Estratégia | F98: Participação na meta | G98: Meta Setembro por estratégia | H98: Qtdd venda mensal
E99: Ativa | F99: 1 | G99: =C97*F99 -> 0 | H99: =G99/$C$5 -> 0
E100: Passiva | F100: 0 | G100: =C97*F100 -> 0 | H100: =G100/$C$5 -> 0
E101: Recuperação | F101: 0 | G101: =C97*F101 -> 0 | H101: =G101/$C$5 -> 0
E102: Expansão | F102: 0 | G102: =C97*F102 -> 0 | H102: =G102/$C$5 -> 0
E103: Total do mês | F103: =SUM(F99:F102) -> 1 | G103: =SUM(G99:G102) -> 0 | H103: =SUM(H99:H102) -> 0
B105: MÊS 10 – OUTUBRO | E105: ESTRATÉGIAS – OUTUBRO
B106: Meta Outubro
E107: Estratégia | F107: Participação na meta | G107: Meta Outubro por estratégia | H107: Qtdd venda mensal
E108: Ativa | F108: 1 | G108: =C106*F108 -> 0 | H108: =G108/$C$5 -> 0
E109: Passiva | F109: 0 | G109: =C106*F109 -> 0 | H109: =G109/$C$5 -> 0
E110: Recuperação | F110: 0 | G110: =C106*F110 -> 0 | H110: =G110/$C$5 -> 0
E111: Expansão | F111: 0 | G111: =C106*F111 -> 0 | H111: =G111/$C$5 -> 0
E112: Total do mês | F112: =SUM(F108:F111) -> 1 | G112: =SUM(G108:G111) -> 0 | H112: =SUM(H108:H111) -> 0
B114: MÊS 11 – NOVEMBRO | E114: ESTRATÉGIAS – NOVEMBRO
B115: Meta Novembro
E116: Estratégia | F116: Participação na meta | G116: Meta Novembro por estratégia | H116: Qtdd venda mensal
E117: Ativa | F117: 0 | G117: =C115*F117 -> 0 | H117: =G117/$C$5 -> 0
E118: Passiva | F118: 0.67 | G118: =C115*F118 -> 0 | H118: =G118/$C$5 -> 0
E119: Recuperação | F119: 0.16 | G119: =C115*F119 -> 0 | H119: =G119/$C$5 -> 0
E120: Expansão | F120: 0.18 | G120: =C115*F120 -> 0 | H120: =G120/$C$5 -> 0
E121: Total do mês | F121: =SUM(F117:F120) -> 1.01 | G121: =SUM(G117:G120) -> 0 | H121: =SUM(H117:H120) -> 0
B123: MÊS 12 – DEZEMBRO | E123: ESTRATÉGIAS – DEZEMBRO
B124: Meta Dezembro
E125: Estratégia | F125: Participação na meta | G125: Meta Dezembro por estratégia | H125: Qtdd venda mensal
...

Sheet Indicadores e Metas
C1: Obs: Preencha apenas os campos em amarelos, demais campos automatizados
C2: Obs: Preenchimento de alcance deve ser preenchindo nas colunas de Atingidodas semanas.
D4: EXECUÇÃO GERAL | F4: JAN | I4: SEMANA 1 | K4: SEMANA 2 | M4: SEMANA 3 | O4: SEMANA 04 | Q4: FEV | S4: SEMANA 1 | U4: SEMANA 2 | W4: SEMANA 3 | Y4: SEMANA 04 | AA4: MAR | AC4: SEMANA 1 | AE4: SEMANA 2 | AG4: SEMANA 3 | AI4: SEMANA 04 | AK4: ABR | AM4: SEMANA 1 | AO4: SEMANA 2 | AQ4: SEMANA 3 | AS4: SEMANA 04 | AU4: MAI | AW4: SEMANA 1 | AY4: SEMANA 2 | BA4: SEMANA 3 | BC4: SEMANA 04 | BE4: JUN | BG4: SEMANA 1 | BI4: SEMANA 2 | BK4: SEMANA 3 | BM4: SEMANA 04 | BO4: JUL | BQ4: SEMANA 1 | BS4: SEMANA 2 | BU4: SEMANA 3 | BW4: SEMANA 04 | BY4: AGO | CA4: SEMANA 1 | CC4: SEMANA 2 | CE4: SEMANA 3 | CG4: SEMANA 04 | CI4: SET | CK4: SEMANA 1 | CM4: SEMANA 2 | CO4: SEMANA 3 | CQ4: SEMANA 04 | CS4: OUT | CU4: SEMANA 1 | CW4: SEMANA 2 | CY4: SEMANA 3 | DA4: SEMANA 04 | DC4: NOV | DE4: SEMANA 1 | DG4: SEMANA 2 | DI4: SEMANA 3 | DK4: SEMANA 04 | DM4: DEZ | DO4: SEMANA 1 | DQ4: SEMANA 2 | DS4: SEMANA 3 | DU4: SEMANA 04
D5: Atingido | E5: Meta | F5: Atingido | G5: Meta | H5: Farol | I5: Atingido | J5: Meta | K5: Atingido | L5: Meta | M5: Atingido | N5: Meta | O5: Atingido | P5: Meta | Q5: Atingido | R5: Meta | S5: Atingido | T5: Meta | U5: Atingido | V5: Meta | W5: Atingido | X5: Meta | Y5: Atingido | Z5: Meta | AA5: Atingido | AB5: Meta | AC5: Atingido | AD5: Meta | AE5: Atingido | AF5: Meta | AG5: Atingido | AH5: Meta | AI5: Atingido | AJ5: Meta | AK5: Atingido | AL5: Meta | AM5: Atingido | AN5: Meta | AO5: Atingido | AP5: Meta | AQ5: Atingido | AR5: Meta | AS5: Atingido | AT5: Meta | AU5: Atingido | AV5: Meta | AW5: Atingido | AX5: Meta | AY5: Atingido | AZ5: Meta | BA5: Atingido | BB5: Meta | BC5: Atingido | BD5: Meta | BE5: Atingido | BF5: Meta | BG5: Atingido | BH5: Meta | BI5: Atingido | BJ5: Meta | BK5: Atingido | BL5: Meta | BM5: Atingido | BN5: Meta | BO5: Atingido | BP5: Meta | BQ5: Atingido | BR5: Meta | BS5: Atingido | BT5: Meta | BU5: Atingido | BV5: Meta | BW5: Atingido | BX5: Meta | BY5: Atingido | BZ5: Meta | CA5: Atingido | CB5: Meta | CC5: Atingido | CD5: Meta | CE5: Atingido | CF5: Meta | CG5: Atingido | CH5: Meta | CI5: Atingido | CJ5: Meta | CK5: Atingido | CL5: Meta | CM5: Atingido | CN5: Meta | CO5: Atingido | CP5: Meta | CQ5: Atingido | CR5: Meta | CS5: Atingido | CT5: Meta | CU5: Atingido | CV5: Meta | CW5: Atingido | CX5: Meta | CY5: Atingido | CZ5: Meta | DA5: Atingido | DB5: Meta | DC5: Atingido | DD5: Meta | DE5: Atingido | DF5: Meta | DG5: Atingido | DH5: Meta | DI5: Atingido | DJ5: Meta | DK5: Atingido | DL5: Meta | DM5: Atingido | DN5: Meta | DO5: Atingido | DP5: Meta | DQ5: Atingido | DR5: Meta | DS5: Atingido | DT5: Meta | DU5: Atingido | DV5: Meta
B6: TOTAL | C6: Total de cadências abertas | D6: =SUM(F6+Q6+AA6+AK6+AU6+BE6+BO6+BY6+CI6+CS6+DC6+DM6) -> 0 | E6: =SUM(G6+R6+AB6+AL6+AV6+BF6+BP6+BZ6+CJ6+CT6+DD6+DN6) -> 248.01587 | F6: =SUM(F20+F34+F48+F62) -> 0 | G6: =SUM(G20+G34+G48+G62) -> 0 | H6: =F6/G6 -> #DIV/0! | I6: =SUM(I20+I34+I48+I62) -> 0 | J6: =SUM(J20+J34+J48+J62) -> 0 | K6: =SUM(K20+K34+K48+K62) -> 0 | L6: =SUM(L20+L34+L48+L62) -> 0 | M6: =SUM(M20+M34+M48+M62) -> 0 | N6: =SUM(N20+N34+N48+N62) -> 0 | O6: =SUM(O20+O34+O48+O62) -> 0 | P6: =SUM(P20+P34+P48+P62) -> 0 | ... DV6: =SUM(DV20+DV34+DV48+DV62) -> 0
C7: % Conversão em Lead Conectado | D7: =D8/D6 -> #DIV/0! | E7: =E8/E6 -> 0.15 | F7: =F8/F6 -> #DIV/0! | G7: =G8/G6 -> #DIV/0! | H7: - | I7: =I8/I6 -> #DIV/0! | J7: =J8/J6 -> #DIV/0! | K7: =K8/K6 -> #DIV/0! | L7: =L8/L6 -> #DIV/0! | M7: =M8/M6 -> #DIV/0! | N7: =N8/N6 -> #DIV/0! | O7: =O8/O6 -> #DIV/0! | P7: =P8/P6 -> #DIV/0! | ... DV7: =DV8/DV6 -> #DIV/0!
C8: Total de leads conectados | D8: =SUM(F8+Q8+AA8+AK8+AU8+BE8+BO8+BY8+CI8+CS8+DC8+DM8) -> 0 | E8: =SUM(G8+R8+AB8+AL8+AV8+BF8+BP8+BZ8+CJ8+CT8+DD8+DN8) -> 37.202381 | F8: =SUM(F22+F36+F50+F64) -> 0 | G8: =SUM(G22+G36+G50+G64) -> 0 | H8: =G8/F8 -> #DIV/0! | I8: =SUM(I22+I36+I50+I64) -> 0 | J8: =SUM(J22+J36+J50+J64) -> 0 | K8: =SUM(K22+K36+K50+K64) -> 0 | L8: =SUM(L22+L36+L50+L64) -> 0 | M8: =SUM(M22+M36+M50+M64) -> 0 | N8: =SUM(N22+N36+N50+N64) -> 0 | O8: =SUM(O22+O36+O50+O64) -> 0 | P8: =SUM(P22+P36+P50+P64) -> 0 | ... DV8: =SUM(DV22+DV36+DV50+DV64) -> 0
C9: % Conversão em Reunião agendada | D9: =D10/D8 -> #DIV/0! | E9: =E10/E8 -> 0.2 | F9: =F10/F8 -> #DIV/0! | G9: =G10/G8 -> #DIV/0! | H9: - | I9: =I10/I8 -> #DIV/0! | J9: =J10/J8 -> #DIV/0! | K9: =K10/K8 -> #DIV/0! | L9: =L10/L8 -> #DIV/0! | M9: =M10/M8 -> #DIV/0! | N9: =N10/N8 -> #DIV/0! | O9: =O10/O8 -> #DIV/0! | P9: =P10/P8 -> #DIV/0! | ... DV9: =DV10/DV8 -> #DIV/0!
C10: Total de reuniões agendadas | D10: =SUM(F10+Q10+AA10+AK10+AU10+BE10+BO10+BY10+CI10+CS10+DC10+DM10) -> 0 | E10: =SUM(G10+R10+AB10+AL10+AV10+BF10+BP10+BZ10+CJ10+CT10+DD10+DN10) -> 7.4404762 | F10: =SUM(F24+F38+F52+F66) -> 0 | G10: =SUM(G24+G38+G52+G66) -> 0 | H10: =G10/F10 -> #DIV/0! | I10: =SUM(I24+I38+I52+I66) -> 0 | J10: =SUM(J24+J38+J52+J66) -> 0 | K10: =SUM(K24+K38+K52+K66) -> 0 | L10: =SUM(L24+L38+L52+L66) -> 0 | M10: =SUM(M24+M38+M52+M66) -> 0 | N10: =SUM(N24+N38+N52+N66) -> 0 | O10: =SUM(O24+O38+O52+O66) -> 0 | P10: =SUM(P24+P38+P52+P66) -> 0 | ... DV10: =SUM(DV24+DV38+DV52+DV66) -> 0
C11: % de reunião realizada | D11: =D12/D10 -> #DIV/0! | E11: =E12/E10 -> 0.8 | F11: =F12/F10 -> #DIV/0! | G11: =G12/G10 -> #DIV/0! | H11: - | I11: =I12/I10 -> #DIV/0! | J11: =J12/J10 -> #DIV/0! | K11: =K12/K10 -> #DIV/0! | L11: =L12/L10 -> #DIV/0! | M11: =M12/M10 -> #DIV/0! | N11: =N12/N10 -> #DIV/0! | O11: =O12/O10 -> #DIV/0! | P11: =P12/P10 -> #DIV/0! | ... DV11: =DV12/DV10 -> #DIV/0!
C12: Total de reuniões realizadas | D12: =SUM(F12+Q12+AA12+AK12+AU12+BE12+BO12+BY12+CI12+CS12+DC12+DM12) -> 0 | E12: =SUM(G12+R12+AB12+AL12+AV12+BF12+BP12+BZ12+CJ12+CT12+DD12+DN12) -> 5.952381 | F12: =SUM(F26+F40+F54+F68) -> 0 | G12: =SUM(G26+G40+G54+G68) -> 0 | H12: =G12/F12 -> #DIV/0! | I12: =SUM(I26+I40+I54+I68) -> 0 | J12: =SUM(J26+J40+J54+J68) -> 0 | K12: =SUM(K26+K40+K54+K68) -> 0 | L12: =SUM(L26+L40+L54+L68) -> 0 | M12: =SUM(M26+M40+M54+M68) -> 0 | N12: =SUM(N26+N40+N54+N68) -> 0 | O12: =SUM(O26+O40+O54+O68) -> 0 | P12: =SUM(P26+P40+P54+P68) -> 0 | ... DV12: =SUM(DV26+DV40+DV54+DV68) -> 0
C13: % de propostas apresentadas | D13: =D14/D12 -> #DIV/0! | E13: =E14/E12 -> 0.7 | F13: =F14/F12 -> #DIV/0! | G13: =G14/G12 -> #DIV/0! | H13: - | I13: =I14/I12 -> #DIV/0! | J13: =J14/J12 -> #DIV/0! | K13: =K14/K12 -> #DIV/0! | L13: =L14/L12 -> #DIV/0! | M13: =M14/M12 -> #DIV/0! | N13: =N14/N12 -> #DIV/0! | O13: =O14/O12 -> #DIV/0! | P13: =P14/P12 -> #DIV/0! | ... DV13: =DV14/DV12 -> #DIV/0!
C14: Total de propostas apresentadas | D14: =SUM(F14+Q14+AA14+AK14+AU14+BE14+BO14+BY14+CI14+CS14+DC14+DM14) -> 0 | E14: =SUM(G14+R14+AB14+AL14+AV14+BF14+BP14+BZ14+CJ14+CT14+DD14+DN14) -> 4.1666667 | F14: =SUM(F28+F42+F56+F70) -> 0 | G14: =SUM(G28+G42+G56+G70) -> 0 | H14: =G14/F14 -> #DIV/0! | I14: =SUM(I28+I42+I56+I70) -> 0 | J14: =SUM(J28+J42+J56+J70) -> 0 | K14: =SUM(K28+K42+K56+K70) -> 0 | L14: =SUM(L28+L42+L56+L70) -> 0 | M14: =SUM(M28+M42+M56+M70) -> 0 | N14: =SUM(N28+N42+N56+N70) -> 0 | O14: =SUM(O28+O42+O56+O70) -> 0 | P14: =SUM(P28+P42+P56+P70) -> 0 | ... DV14: =SUM(DV28+DV42+DV56+DV70) -> 0
C15: % de fechamento | D15: =D16/D14 -> #DIV/0! | E15: =E16/E14 -> 0.4 | F15: =F16/F14 -> #DIV/0! | G15: =G16/G14 -> #DIV/0! | H15: - | I15: =I16/I14 -> #DIV/0! | J15: =J16/J14 -> #DIV/0! | K15: =K16/K14 -> #DIV/0! | L15: =L16/L14 -> #DIV/0! | M15: =M16/M14 -> #DIV/0! | N15: =N16/N14 -> #DIV/0! | O15: =O16/O14 -> #DIV/0! | P15: =P16/P14 -> #DIV/0! | ... DV15: =DV16/DV14 -> #DIV/0!
C16: Total de propostas fechadas | D16: =SUM(F16+Q16+AA16+AK16+AU16+BE16+BO16+BY16+CI16+CS16+DC16+DM16) -> 0 | E16: =SUM(G16+R16+AB16+AL16+AV16+BF16+BP16+BZ16+CJ16+CT16+DD16+DN16) -> 1.6666667 | F16: =SUM(F30+F44+F58+F72) -> 0 | G16: =SUM(G30+G44+G58+G72) -> 0 | H16: =G16/F16 -> #DIV/0! | I16: =SUM(I30+I44+I58+I72) -> 0 | J16: =SUM(J30+J44+J58+J72) -> 0 | K16: =SUM(K30+K44+K58+K72) -> 0 | L16: =SUM(L30+L44+L58+L72) -> 0 | M16: =SUM(M30+M44+M58+M72) -> 0 | N16: =SUM(N30+N44+N58+N72) -> 0 | O16: =SUM(O30+O44+O58+O72) -> 0 | P16: =SUM(P30+P44+P58+P72) -> 0 | ... DV16: =SUM(DV30+DV44+DV58+DV72) -> 0
C17: Total de faturamento | D17: =SUM(F17+Q17+AA17+AK17+AU17+BE17+BO17+BY17+CI17+CS17+DC17+DM17) -> 0 | E17: =SUM(G17+R17+AB17+AL17+AV17+BF17+BP17+BZ17+CJ17+CT17+DD17+DN17) -> 4166.6667 | F17: =SUM(F31+F45+F59+F73) -> 0 | G17: =SUM(G31+G45+G59+G73) -> 0 | H17: =G17/F17 -> #DIV/0! | I17: =SUM(I31+I45+I59+I73) -> 0 | J17: =SUM(J31+J45+J59+J73) -> 0 | K17: =SUM(K31+K45+K59+K73) -> 0 | L17: =SUM(L31+L45+L59+L73) -> 0 | M17: =SUM(M31+M45+M59+M73) -> 0 | N17: =SUM(N31+N45+N59+N73) -> 0 | O17: =SUM(O31+O45+O59+O73) -> 0 | P17: =SUM(P31+P45+P59+P73) -> 0 | ... DV17: =SUM(DV31+DV45+DV59+DV73) -> 0
C18: Ticket médio | D18: =D17/D16 -> #DIV/0! | E18: =E17/E16 -> 2500 | F18: =F17/F16 -> #DIV/0! | G18: =SUM(G32+G46+G60+G74) -> 10000 | H18: =G18/F18 -> #DIV/0! | I18: =SUM(I32+I46+I60+I74) -> #DIV/0! | J18: =SUM(J32+J46+J60+J74) -> 10000 | K18: =SUM(K32+K46+K60+K74) -> #DIV/0! | L18: =SUM(L32+L46+L60+L74) -> 10000 | M18: =SUM(M32+M46+M60+M74) -> #DIV/0! | N18: =SUM(N32+N46+N60+N74) -> 10000 | O18: =SUM(O32+O46+O60+O74) -> #DIV/0! | P18: =SUM(P32+P46+P60+P74) -> 10000 | Q18: =Q17/Q16 -> #DIV/0! | R18: =SUM(R32+R46+R60+R74) -> 10000 | S18: =SUM(S32+S46+S60+S74) -> #DIV/0! | T18: =SUM(T32+T46+T60+T74) -> 10000 | U18: =SUM(U32+U46+U60+U74) -> #DIV/0! | V18: =SUM(V32+V46+V60+V74) -> 10000 | W18: =SUM(W32+W46+W60+W74) -> #DIV/0! | X18: =SUM(X32+X46+X60+X74) -> 10000 | Y18: =SUM(Y32+Y46+Y60+Y74) -> #DIV/0! | Z18: =SUM(Z32+Z46+Z60+Z74) -> 10000 | AA18: =AA17/AA16 -> #DIV/0! | AB18: =SUM(AB32+AB46+AB60+AB74) -> 10000 | AC18: =SUM(AC32+AC46+AC60+AC74) -> #DIV/0! | AD18: =SUM(AD32+AD46+AD60+AD74) -> 10000 | AE18: =SUM(AE32+AE46+AE60+AE74) -> #DIV/0! | AF18: =SUM(AF32+AF46+AF60+AF74) -> 10000 | AG18: =SUM(AG32+AG46+AG60+AG74) -> #DIV/0! | AH18: =SUM(AH32+AH46+AH60+AH74) -> 10000 | AI18: =SUM(AI32+AI46+AI60+AI74) -> #DIV/0! | AJ18: =SUM(AJ32+AJ46+AJ60+AJ74) -> 10000 | AK18: =AK17/AK16 -> #DIV/0! | AL18: =SUM(AL32+AL46+AL60+AL74) -> 10000 | AM18: =SUM(AM32+AM46+AM60+AM74) -> #DIV/0! | AN18: =SUM(AN32+AN46+AN60+AN74) -> 10000 | AO18: =SUM(AO32+AO46+AO60+AO74) -> #DIV/0! | AP18: =SUM(AP32+AP46+AP60+AP74) -> 10000 | AQ18: =SUM(AQ32+AQ46+AQ60+AQ74) -> #DIV/0! | AR18: =SUM(AR32+AR46+AR60+AR74) -> 10000 | AS18: =SUM(AS32+AS46+AS60+AS74) -> #DIV/0! | AT18: =SUM(AT32+AT46+AT60+AT74) -> 10000 | AU18: =AU17/AU16 -> #DIV/0! | AV18: =SUM(AV32+AV46+AV60+AV74) -> 10000 | AW18: =SUM(AW32+AW46+AW60+AW74) -> #DIV/0! | AX18: =SUM(AX32+AX46+AX60+AX74) -> 10000 | AY18: =SUM(AY32+AY46+AY60+AY74) -> #DIV/0! | AZ18: =SUM(AZ32+AZ46+AZ60+AZ74) -> 10000 | BA18: =SUM(BA32+BA46+BA60+BA74) -> #DIV/0! | BB18: =SUM(BB32+BB46+BB60+BB74) -> 10000 | BC18: =SUM(BC32+BC46+BC60+BC74) -> #DIV/0! | BD18: =SUM(BD32+BD46+BD60+BD74) -> 10000 | BE18: =BE17/BE16 -> #DIV/0! | BF18: ='Dados da Operação'!$C$5 -> 2500 | BG18: =SUM(BG32+BG46+BG60+BG74) -> #DIV/0! | BH18: ='Dados da Operação'!$C$5 -> 2500 | BI18: =SUM(BI32+BI46+BI60+BI74) -> #DIV/0! | BJ18: ='Dados da Operação'!$C$5 -> 2500 | BK18: =SUM(BK32+BK46+BK60+BK74) -> #DIV/0! | BL18: ='Dados da Operação'!$C$5 -> 2500 | BM18: =SUM(BM32+BM46+BM60+BM74) -> #DIV/0! | BN18: ='Dados da Operação'!$C$5 -> 2500 | BO18: =BO17/BO16 -> #DIV/0! | BP18: ='Dados da Operação'!$C$5 -> 2500 | BQ18: =SUM(BQ32+BQ46+BQ60+BQ74) -> #DIV/0! | BR18: =SUM(BR32+BR46+BR60+BR74) -> 10000 | BS18: =SUM(BS32+BS46+BS60+BS74) -> #DIV/0! | BT18: =SUM(BT32+BT46+BT60+BT74) -> 10000 | BU18: =SUM(BU32+BU46+BU60+BU74) -> #DIV/0! | BV18: =SUM(BV32+BV46+BV60+BV74) -> 10000 | BW18: =SUM(BW32+BW46+BW60+BW74) -> #DIV/0! | BX18: =SUM(BX32+BX46+BX60+BX74) -> 10000 | BY18: =BY17/BY16 -> #DIV/0! | BZ18: ='Dados da Operação'!$C$5 -> 2500 | CA18: =SUM(CA32+CA46+CA60+CA74) -> #DIV/0! | CB18: =SUM(CB32+CB46+CB60+CB74) -> 10000 | CC18: =SUM(CC32+CC46+CC60+CC74) -> #DIV/0! | CD18: =SUM(CD32+CD46+CD60+CD74) -> 10000 | CE18: =SUM(CE32+CE46+CE60+CE74) -> #DIV/0! | CF18: =SUM(CF32+CF46+CF60+CF74) -> 10000 | CG18: =SUM(CG32+CG46+CG60+CG74) -> #DIV/0! | CH18: =SUM(CH32+CH46+CH60+CH74) -> 10000 | CI18: =CI17/CI16 -> #DIV/0! | CJ18: ='Dados da Operação'!$C$5 -> 2500 | CK18: =SUM(CK32+CK46+CK60+CK74) -> #DIV/0! | CL18: =SUM(CL32+CL46+CL60+CL74) -> 10000 | CM18: =SUM(CM32+CM46+CM60+CM74) -> #DIV/0! | CN18: =SUM(CN32+CN46+CN60+CN74) -> 10000 | CO18: =SUM(CO32+CO46+CO60+CO74) -> #DIV/0! | CP18: =SUM(CP32+CP46+CP60+CP74) -> 10000 | CQ18: =SUM(CQ32+CQ46+CQ60+CQ74) -> #DIV/0! | CR18: =SUM(CR32+CR46+CR60+CR74) -> 10000 | CS18: =CS17/CS16 -> #DIV/0! | CT18: ='Dados da Operação'!$C$5 -> 2500 | CU18: =SUM(CU32+CU46+CU60+CU74) -> #DIV/0! | CV18: =SUM(CV32+CV46+CV60+CV74) -> 10000 | CW18: =SUM(CW32+CW46+CW60+CW74) -> #DIV/0! | CX18: =SUM(CX32+CX46+CX60+CX74) -> 10000 | CY18: =SUM(CY32+CY46+CY60+CY74) -> #DIV/0! | CZ18: =SUM(CZ32+CZ46+CZ60+CZ74) -> 10000 | DA18: =SUM(DA32+DA46+DA60+DA74) -> #DIV/0! | DB18: =SUM(DB32+DB46+DB60+DB74) -> 10000 | DC18: =DC17/DC16 -> #DIV/0! | DD18: ='Dados da Operação'!$C$5 -> 2500 | DE18: =SUM(DE32+DE46+DE60+DE74) -> #DIV/0! | DF18: =SUM(DF32+DF46+DF60+DF74) -> 10000 | DG18: =SUM(DG32+DG46+DG60+DG74) -> #DIV/0! | DH18: =SUM(DH32+DH46+DH60+DH74) -> 10000 | DI18: =SUM(DI32+DI46+DI60+DI74) -> #DIV/0! | DJ18: =SUM(DJ32+DJ46+DJ60+DJ74) -> 10000 | DK18: =SUM(DK32+DK46+DK60+DK74) -> #DIV/0! | DL18: =SUM(DL32+DL46+DL60+DL74) -> 10000 | DM18: =DM17/DM16 -> #DIV/0! | DN18: ='Dados da Operação'!$C$5 -> 2500 | DO18: =SUM(DO32+DO46+DO60+DO74) -> #DIV/0! | DP18: =SUM(DP32+DP46+DP60+DP74) -> 10000 | DQ18: =SUM(DQ32+DQ46+DQ60+DQ74) -> #DIV/0! | DR18: =SUM(DR32+DR46+DR60+DR74) -> 10000 | DS18: =SUM(DS32+DS46+DS60+DS74) -> #DIV/0! | DT18: =SUM(DT32+DT46+DT60+DT74) -> 10000 | DU18: =SUM(DU32+DU46+DU60+DU74) -> #DIV/0! | DV18: =SUM(DV32+DV46+DV60+DV74) -> 10000
B20: OUTBOUND | C20: Total de cadências abertas | D20: =SUM(F20+Q20+AA20+AK20+AU20+BE20+BO20+BY20+CI20+CS20+DC20+DM20) -> 0 | E20: =SUM(G20+R20+AB20+AL20+AV20+BF20+BP20+BZ20+CJ20+CT20+DD20+DN20) -> 248.01587 | F20: =SUM(I20+K20+M20+O20) -> 0 | G20: =G22/G21 -> 0 | H20: =F20/G20 -> #DIV/0! | J20: =G20/4 -> 0 | L20: =G20/4 -> 0 | N20: =G20/4 -> 0 | P20: =G20/4 -> 0 | Q20: =SUM(S20+U20+W20+Y20) -> 0 | T20: =R20/4 -> 0 | V20: =R20/4 -> 0 | X20: =R20/4 -> 0 | Z20: =R20/4 -> 0 | AA20: =SUM(AC20+AE20+AG20+AI20) -> 0 | AD20: =AB20/4 -> 0 | AF20: =AB20/4 -> 0 | AH20: =AB20/4 -> 0 | AJ20: =AB20/4 -> 0 | AK20: =SUM(AM20+AO20+AQ20+AS20) -> 0 | AN20: =AL20/4 -> 0 | AP20: =AL20/4 -> 0 | AR20: =AL20/4 -> 0 | AT20: =AL20/4 -> 0 | AU20: =SUM(AW20+AY20+BA20+BC20) -> 0 | AX20: =AV20/4 -> 0 | AZ20: =AV20/4 -> 0 | BB20: =AV20/4 -> 0 | BD20: =AV20/4 -> 0 | BE20: =SUM(BG20+BI20+BK20+BM20) -> 0 | BF20: =BF22/BF21 -> 248.01587 | BH20: =BF20/4 -> 62.003968 | BJ20: =BF20/4 -> 62.003968 | BL20: =BF20/4 -> 62.003968 | BN20: =BF20/4 -> 62.003968 | BO20: =SUM(BQ20+BS20+BU20+BW20) -> 0 | BR20: =BP20/4 -> 0 | BT20: =BP20/4 -> 0 | BV20: =BP20/4 -> 0 | BX20: =BP20/4 -> 0 | BY20: =SUM(CA20+CC20+CE20+CG20) -> 0 | CB20: =BZ20/4 -> 0 | CD20: =BZ20/4 -> 0 | CF20: =BZ20/4 -> 0 | CH20: =BZ20/4 -> 0 | CI20: =SUM(CK20+CM20+CO20+CQ20) -> 0 | CL20: =CJ20/4 -> 0 | CN20: =CJ20/4 -> 0 | CP20: =CJ20/4 -> 0 | CR20: =CJ20/4 -> 0 | CS20: =SUM(CU20+CW20+CY20+DA20) -> 0 | CV20: =CT20/4 -> 0 | CX20: =CT20/4 -> 0 | CZ20: =CT20/4 -> 0 | DB20: =CT20/4 -> 0 | DC20: =SUM(DE20+DG20+DI20+DK20) -> 0 | DF20: =DD20/4 -> 0 | DH20: =DD20/4 -> 0 | DJ20: =DD20/4 -> 0 | DL20: =DD20/4 -> 0 | DM20: =SUM(DO20+DQ20+DS20+DU20) -> 0 | DP20: =DN20/4 -> 0 | DR20: =DN20/4 -> 0 | DT20: =DN20/4 -> 0 | DV20: =DN20/4 -> 0
C21: % Conversão em Lead Conectado | D21: =D22/D20 -> #DIV/0! | E21: =E22/E20 -> 0.15 | F21: =F22/F20 -> #DIV/0! | G21: 0.3 | H21: - | I21: =I22/I20 -> #DIV/0! | J21: =G21 -> 0.3 | K21: =K22/K20 -> #DIV/0! | L21: =G21 -> 0.3 | M21: =M22/M20 -> #DIV/0! | N21: =G21 -> 0.3 | O21: =O22/O20 -> #DIV/0! | P21: =G21 -> 0.3 | Q21: =Q22/Q20 -> #DIV/0! | S21: =S22/S20 -> #DIV/0! | T21: =R21 | U21: =U22/U20 -> #DIV/0! | V21: =R21 | W21: =W22/W20 -> #DIV/0! | X21: =R21 | Y21: =Y22/Y20 -> #DIV/0! | Z21: =R21 | AA21: =AA22/AA20 -> #DIV/0! | AC21: =AC22/AC20 -> #DIV/0! | AD21: =AB21 | AE21: =AE22/AE20 -> #DIV/0! | AF21: =AB21 | AG21: =AG22/AG20 -> #DIV/0! | AH21: =AB21 | AI21: =AI22/AI20 -> #DIV/0! | AJ21: =AB21 | AK21: =AK22/AK20 -> #DIV/0! | AM21: =AM22/AM20 -> #DIV/0! | AN21: =AL21 | AO21: =AO22/AO20 -> #DIV/0! | AP21: =AL21 | AQ21: =AQ22/AQ20 -> #DIV/0! | AR21: =AL21 | AS21: =AS22/AS20 -> #DIV/0! | AT21: =AL21 | AU21: =AU22/AU20 -> #DIV/0! | AW21: =AW22/AW20 -> #DIV/0! | AX21: =AV21 | AY21: =AY22/AY20 -> #DIV/0! | AZ21: =AV21 | BA21: =BA22/BA20 -> #DIV/0! | BB21: =AV21 | BC21: =BC22/BC20 -> #DIV/0! | BD21: =AV21 | BE21: =BE22/BE20 -> #DIV/0! | BF21: 0.15 | BG21: =BG22/BG20 -> #DIV/0! | BH21: =BF21 -> 0.15 | BI21: =BI22/BI20 -> #DIV/0! | BJ21: =BF21 -> 0.15 | BK21: =BK22/BK20 -> #DIV/0! | BL21: =BF21 -> 0.15 | BM21: =BM22/BM20 -> #DIV/0! | BN21: =BF21 -> 0.15 | BO21: =BO22/BO20 -> #DIV/0! | BQ21: =BQ22/BQ20 -> #DIV/0! | BR21: =BP21 | BS21: =BS22/BS20 -> #DIV/0! | BT21: =BP21 | BU21: =BU22/BU20 -> #DIV/0! | BV21: =BP21 | BW21: =BW22/BW20 -> #DIV/0! | BX21: =BP21 | BY21: =BY22/BY20 -> #DIV/0! | CA21: =CA22/CA20 -> #DIV/0! | CB21: =BZ21 | CC21: =CC22/CC20 -> #DIV/0! | CD21: =BZ21 | CE21: =CE22/CE20 -> #DIV/0! | CF21: =BZ21 | CG21: =CG22/CG20 -> #DIV/0! | CH21: =BZ21 | CI21: =CI22/CI20 -> #DIV/0! | CK21: =CK22/CK20 -> #DIV/0! | CL21: =CJ21 | CM21: =CM22/CM20 -> #DIV/0! | CN21: =CJ21 | CO21: =CO22/CO20 -> #DIV/0! | CP21: =CJ21 | CQ21: =CQ22/CQ20 -> #DIV/0! | CR21: =CJ21 | CS21: =CS22/CS20 -> #DIV/0! | CU21: =CU22/CU20 -> #DIV/0! | CV21: =CT21 | CW21: =CW22/CW20 -> #DIV/0! | CX21: =CT21 | CY21: =CY22/CY20 -> #DIV/0! | CZ21: =CT21 | DA21: =DA22/DA20 -> #DIV/0! | DB21: =CT21 | DC21: =DC22/DC20 -> #DIV/0! | DE21: =DE22/DE20 -> #DIV/0! | DF21: =DD21 | DG21: =DG22/DG20 -> #DIV/0! | DH21: =DD21 | DI21: =DI22/DI20 -> #DIV/0! | DJ21: =DD21 | DK21: =DK22/DK20 -> #DIV/0! | DL21: =DD21 | DM21: =DM22/DM20 -> #DIV/0! | DO21: =DO22/DO20 -> #DIV/0! | DP21: =DN21 | DQ21: =DQ22/DQ20 -> #DIV/0! | DR21: =DN21 | DS21: =DS22/DS20 -> #DIV/0! | DT21: =DN21 | DU21: =DU22/DU20 -> #DIV/0! | DV21: =DN21
C22: Total de leads conectados | D22: =SUM(F22+Q22+AA22+AK22+AU22+BE22+BO22+BY22+CI22+CS22+DC22+DM22) -> 0 | E22: =SUM(G22+R22+AB22+AL22+AV22+BF22+BP22+BZ22+CJ22+CT22+DD22+DN22) -> 37.202381 | F22: =SUM(I22+K22+M22+O22) -> 0 | G22: =G24/G23 -> 0 | H22: =G22/F22 -> #DIV/0! | J22: =G22/4 -> 0 | L22: =G22/4 -> 0 | N22: =G22/4 -> 0 | P22: =G22/4 -> 0 | Q22: =SUM(S22+U22+W22+Y22) -> 0 | T22: =R22/4 -> 0 | V22: =R22/4 -> 0 | X22: =R22/4 -> 0 | Z22: =R22/4 -> 0 | AA22: =SUM(AC22+AE22+AG22+AI22) -> 0 | AD22: =AB22/4 -> 0 | AF22: =AB22/4 -> 0 | AH22: =AB22/4 -> 0 | AJ22: =AB22/4 -> 0 | AK22: =SUM(AM22+AO22+AQ22+AS22) -> 0 | AN22: =AL22/4 -> 0 | AP22: =AL22/4 -> 0 | AR22: =AL22/4 -> 0 | AT22: =AL22/4 -> 0 | AU22: =SUM(AW22+AY22+BA22+BC22) -> 0 | AX22: =AV22/4 -> 0 | AZ22: =AV22/4 -> 0 | BB22: =AV22/4 -> 0 | BD22: =AV22/4 -> 0 | BE22: =SUM(BG22+BI22+BK22+BM22) -> 0 | BF22: =BF24/BF23 -> 37.202381 | BH22: =BF22/4 -> 9.3005952 | BJ22: =BF22/4 -> 9.3005952 | BL22: =BF22/4 -> 9.3005952 | BN22: =BF22/4 -> 9.3005952 | BO22: =SUM(BQ22+BS22+BU22+BW22) -> 0 | BR22: =BP22/4 -> 0 | BT22: =BP22/4 -> 0 | BV22: =BP22/4 -> 0 | BX22: =BP22/4 -> 0 | BY22: =SUM(CA22+CC22+CE22+CG22) -> 0 | CB22: =BZ22/4 -> 0 | CD22: =BZ22/4 -> 0 | CF22: =BZ22/4 -> 0 | CH22: =BZ22/4 -> 0 | CI22: =SUM(CK22+CM22+CO22+CQ22) -> 0 | CL22: =CJ22/4 -> 0 | CN22: =CJ22/4 -> 0 | CP22: =CJ22/4 -> 0 | CR22: =CJ22/4 -> 0 | CS22: =SUM(CU22+CW22+CY22+DA22) -> 0 | CV22: =CT22/4 -> 0 | CX22: =CT22/4 -> 0 | CZ22: =CT22/4 -> 0 | DB22: =CT22/4 -> 0 | DC22: =SUM(DE22+DG22+DI22+DK22) -> 0 | DF22: =DD22/4 -> 0 | DH22: =DD22/4 -> 0 | DJ22: =DD22/4 -> 0 | DL22: =DD22/4 -> 0 | DM22: =SUM(DO22+DQ22+DS22+DU22) -> 0 | DP22: =DN22/4 -> 0 | DR22: =DN22/4 -> 0 | DT22: =DN22/4 -> 0 | DV22: =DN22/4 -> 0
C23: % Conversão em Reunião agendada | D23: =D24/D22 -> #DIV/0! | E23: =E24/E22 -> 0.2 | F23: =F24/F22 -> #DIV/0! | G23: 0.3 | H23: - | I23: =I24/I22 -> #DIV/0! | J23: =G23 -> 0.3 | K23: =K24/K22 -> #DIV/0! | L23: =G23 -> 0.3 | M23: =M24/M22 -> #DIV/0! | N23: =G23 -> 0.3 | O23: =O24/O22 -> #DIV/0! | P23: =G23 -> 0.3 | Q23: =Q24/Q22 -> #DIV/0! | S23: =S24/S22 -> #DIV/0! | T23: =R23 | U23: =U24/U22 -> #DIV/0! | V23: =R23 | W23: =W24/W22 -> #DIV/0! | X23: =R23 | Y23: =Y24/Y22 -> #DIV/0! | Z23: =R23 | AA23: =AA24/AA22 -> #DIV/0! | AC23: =AC24/AC22 -> #DIV/0! | AD23: =AB23 | AE23: =AE24/AE22 -> #DIV/0! | AF23: =AB23 | AG23: =AG24/AG22 -> #DIV/0! | AH23: =AB23 | AI23: =AI24/AI22 -> #DIV/0! | AJ23: =AB23 | AK23: =AK24/AK22 -> #DIV/0! | AM23: =AM24/AM22 -> #DIV/0! | AN23: =AL23 | AO23: =AO24/AO22 -> #DIV/0! | AP23: =AL23 | AQ23: =AQ24/AQ22 -> #DIV/0! | AR23: =AL23 | AS23: =AS24/AS22 -> #DIV/0! | AT23: =AL23 | AU23: =AU24/AU22 -> #DIV/0! | AW23: =AW24/AW22 -> #DIV/0! | AX23: =AV23 | AY23: =AY24/AY22 -> #DIV/0! | AZ23: =AV23 | BA23: =BA24/BA22 -> #DIV/0! | BB23: =AV23 | BC23: =BC24/BC22 -> #DIV/0! | BD23: =AV23 | BE23: =BE24/BE22 -> #DIV/0! | BF23: 0.2 | BG23: =BG24/BG22 -> #DIV/0! | BH23: =BF23 -> 0.2 | BI23: =BI24/BI22 -> #DIV/0! | BJ23: =BF23 -> 0.2 | BK23: =BK24/BK22 -> #DIV/0! | BL23: =BF23 -> 0.2 | BM23: =BM24/BM22 -> #DIV/0! | BN23: =BF23 -> 0.2 | BO23: =BO24/BO22 -> #DIV/0! | BQ23: =BQ24/BQ22 -> #DIV/0! | BR23: =BP23 | BS23: =BS24/BS22 -> #DIV/0! | BT23: =BP23 | BU23: =BU24/BU22 -> #DIV/0! | BV23: =BP23 | BW23: =BW24/BW22 -> #DIV/0! | BX23: =BP23 | BY23: =BY24/BY22 -> #DIV/0! | CA23: =CA24/CA22 -> #DIV/0! | CB23: =BZ23 | CC23: =CC24/CC22 -> #DIV/0! | CD23: =BZ23 | CE23: =CE24/CE22 -> #DIV/0! | CF23: =BZ23 | CG23: =CG24/CG22 -> #DIV/0! | CH23: =BZ23 | CI23: =CI24/CI22 -> #DIV/0! | CK23: =CK24/CK22 -> #DIV/0! | CL23: =CJ23 | CM23: =CM24/CM22 -> #DIV/0! | CN23: =CJ23 | CO23: =CO24/CO22 -> #DIV/0! | CP23: =CJ23 | CQ23: =CQ24/CQ22 -> #DIV/0! | CR23: =CJ23 | CS23: =CS24/CS22 -> #DIV/0! | CU23: =CU24/CU22 -> #DIV/0! | CV23: =CT23 | CW23: =CW24/CW22 -> #DIV/0! | CX23: =CT23 | CY23: =CY24/CY22 -> #DIV/0! | CZ23: =CT23 | DA23: =DA24/DA22 -> #DIV/0! | DB23: =CT23 | DC23: =DC24/DC22 -> #DIV/0! | DE23: =DE24/DE22 -> #DIV/0! | DF23: =DD23 | DG23: =DG24/DG22 -> #DIV/0! | DH23: =DD23 | DI23: =DI24/DI22 -> #DIV/0! | DJ23: =DD23 | DK23: =DK24/DK22 -> #DIV/0! | DL23: =DD23 | DM23: =DM24/DM22 -> #DIV/0! | DO23: =DO24/DO22 -> #DIV/0! | DP23: =DN23 | DQ23: =DQ24/DQ22 -> #DIV/0! | DR23: =DN23 | DS23: =DS24/DS22 -> #DIV/0! | DT23: =DN23 | DU23: =DU24/DU22 -> #DIV/0! | DV23: =DN23
C24: Total de reuniões agendadas | D24: =SUM(F24+Q24+AA24+AK24+AU24+BE24+BO24+BY24+CI24+CS24+DC24+DM24) -> 0 | E24: =SUM(G24+R24+AB24+AL24+AV24+BF24+BP24+BZ24+CJ24+CT24+DD24+DN24) -> 7.4404762 | F24: =SUM(I24+K24+M24+O24) -> 0 | G24: =G26/G25 -> 0 | H24: =G24/F24 -> #DIV/0! | J24: =G24/4 -> 0 | L24: =G24/4 -> 0 | N24: =G24/4 -> 0 | P24: =G24/4 -> 0 | Q24: =SUM(S24+U24+W24+Y24) -> 0 | T24: =R24/4 -> 0 | V24: =R24/4 -> 0 | X24: =R24/4 -> 0 | Z24: =R24/4 -> 0 | AA24: =SUM(AC24+AE24+AG24+AI24) -> 0 | AD24: =AB24/4 -> 0 | AF24: =AB24/4 -> 0 | AH24: =AB24/4 -> 0 | AJ24: =AB24/4 -> 0 | AK24: =SUM(AM24+AO24+AQ24+AS24) -> 0 | AN24: =AL24/4 -> 0 | AP24: =AL24/4 -> 0 | AR24: =AL24/4 -> 0 | AT24: =AL24/4 -> 0 | AU24: =SUM(AW24+AY24+BA24+BC24) -> 0 | AX24: =AV24/4 -> 0 | AZ24: =AV24/4 -> 0 | BB24: =AV24/4 -> 0 | BD24: =AV24/4 -> 0 | BE24: =SUM(BG24+BI24+BK24+BM24) -> 0 | BF24: =BF26/BF25 -> 7.4404762 | BH24: =BF24/4 -> 1.860119 | BJ24: =BF24/4 -> 1.860119 | BL24: =BF24/4 -> 1.860119 | BN24: =BF24/4 -> 1.860119 | BO24: =SUM(BQ24+BS24+BU24+BW24) -> 0 | BR24: =BP24/4 -> 0 | BT24: =BP24/4 -> 0 | BV24: =BP24/4 -> 0 | BX24: =BP24/4 -> 0 | BY24: =SUM(CA24+CC24+CE24+CG24) -> 0 | CB24: =BZ24/4 -> 0 | CD24: =BZ24/4 -> 0 | CF24: =BZ24/4 -> 0 | CH24: =BZ24/4 -> 0 | CI24: =SUM(CK24+CM24+CO24+CQ24) -> 0 | CL24: =CJ24/4 -> 0 | CN24: =CJ24/4 -> 0 | CP24: =CJ24/4 -> 0 | CR24: =CJ24/4 -> 0 | CS24: =SUM(CU24+CW24+CY24+DA24) -> 0 | CV24: =CT24/4 -> 0 | CX24: =CT24/4 -> 0 | CZ24: =CT24/4 -> 0 | DB24: =CT24/4 -> 0 | DC24: =SUM(DE24+DG24+DI24+DK24) -> 0 | DF24: =DD24/4 -> 0 | DH24: =DD24/4 -> 0 | DJ24: =DD24/4 -> 0 | DL24: =DD24/4 -> 0 | DM24: =SUM(DO24+DQ24+DS24+DU24) -> 0 | DP24: =DN24/4 -> 0 | DR24: =DN24/4 -> 0 | DT24: =DN24/4 -> 0 | DV24: =DN24/4 -> 0
C25: % de reunião realizada | D25: =D26/D24 -> #DIV/0! | E25: =E26/E24 -> 0.8 | F25: =F26/F24 -> #DIV/0! | G25: 0.9 | H25: - | I25: =I26/I24 -> #DIV/0! | J25: =G25 -> 0.9 | K25: =K26/K24 -> #DIV/0! | L25: =G25 -> 0.9 | M25: =M26/M24 -> #DIV/0! | N25: =G25 -> 0.9 | O25: =O26/O24 -> #DIV/0! | P25: =G25 -> 0.9 | Q25: =Q26/Q24 -> #DIV/0! | S25: =S26/S24 -> #DIV/0! | T25: =R25 | U25: =U26/U24 -> #DIV/0! | V25: =R25 | W25: =W26/W24 -> #DIV/0! | X25: =R25 | Y25: =Y26/Y24 -> #DIV/0! | Z25: =R25 | AA25: =AA26/AA24 -> #DIV/0! | AC25: =AC26/AC24 -> #DIV/0! | AD25: =AB25 | AE25: =AE26/AE24 -> #DIV/0! | AF25: =AB25 | AG25: =AG26/AG24 -> #DIV/0! | AH25: =AB25 | AI25: =AI26/AI24 -> #DIV/0! | AJ25: =AB25 | AK25: =AK26/AK24 -> #DIV/0! | AM25: =AM26/AM24 -> #DIV/0! | AN25: =AL25 | AO25: =AO26/AO24 -> #DIV/0! | AP25: =AL25 | AQ25: =AQ26/AQ24 -> #DIV/0! | AR25: =AL25 | AS25: =AS26/AS24 -> #DIV/0! | AT25: =AL25 | AU25: =AU26/AU24 -> #DIV/0! | AW25: =AW26/AW24 -> #DIV/0! | AX25: =AV25 | AY25: =AY26/AY24 -> #DIV/0! | AZ25: =AV25 | BA25: =BA26/BA24 -> #DIV/0! | BB25: =AV25 | BC25: =BC26/BC24 -> #DIV/0! | BD25: =AV25 | BE25: =BE26/BE24 -> #DIV/0! | BF25: 0.8 | BG25: =BG26/BG24 -> #DIV/0! | BH25: =BF25 -> 0.8 | BI25: =BI26/BI24 -> #DIV/0! | BJ25: =BF25 -> 0.8 | BK25: =BK26/BK24 -> #DIV/0! | BL25: =BF25 -> 0.8 | BM25: =BM26/BM24 -> #DIV/0! | BN25: =BF25 -> 0.8 | BO25: =BO26/BO24 -> #DIV/0! | BQ25: =BQ26/BQ24 -> #DIV/0! | BR25: =BP25 | BS25: =BS26/BS24 -> #DIV/0! | BT25: =BP25 | BU25: =BU26/BU24 -> #DIV/0! | BV25: =BP25 | BW25: =BW26/BW24 -> #DIV/0! | BX25: =BP25 | BY25: =BY26/BY24 -> #DIV/0! | CA25: =CA26/CA24 -> #DIV/0! | CB25: =BZ25 | CC25: =CC26/CC24 -> #DIV/0! | CD25: =BZ25 | CE25: =CE26/CE24 -> #DIV/0! | CF25: =BZ25 | CG25: =CG26/CG24 -> #DIV/0! | CH25: =BZ25 | CI25: =CI26/CI24 -> #DIV/0! | CK25: =CK26/CK24 -> #DIV/0! | CL25: =CJ25 | CM25: =CM26/CM24 -> #DIV/0! | CN25: =CJ25 | CO25: =CO26/CO24 -> #DIV/0! | CP25: =CJ25 | CQ25: =CQ26/CQ24 -> #DIV/0! | CR25: =CJ25 | CS25: =CS26/CS24 -> #DIV/0! | CU25: =CU26/CU24 -> #DIV/0! | CV25: =CT25 | CW25: =CW26/CW24 -> #DIV/0! | CX25: =CT25 | CY25: =CY26/CY24 -> #DIV/0! | CZ25: =CT25 | DA25: =DA26/DA24 -> #DIV/0! | DB25: =CT25 | DC25: =DC26/DC24 -> #DIV/0! | DE25: =DE26/DE24 -> #DIV/0! | DF25: =DD25 | DG25: =DG26/DG24 -> #DIV/0! | DH25: =DD25 | DI25: =DI26/DI24 -> #DIV/0! | DJ25: =DD25 | DK25: =DK26/DK24 -> #DIV/0! | DL25: =DD25 | DM25: =DM26/DM24 -> #DIV/0! | DO25: =DO26/DO24 -> #DIV/0! | DP25: =DN25 | DQ25: =DQ26/DQ24 -> #DIV/0! | DR25: =DN25 | DS25: =DS26/DS24 -> #DIV/0! | DT25: =DN25 | DU25: =DU26/DU24 -> #DIV/0! | DV25: =DN25
C26: Total de reuniões realizadas | D26: =SUM(F26+Q26+AA26+AK26+AU26+BE26+BO26+BY26+CI26+CS26+DC26+DM26) -> 0 | E26: =SUM(G26+R26+AB26+AL26+AV26+BF26+BP26+BZ26+CJ26+CT26+DD26+DN26) -> 5.952381 | F26: =SUM(I26+K26+M26+O26) -> 0 | G26: =G28/G27 -> 0 | H26: =G26/F26 -> #DIV/0! | J26: =G26/4 -> 0 | L26: =G26/4 -> 0 | N26: =G26/4 -> 0 | P26: =G26/4 -> 0 | Q26: =SUM(S26+U26+W26+Y26) -> 0 | T26: =R26/4 -> 0 | V26: =R26/4 -> 0 | X26: =R26/4 -> 0 | Z26: =R26/4 -> 0 | AA26: =SUM(AC26+AE26+AG26+AI26) -> 0 | AD26: =AB26/4 -> 0 | AF26: =AB26/4 -> 0 | AH26: =AB26/4 -> 0 | AJ26: =AB26/4 -> 0 | AK26: =SUM(AM26+AO26+AQ26+AS26) -> 0 | AN26: =AL26/4 -> 0 | AP26: =AL26/4 -> 0 | AR26: =AL26/4 -> 0 | AT26: =AL26/4 -> 0 | AU26: =SUM(AW26+AY26+BA26+BC26) -> 0 | AX26: =AV26/4 -> 0 | AZ26: =AV26/4 -> 0 | BB26: =AV26/4 -> 0 | BD26: =AV26/4 -> 0 | BE26: =SUM(BG26+BI26+BK26+BM26) -> 0 | BF26: =BF28/BF27 -> 5.952381 | BH26: =BF26/4 -> 1.4880952 | BJ26: =BF26/4 -> 1.4880952 | BL26: =BF26/4 -> 1.4880952 | BN26: =BF26/4 -> 1.4880952 | BO26: =SUM(BQ26+BS26+BU26+BW26) -> 0 | BR26: =BP26/4 -> 0 | BT26: =BP26/4 -> 0 | BV26: =BP26/4 -> 0 | BX26: =BP26/4 -> 0 | BY26: =SUM(CA26+CC26+CE26+CG26) -> 0 | CB26: =BZ26/4 -> 0 | CD26: =BZ26/4 -> 0 | CF26: =BZ26/4 -> 0 | CH26: =BZ26/4 -> 0 | CI26: =SUM(CK26+CM26+CO26+CQ26) -> 0 | CL26: =CJ26/4 -> 0 | CN26: =CJ26/4 -> 0 | CP26: =CJ26/4 -> 0 | CR26: =CJ26/4 -> 0 | CS26: =SUM(CU26+CW26+CY26+DA26) -> 0 | CV26: =CT26/4 -> 0 | CX26: =CT26/4 -> 0 | CZ26: =CT26/4 -> 0 | DB26: =CT26/4 -> 0 | DC26: =SUM(DE26+DG26+DI26+DK26) -> 0 | DF26: =DD26/4 -> 0 | DH26: =DD26/4 -> 0 | DJ26: =DD26/4 -> 0 | DL26: =DD26/4 -> 0 | DM26: =SUM(DO26+DQ26+DS26+DU26) -> 0 | DP26: =DN26/4 -> 0 | DR26: =DN26/4 -> 0 | DT26: =DN26/4 -> 0 | DV26: =DN26/4 -> 0
C27: % de propostas apresentadas | D27: =D28/D26 -> #DIV/0! | E27: =E28/E26 -> 0.7 | F27: =F28/F26 -> #DIV/0! | G27: 0.8 | H27: - | I27: =I28/I26 -> #DIV/0! | J27: =G27 -> 0.8 | K27: =K28/K26 -> #DIV/0! | L27: =G27 -> 0.8 | M27: =M28/M26 -> #DIV/0! | N27: =G27 -> 0.8 | O27: =O28/O26 -> #DIV/0! | P27: =G27 -> 0.8 | Q27: =Q28/Q26 -> #DIV/0! | S27: =S28/S26 -> #DIV/0! | T27: =R27 | U27: =U28/U26 -> #DIV/0! | V27: =R27 | W27: =W28/W26 -> #DIV/0! | X27: =R27 | Y27: =Y28/Y26 -> #DIV/0! | Z27: =R27 | AA27: =AA28/AA26 -> #DIV/0! | AC27: =AC28/AC26 -> #DIV/0! | AD27: =AB27 | AE27: =AE28/AE26 -> #DIV/0! | AF27: =AB27 | AG27: =AG28/AG26 -> #DIV/0! | AH27: =AB27 | AI27: =AI28/AI26 -> #DIV/0! | AJ27: =AB27 | AK27: =AK28/AK26 -> #DIV/0! | AM27: =AM28/AM26 -> #DIV/0! | AN27: =AL27 | AO27: =AO28/AO26 -> #DIV/0! | AP27: =AL27 | AQ27: =AQ28/AQ26 -> #DIV/0! | AR27: =AL27 | AS27: =AS28/AS26 -> #DIV/0! | AT27: =AL27 | AU27: =AU28/AU26 -> #DIV/0! | AW27: =AW28/AW26 -> #DIV/0! | AX27: =AV27 | AY27: =AY28/AY26 -> #DIV/0! | AZ27: =AV27 | BA27: =BA28/BA26 -> #DIV/0! | BB27: =AV27 | BC27: =BC28/BC26 -> #DIV/0! | BD27: =AV27 | BE27: =BE28/BE26 -> #DIV/0! | BF27: 0.7 | BG27: =BG28/BG26 -> #DIV/0! | BH27: =BF27 -> 0.7 | BI27: =BI28/BI26 -> #DIV/0! | BJ27: =BF27 -> 0.7 | BK27: =BK28/BK26 -> #DIV/0! | BL27: =BF27 -> 0.7 | BM27: =BM28/BM26 -> #DIV/0! | BN27: =BF27 -> 0.7 | BO27: =BO28/BO26 -> #DIV/0! | BQ27: =BQ28/BQ26 -> #DIV/0! | BR27: =BP27 | BS27: =BS28/BS26 -> #DIV/0! | BT27: =BP27 | BU27: =BU28/BU26 -> #DIV/0! | BV27: =BP27 | BW27: =BW28/BW26 -> #DIV/0! | BX27: =BP27 | BY27: =BY28/BY26 -> #DIV/0! | CA27: =CA28/CA26 -> #DIV/0! | CB27: =BZ27 | CC27: =CC28/CC26 -> #DIV/0! | CD27: =BZ27 | CE27: =CE28/CE26 -> #DIV/0! | CF27: =BZ27 | CG27: =CG28/CG26 -> #DIV/0! | CH27: =BZ27 | CI27: =CI28/CI26 -> #DIV/0! | CK27: =CK28/CK26 -> #DIV/0! | CL27: =CJ27 | CM27: =CM28/CM26 -> #DIV/0! | CN27: =CJ27 | CO27: =CO28/CO26 -> #DIV/0! | CP27: =CJ27 | CQ27: =CQ28/CQ26 -> #DIV/0! | CR27: =CJ27 | CS27: =CS28/CS26 -> #DIV/0! | CU27: =CU28/CU26 -> #DIV/0! | CV27: =CT27 | CW27: =CW28/CW26 -> #DIV/0! | CX27: =CT27 | CY27: =CY28/CY26 -> #DIV/0! | CZ27: =CT27 | DA27: =DA28/DA26 -> #DIV/0! | DB27: =CT27 | DC27: =DC28/DC26 -> #DIV/0! | DE27: =DE28/DE26 -> #DIV/0! | DF27: =DD27 | DG27: =DG28/DG26 -> #DIV/0! | DH27: =DD27 | DI27: =DI28/DI26 -> #DIV/0! | DJ27: =DD27 | DK27: =DK28/DK26 -> #DIV/0! | DL27: =DD27 | DM27: =DM28/DM26 -> #DIV/0! | DO27: =DO28/DO26 -> #DIV/0! | DP27: =DN27 | DQ27: =DQ28/DQ26 -> #DIV/0! | DR27: =DN27 | DS27: =DS28/DS26 -> #DIV/0! | DT27: =DN27 | DU27: =DU28/DU26 -> #DIV/0! | DV27: =DN27
C28: Total de propostas apresentadas | D28: =SUM(F28+Q28+AA28+AK28+AU28+BE28+BO28+BY28+CI28+CS28+DC28+DM28) -> 0 | E28: =SUM(G28+R28+AB28+AL28+AV28+BF28+BP28+BZ28+CJ28+CT28+DD28+DN28) -> 4.1666667 | F28: =SUM(I28+K28+M28+O28) -> 0 | G28: =G30/G29 -> 0 | H28: =G28/F28 -> #DIV/0! | J28: =G28/4 -> 0 | L28: =G28/4 -> 0 | N28: =G28/4 -> 0 | P28: =G28/4 -> 0 | Q28: =SUM(S28+U28+W28+Y28) -> 0 | T28: =R28/4 -> 0 | V28: =R28/4 -> 0 | X28: =R28/4 -> 0 | Z28: =R28/4 -> 0 | AA28: =SUM(AC28+AE28+AG28+AI28) -> 0 | AD28: =AB28/4 -> 0 | AF28: =AB28/4 -> 0 | AH28: =AB28/4 -> 0 | AJ28: =AB28/4 -> 0 | AK28: =SUM(AM28+AO28+AQ28+AS28) -> 0 | AN28: =AL28/4 -> 0 | AP28: =AL28/4 -> 0 | AR28: =AL28/4 -> 0 | AT28: =AL28/4 -> 0 | AU28: =SUM(AW28+AY28+BA28+BC28) -> 0 | AX28: =AV28/4 -> 0 | AZ28: =AV28/4 -> 0 | BB28: =AV28/4 -> 0 | BD28: =AV28/4 -> 0 | BE28: =SUM(BG28+BI28+BK28+BM28) -> 0 | BF28: =BF30/BF29 -> 4.1666667 | BH28: =BF28/4 -> 1.0416667 | BJ28: =BF28/4 -> 1.0416667 | BL28: =BF28/4 -> 1.0416667 | BN28: =BF28/4 -> 1.0416667 | BO28: =SUM(BQ28+BS28+BU28+BW28) -> 0 | BR28: =BP28/4 -> 0 | BT28: =BP28/4 -> 0 | BV28: =BP28/4 -> 0 | BX28: =BP28/4 -> 0 | BY28: =SUM(CA28+CC28+CE28+CG28) -> 0 | CB28: =BZ28/4 -> 0 | CD28: =BZ28/4 -> 0 | CF28: =BZ28/4 -> 0 | CH28: =BZ28/4 -> 0 | CI28: =SUM(CK28+CM28+CO28+CQ28) -> 0 | CL28: =CJ28/4 -> 0 | CN28: =CJ28/4 -> 0 | CP28: =CJ28/4 -> 0 | CR28: =CJ28/4 -> 0 | CS28: =SUM(CU28+CW28+CY28+DA28) -> 0 | CV28: =CT28/4 -> 0 | CX28: =CT28/4 -> 0 | CZ28: =CT28/4 -> 0 | DB28: =CT28/4 -> 0 | DC28: =SUM(DE28+DG28+DI28+DK28) -> 0 | DF28: =DD28/4 -> 0 | DH28: =DD28/4 -> 0 | DJ28: =DD28/4 -> 0 | DL28: =DD28/4 -> 0 | DM28: =SUM(DO28+DQ28+DS28+DU28) -> 0 | DP28: =DN28/4 -> 0 | DR28: =DN28/4 -> 0 | DT28: =DN28/4 -> 0 | DV28: =DN28/4 -> 0
C29: % de fechamento | D29: =D30/D28 -> #DIV/0! | E29: =E30/E28 -> 0.4 | F29: =F30/F28 -> #DIV/0! | G29: 0.4 | H29: - | I29: =I30/I28 -> #DIV/0! | J29: =G29 -> 0.4 | K29: =K30/K28 -> #DIV/0! | L29: =G29 -> 0.4 | M29: =M30/M28 -> #DIV/0! | N29: =G29 -> 0.4 | O29: =O30/O28 -> #DIV/0! | P29: =G29 -> 0.4 | Q29: =Q30/Q28 -> #DIV/0! | S29: =S30/S28 -> #DIV/0! | T29: =R29 | U29: =U30/U28 -> #DIV/0! | V29: =R29 | W29: =W30/W28 -> #DIV/0! | X29: =R29 | Y29: =Y30/Y28 -> #DIV/0! | Z29: =R29 | AA29: =AA30/AA28 -> #DIV/0! | AC29: =AC30/AC28 -> #DIV/0! | AD29: =AB29 | AE29: =AE30/AE28 -> #DIV/0! | AF29: =AB29 | AG29: =AG30/AG28 -> #DIV/0! | AH29: =AB29 | AI29: =AI30/AI28 -> #DIV/0! | AJ29: =AB29 | AK29: =AK30/AK28 -> #DIV/0! | AM29: =AM30/AM28 -> #DIV/0! | AN29: =AL29 | AO29: =AO30/AO28 -> #DIV/0! | AP29: =AL29 | AQ29: =AQ30/AQ28 -> #DIV/0! | AR29: =AL29 | AS29: =AS30/AS28 -> #DIV/0! | AT29: =AL29 | AU29: =AU30/AU28 -> #DIV/0! | AW29: =AW30/AW28 -> #DIV/0! | AX29: =AV29 | AY29: =AY30/AY28 -> #DIV/0! | AZ29: =AV29 | BA29: =BA30/BA28 -> #DIV/0! | BB29: =AV29 | BC29: =BC30/BC28 -> #DIV/0! | BD29: =AV29 | BE29: =BE30/BE28 -> #DIV/0! | BF29: 0.4 | BG29: =BG30/BG28 -> #DIV/0! | BH29: =BF29 -> 0.4 | BI29: =BI30/BI28 -> #DIV/0! | BJ29: =BF29 -> 0.4 | BK29: =BK30/BK28 -> #DIV/0! | BL29: =BF29 -> 0.4 | BM29: =BM30/BM28 -> #DIV/0! | BN29: =BF29 -> 0.4 | BO29: =BO30/BO28 -> #DIV/0! | BQ29: =BQ30/BQ28 -> #DIV/0! | BR29: =BP29 | BS29: =BS30/BS28 -> #DIV/0! | BT29: =BP29 | BU29: =BU30/BU28 -> #DIV/0! | BV29: =BP29 | BW29: =BW30/BW28 -> #DIV/0! | BX29: =BP29 | BY29: =BY30/BY28 -> #DIV/0! | CA29: =CA30/CA28 -> #DIV/0! | CB29: =BZ29 | CC29: =CC30/CC28 -> #DIV/0! | CD29: =BZ29 | CE29: =CE30/CE28 -> #DIV/0! | CF29: =BZ29 | CG29: =CG30/CG28 -> #DIV/0! | CH29: =BZ29 | CI29: =CI30/CI28 -> #DIV/0! | CK29: =CK30/CK28 -> #DIV/0! | CL29: =CJ29 | CM29: =CM30/CM28 -> #DIV/0! | CN29: =CJ29 | CO29: =CO30/CO28 -> #DIV/0! | CP29: =CJ29 | CQ29: =CQ30/CQ28 -> #DIV/0! | CR29: =CJ29 | CS29: =CS30/CS28 -> #DIV/0! | CU29: =CU30/CU28 -> #DIV/0! | CV29: =CT29 | CW29: =CW30/CW28 -> #DIV/0! | CX29: =CT29 | CY29: =CY30/CY28 -> #DIV/0! | CZ29: =CT29 | DA29: =DA30/DA28 -> #DIV/0! | DB29: =CT29 | DC29: =DC30/DC28 -> #DIV/0! | DE29: =DE30/DE28 -> #DIV/0! | DF29: =DD29 | DG29: =DG30/DG28 -> #DIV/0! | DH29: =DD29 | DI29: =DI30/DI28 -> #DIV/0! | DJ29: =DD29 | DK29: =DK30/DK28 -> #DIV/0! | DL29: =DD29 | DM29: =DM30/DM28 -> #DIV/0! | DO29: =DO30/DO28 -> #DIV/0! | DP29: =DN29 | DQ29: =DQ30/DQ28 -> #DIV/0! | DR29: =DN29 | DS29: =DS30/DS28 -> #DIV/0! | DT29: =DN29 | DU29: =DU30/DU28 -> #DIV/0! | DV29: =DN29
C30: Total de propostas fechadas | D30: =SUM(F30+Q30+AA30+AK30+AU30+BE30+BO30+BY30+CI30+CS30+DC30+DM30) -> 0 | E30: =SUM(G30+R30+AB30+AL30+AV30+BF30+BP30+BZ30+CJ30+CT30+DD30+DN30) -> 1.6666667 | F30: =SUM(I30+K30+M30+O30) -> 0 | G30: ='Dados da Operação'!H27 -> 0 | H30: =G30/F30 -> #DIV/0! | J30: =G30/4 -> 0 | L30: =G30/4 -> 0 | N30: =G30/4 -> 0 | P30: =G30/4 -> 0 | Q30: =SUM(S30+U30+W30+Y30) -> 0 | R30: ='Dados da Operação'!H36 -> 0 | T30: =R30/4 -> 0 | V30: =R30/4 -> 0 | X30: =R30/4 -> 0 | Z30: =R30/4 -> 0 | AA30: =SUM(AC30+AE30+AG30+AI30) -> 0 | AB30: ='Dados da Operação'!H45 -> 0 | AD30: =AB30/4 -> 0 | AF30: =AB30/4 -> 0 | AH30: =AB30/4 -> 0 | AJ30: =AB30/4 -> 0 | AK30: =SUM(AM30+AO30+AQ30+AS30) -> 0 | AL30: ='Dados da Operação'!H54 -> 0 | AN30: =AL30/4 -> 0 | AP30: =AL30/4 -> 0 | AR30: =AL30/4 -> 0 | AT30: =AL30/4 -> 0 | AU30: =SUM(AW30+AY30+BA30+BC30) -> 0 | AV30: ='Dados da Operação'!H63 -> 0 | AX30: =AV30/4 -> 0 | AZ30: =AV30/4 -> 0 | BB30: =AV30/4 -> 0 | BD30: =AV30/4 -> 0 | BE30: =SUM(BG30+BI30+BK30+BM30) -> 0 | BF30: ='Dados da Operação'!J4 -> 1.6666667 | BH30: =BF30/4 -> 0.41666667 | BJ30: =BF30/4 -> 0.41666667 | BL30: =BF30/4 -> 0.41666667 | BN30: =BF30/4 -> 0.41666667 | BO30: =SUM(BQ30+BS30+BU30+BW30) -> 0 | BP30: ='Dados da Operação'!H81 -> 0 | BR30: =BP30/4 -> 0 | BT30: =BP30/4 -> 0 | BV30: =BP30/4 -> 0 | BX30: =BP30/4 -> 0 | BY30: =SUM(CA30+CC30+CE30+CG30) -> 0 | BZ30: ='Dados da Operação'!H90 -> 0 | CB30: =BZ30/4 -> 0 | CD30: =BZ30/4 -> 0 | CF30: =BZ30/4 -> 0 | CH30: =BZ30/4 -> 0 | CI30: =SUM(CK30+CM30+CO30+CQ30) -> 0 | CJ30: ='Dados da Operação'!H99 -> 0 | CL30: =CJ30/4 -> 0 | CN30: =CJ30/4 -> 0 | CP30: =CJ30/4 -> 0 | CR30: =CJ30/4 -> 0 | CS30: =SUM(CU30+CW30+CY30+DA30) -> 0 | CT30: ='Dados da Operação'!H108 -> 0 | CV30: =CT30/4 -> 0 | CX30: =CT30/4 -> 0 | CZ30: =CT30/4 -> 0 | DB30: =CT30/4 -> 0 | DC30: =SUM(DE30+DG30+DI30+DK30) -> 0 | DD30: ='Dados da Operação'!H117 -> 0 | DF30: =DD30/4 -> 0 | DH30: =DD30/4 -> 0 | DJ30: =DD30/4 -> 0 | DL30: =DD30/4 -> 0 | DM30: =SUM(DO30+DQ30+DS30+DU30) -> 0 | DN30: ='Dados da Operação'!H126 -> 0 | DP30: =DN30/4 -> 0 | DR30: =DN30/4 -> 0 | DT30: =DN30/4 -> 0 | DV30: =DN30/4 -> 0
C31: Total de faturamento | D31: =SUM(F31+Q31+AA31+AK31+AU31+BE31+BO31+BY31+CI31+CS31+DC31+DM31) -> 0 | E31: =SUM(G31+R31+AB31+AL31+AV31+BF31+BP31+BZ31+CJ31+CT31+DD31+DN31) -> 4166.6667 | F31: =SUM(I31+K31+M31+O31) -> 0 | G31: ='Dados da Operação'!G27 -> 0 | H31: =G31/F31 -> #DIV/0! | J31: =G31/4 -> 0 | L31: =G31/4 -> 0 | N31: =G31/4 -> 0 | P31: =G31/4 -> 0 | Q31: =SUM(S31+U31+W31+Y31) -> 0 | R31: ='Dados da Operação'!G36 -> 0 | T31: =R31/4 -> 0 | V31: =R31/4 -> 0 | X31: =R31/4 -> 0 | Z31: =R31/4 -> 0 | AA31: =SUM(AC31+AE31+AG31+AI31) -> 0 | AB31: ='Dados da Operação'!G45 -> 0 | AD31: =AB31/4 -> 0 | AF31: =AB31/4 -> 0 | AH31: =AB31/4 -> 0 | AJ31: =AB31/4 -> 0 | AK31: =SUM(AM31+AO31+AQ31+AS31) -> 0 | AL31: ='Dados da Operação'!G54 -> 0 | AN31: =AL31/4 -> 0 | AP31: =AL31/4 -> 0 | AR31: =AL31/4 -> 0 | AT31: =AL31/4 -> 0 | AU31: =SUM(AW31+AY31+BA31+BC31) -> 0 | AV31: ='Dados da Operação'!G63 -> 0 | AX31: =AV31/4 -> 0 | AZ31: =AV31/4 -> 0 | BB31: =AV31/4 -> 0 | BD31: =AV31/4 -> 0 | BE31: =SUM(BG31+BI31+BK31+BM31) -> 0 | BF31: =BF32*BF30 -> 4166.6667 | BH31: =BF31/4 -> 1041.6667 | BJ31: =BF31/4 -> 1041.6667 | BL31: =BF31/4 -> 1041.6667 | BN31: =BF31/4 -> 1041.6667 | BO31: =SUM(BQ31+BS31+BU31+BW31) -> 0 | BP31: ='Dados da Operação'!G81 -> 0 | BR31: =BP31/4 -> 0 | BT31: =BP31/4 -> 0 | BV31: =BP31/4 -> 0 | BX31: =BP31/4 -> 0 | BY31: =SUM(CA31+CC31+CE31+CG31) -> 0 | BZ31: ='Dados da Operação'!G90 -> 0 | CB31: =BZ31/4 -> 0 | CD31: =BZ31/4 -> 0 | CF31: =BZ31/4 -> 0 | CH31: =BZ31/4 -> 0 | CI31: =SUM(CK31+CM31+CO31+CQ31) -> 0 | CJ31: ='Dados da Operação'!G99 -> 0 | CL31: =CJ31/4 -> 0 | CN31: =CJ31/4 -> 0 | CP31: =CJ31/4 -> 0 | CR31: =CJ31/4 -> 0 | CS31: =SUM(CU31+CW31+CY31+DA31) -> 0 | CT31: ='Dados da Operação'!G108 -> 0 | CV31: =CT31/4 -> 0 | CX31: =CT31/4 -> 0 | CZ31: =CT31/4 -> 0 | DB31: =CT31/4 -> 0 | DC31: =SUM(DE31+DG31+DI31+DK31) -> 0 | DD31: ='Dados da Operação'!G117 -> 0 | DF31: =DD31/4 -> 0 | DH31: =DD31/4 -> 0 | DJ31: =DD31/4 -> 0 | DL31: =DD31/4 -> 0 | DM31: =SUM(DO31+DQ31+DS31+DU31) -> 0 | DN31: ='Dados da Operação'!G126 -> 0 | DP31: =DN31/4 -> 0 | DR31: =DN31/4 -> 0 | DT31: =DN31/4 -> 0 | DV31: =DN31/4 -> 0
C32: Ticket médio | D32: =D31/D30 -> #DIV/0! | E32: =E31/E30 -> 2500 | F32: =F31/F30 -> #DIV/0! | G32: ='Dados da Operação'!$C$5 -> 2500 | H32: =G32/F32 -> #DIV/0! | I32: =I31/I30 -> #DIV/0! | J32: =G32 -> 2500 | K32: =K31/K30 -> #DIV/0! | L32: =G32 -> 2500 | M32: =M31/M30 -> #DIV/0! | N32: =G32 -> 2500 | O32: =O31/O30 -> #DIV/0! | P32: =G32 -> 2500 | Q32: =Q31/Q30 -> #DIV/0! | R32: ='Dados da Operação'!$C$5 -> 2500 | S32: =S31/S30 -> #DIV/0! | T32: =R32 -> 2500 | U32: =U31/U30 -> #DIV/0! | V32: =R32 -> 2500 | W32: =W31/W30 -> #DIV/0! | X32: =R32 -> 2500 | Y32: =Y31/Y30 -> #DIV/0! | Z32: =R32 -> 2500 | AA32: =AA31/AA30 -> #DIV/0! | AB32: ='Dados da Operação'!$C$5 -> 2500 | AC32: =AC31/AC30 -> #DIV/0! | AD32: =AB32 -> 2500 | AE32: =AE31/AE30 -> #DIV/0! | AF32: =AB32 -> 2500 | AG32: =AG31/AG30 -> #DIV/0! | AH32: =AB32 -> 2500 | AI32: =AI31/AI30 -> #DIV/0! | AJ32: =AB32 -> 2500 | AK32: =AK31/AK30 -> #DIV/0! | AL32: ='Dados da Operação'!$C$5 -> 2500 | AM32: =AM31/AM30 -> #DIV/0! | AN32: =AL32 -> 2500 | AO32: =AO31/AO30 -> #DIV/0! | AP32: =AL32 -> 2500 | AQ32: =AQ31/AQ30 -> #DIV/0! | AR32: =AL32 -> 2500 | AS32: =AS31/AS30 -> #DIV/0! | AT32: =AL32 -> 2500 | AU32: =AU31/AU30 -> #DIV/0! | AV32: ='Dados da Operação'!$C$5 -> 2500 | AW32: =AW31/AW30 -> #DIV/0! | AX32: =AV32 -> 2500 | AY32: =AY31/AY30 -> #DIV/0! | AZ32: =AV32 -> 2500 | BA32: =BA31/BA30 -> #DIV/0! | BB32: =AV32 -> 2500 | BC32: =BC31/BC30 -> #DIV/0! | BD32: =AV32 -> 2500 | BE32: =BE31/BE30 -> #DIV/0! | BF32: ='Dados da Operação'!$C$5 -> 2500 | BG32: =BG31/BG30 -> #DIV/0! | BH32: =BF32 -> 2500 | BI32: =BI31/BI30 -> #DIV/0! | BJ32: =BF32 -> 2500 | BK32: =BK31/BK30 -> #DIV/0! | BL32: =BF32 -> 2500 | BM32: =BM31/BM30 -> #DIV/0! | BN32: =BF32 -> 2500 | BO32: =BO31/BO30 -> #DIV/0! | BP32: ='Dados da Operação'!$C$5 -> 2500 | BQ32: =BQ31/BQ30 -> #DIV/0! | BR32: =BP32 -> 2500 | BS32: =BS31/BS30 -> #DIV/0! | BT32: =BP32 -> 2500 | BU32: =BU31/BU30 -> #DIV/0! | BV32: =BP32 -> 2500 | BW32: =BW31/BW30 -> #DIV/0! | BX32: =BP32 -> 2500 | BY32: =BY31/BY30 -> #DIV/0! | BZ32: ='Dados da Operação'!$C$5 -> 2500 | CA32: =CA31/CA30 -> #DIV/0! | CB32: =BZ32 -> 2500 | CC32: =CC31/CC30 -> #DIV/0! | CD32: =BZ32 -> 2500 | CE32: =CE31/CE30 -> #DIV/0! | CF32: =BZ32 -> 2500 | CG32: =CG31/CG30 -> #DIV/0! | CH32: =BZ32 -> 2500 | CI32: =CI31/CI30 -> #DIV/0! | CJ32: ='Dados da Operação'!$C$5 -> 2500 | CK32: =CK31/CK30 -> #DIV/0! | CL32: =CJ32 -> 2500 | CM32: =CM31/CM30 -> #DIV/0! | CN32: =CJ32 -> 2500 | CO32: =CO31/CO30 -> #DIV/0! | CP32: =CJ32 -> 2500 | CQ32: =CQ31/CQ30 -> #DIV/0! | CR32: =CJ32 -> 2500 | CS32: =CS31/CS30 -> #DIV/0! | CT32: ='Dados da Operação'!$C$5 -> 2500 | CU32: =CU31/CU30 -> #DIV/0! | CV32: =CT32 -> 2500 | CW32: =CW31/CW30 -> #DIV/0! | CX32: =CT32 -> 2500 | CY32: =CY31/CY30 -> #DIV/0! | CZ32: =CT32 -> 2500 | DA32: =DA31/DA30 -> #DIV/0! | DB32: =CT32 -> 2500 | DC32: =DC31/DC30 -> #DIV/0! | DD32: ='Dados da Operação'!$C$5 -> 2500 | DE32: =DE31/DE30 -> #DIV/0! | DF32: =DD32 -> 2500 | DG32: =DG31/DG30 -> #DIV/0! | DH32: =DD32 -> 2500 | DI32: =DI31/DI30 -> #DIV/0! | DJ32: =DD32 -> 2500 | DK32: =DK31/DK30 -> #DIV/0! | DL32: =DD32 -> 2500 | DM32: =DM31/DM30 -> #DIV/0! | DN32: ='Dados da Operação'!$C$5 -> 2500 | DO32: =DO31/DO30 -> #DIV/0! | DP32: =DN32 -> 2500 | DQ32: =DQ31/DQ30 -> #DIV/0! | DR32: =DN32 -> 2500 | DS32: =DS31/DS30 -> #DIV/0! | DT32: =DN32 -> 2500 | DU32: =DU31/DU30 -> #DIV/0! | DV32: =DN32 -> 2500
B34: INBOUND | C34: Total de leads captados | D34: =SUM(F34+Q34+AA34+AK34+AU34+BE34+BO34+BY34+CI34+CS34+DC34+DM34) -> 0 | E34: =SUM(G34+R34+AB34+AL34+AV34+BF34+BP34+BZ34+CJ34+CT34+DD34+DN34) -> 0 | F34: =SUM(I34+K34+M34+O34) -> 0 | G34: =G36/G35 -> 0 | H34: =F34/G34 -> #DIV/0! | J34: =G34/4 -> 0 | L34: =G34/4 -> 0 | N34: =G34/4 -> 0 | P34: =G34/4 -> 0 | Q34: =SUM(S34+U34+W34+Y34) -> 0 | R34: =R36/R35 -> 0 | T34: =R34/4 -> 0 | V34: =R34/4 -> 0 | X34: =R34/4 -> 0 | Z34: =R34/4 -> 0 | AA34: =SUM(AC34+AE34+AG34+AI34) -> 0 | AB34: =AB36/AB35 -> 0 | AD34: =AB34/4 -> 0 | AF34: =AB34/4 -> 0 | AH34: =AB34/4 -> 0 | AJ34: =AB34/4 -> 0 | AK34: =SUM(AM34+AO34+AQ34+AS34) -> 0 | AL34: =AL36/AL35 -> 0 | AN34: =AL34/4 -> 0 | AP34: =AL34/4 -> 0 | AR34: =AL34/4 -> 0 | AT34: =AL34/4 -> 0 | AU34: =SUM(AW34+AY34+BA34+BC34) -> 0 | AV34: =AV36/AV35 -> 0 | AX34: =AV34/4 -> 0 | AZ34: =AV34/4 -> 0 | BB34: =AV34/4 -> 0 | BD34: =AV34/4 -> 0 | BE34: =SUM(BG34+BI34+BK34+BM34) -> 0 | BF34: =BF36/BF35 -> 0 | BH34: =BF34/4 -> 0 | BJ34: =BF34/4 -> 0 | BL34: =BF34/4 -> 0 | BN34: =BF34/4 -> 0 | BO34: =SUM(BQ34+BS34+BU34+BW34) -> 0 | BP34: =BP36/BP35 -> 0 | BR34: =BP34/4 -> 0 | BT34: =BP34/4 -> 0 | BV34: =BP34/4 -> 0 | BX34: =BP34/4 -> 0 | BY34: =SUM(CA34+CC34+CE34+CG34) -> 0 | BZ34: =BZ36/BZ35 -> 0 | CB34: =BZ34/4 -> 0 | CD34: =BZ34/4 -> 0 | CF34: =BZ34/4 -> 0 | CH34: =BZ34/4 -> 0 | CI34: =SUM(CK34+CM34+CO34+CQ34) -> 0 | CJ34: =CJ36/CJ35 -> 0 | CL34: =CJ34/4 -> 0 | CN34: =CJ34/4 -> 0 | CP34: =CJ34/4 -> 0 | CR34: =CJ34/4 -> 0 | CS34: =SUM(CU34+CW34+CY34+DA34) -> 0 | CT34: =CT36/CT35 -> 0 | CV34: =CT34/4 -> 0 | CX34: =CT34/4 -> 0 | CZ34: =CT34/4 -> 0 | DB34: =CT34/4 -> 0 | DC34: =SUM(DE34+DG34+DI34+DK34) -> 0 | DD34: =DD36/DD35 -> 0 | DF34: =DD34/4 -> 0 | DH34: =DD34/4 -> 0 | DJ34: =DD34/4 -> 0 | DL34: =DD34/4 -> 0 | DM34: =SUM(DO34+DQ34+DS34+DU34) -> 0 | DN34: =DN36/DN35 -> 0 | DP34: =DN34/4 -> 0 | DR34: =DN34/4 -> 0 | DT34: =DN34/4 -> 0 | DV34: =DN34/4 -> 0
C35: % Conversão em Lead Conectado | D35: =D36/D34 -> #DIV/0! | E35: =E36/E34 -> #DIV/0! | F35: =F36/F34 -> #DIV/0! | G35: 0.6 | H35: - | I35: =I36/I34 -> #DIV/0! | J35: =G35 -> 0.6 | K35: =K36/K34 -> #DIV/0! | L35: =G35 -> 0.6 | M35: =M36/M34 -> #DIV/0! | N35: =G35 -> 0.6 | O35: =O36/O34 -> #DIV/0! | P35: =G35 -> 0.6 | Q35: =Q36/Q34 -> #DIV/0! | R35: 0.6 | S35: =S36/S34 -> #DIV/0! | T35: =R35 -> 0.6 | U35: =U36/U34 -> #DIV/0! | V35: =R35 -> 0.6 | W35: =W36/W34 -> #DIV/0! | X35: =R35 -> 0.6 | Y35: =Y36/Y34 -> #DIV/0! | Z35: =R35 -> 0.6 | AA35: =AA36/AA34 -> #DIV/0! | AB35: 0.6 | AC35: =AC36/AC34 -> #DIV/0! | AD35: =AB35 -> 0.6 | AE35: =AE36/AE34 -> #DIV/0! | AF35: =AB35 -> 0.6 | AG35: =AG36/AG34 -> #DIV/0! | AH35: =AB35 -> 0.6 | AI35: =AI36/AI34 -> #DIV/0! | AJ35: =AB35 -> 0.6 | AK35: =AK36/AK34 -> #DIV/0! | AL35: 0.6 | AM35: =AM36/AM34 -> #DIV/0! | AN35: =AL35 -> 0.6 | AO35: =AO36/AO34 -> #DIV/0! | AP35: =AL35 -> 0.6 | AQ35: =AQ36/AQ34 -> #DIV/0! | AR35: =AL35 -> 0.6 | AS35: =AS36/AS34 -> #DIV/0! | AT35: =AL35 -> 0.6 | AU35: =AU36/AU34 -> #DIV/0! | AV35: 0.6 | AW35: =AW36/AW34 -> #DIV/0! | AX35: =AV35 -> 0.6 | AY35: =AY36/AY34 -> #DIV/0! | AZ35: =AV35 -> 0.6 | BA35: =BA36/BA34 -> #DIV/0! | BB35: =AV35 -> 0.6 | BC35: =BC36/BC34 -> #DIV/0! | BD35: =AV35 -> 0.6 | BE35: =BE36/BE34 -> #DIV/0! | BF35: 0.25 | BG35: =BG36/BG34 -> #DIV/0! | BH35: =BF35 -> 0.25 | BI35: =BI36/BI34 -> #DIV/0! | BJ35: =BF35 -> 0.25 | BK35: =BK36/BK34 -> #DIV/0! | BL35: =BF35 -> 0.25 | BM35: =BM36/BM34 -> #DIV/0! | BN35: =BF35 -> 0.25 | BO35: =BO36/BO34 -> #DIV/0! | BP35: 0.6 | BQ35: =BQ36/BQ34 -> #DIV/0! | BR35: =BP35 -> 0.6 | BS35: =BS36/BS34 -> #DIV/0! | BT35: =BP35 -> 0.6 | BU35: =BU36/BU34 -> #DIV/0! | BV35: =BP35 -> 0.6 | BW35: =BW36/BW34 -> #DIV/0! | BX35: =BP35 -> 0.6 | BY35: =BY36/BY34 -> #DIV/0! | BZ35: 0.6 | CA35: =CA36/CA34 -> #DIV/0! | CB35: =BZ35 -> 0.6 | CC35: =CC36/CC34 -> #DIV/0! | CD35: =BZ35 -> 0.6 | CE35: =CE36/CE34 -> #DIV/0! | CF35: =BZ35 -> 0.6 | CG35: =CG36/CG34 -> #DIV/0! | CH35: =BZ35 -> 0.6 | CI35: =CI36/CI34 -> #DIV/0! | CJ35: 0.6 | CK35: =CK36/CK34 -> #DIV/0! | CL35: =CJ35 -> 0.6 | CM35: =CM36/CM34 -> #DIV/0! | CN35: =CJ35 -> 0.6 | CO35: =CO36/CO34 -> #DIV/0! | CP35: =CJ35 -> 0.6 | CQ35: =CQ36/CQ34 -> #DIV/0! | CR35: =CJ35 -> 0.6 | CS35: =CS36/CS34 -> #DIV/0! | CT35: 0.6 | CU35: =CU36/CU34 -> #DIV/0! | CV35: =CT35 -> 0.6 | CW35: =CW36/CW34 -> #DIV/0! | CX35: =CT35 -> 0.6 | CY35: =CY36/CY34 -> #DIV/0! | CZ35: =CT35 -> 0.6 | DA35: =DA36/DA34 -> #DIV/0! | DB35: =CT35 -> 0.6 | DC35: =DC36/DC34 -> #DIV/0! | DD35: 0.6 | DE35: =DE36/DE34 -> #DIV/0! | DF35: =DD35 -> 0.6 | DG35: =DG36/DG34 -> #DIV/0! | DH35: =DD35 -> 0.6 | DI35: =DI36/DI34 -> #DIV/0! | DJ35: =DD35 -> 0.6 | DK35: =DK36/DK34 -> #DIV/0! | DL35: =DD35 -> 0.6 | DM35: =DM36/DM34 -> #DIV/0! | DN35: 0.6 | DO35: =DO36/DO34 -> #DIV/0! | DP35: =DN35 -> 0.6 | DQ35: =DQ36/DQ34 -> #DIV/0! | DR35: =DN35 -> 0.6 | DS35: =DS36/DS34 -> #DIV/0! | DT35: =DN35 -> 0.6 | DU35: =DU36/DU34 -> #DIV/0! | DV35: =DN35 -> 0.6
C36: Total de leads conectados | D36: =SUM(F36+Q36+AA36+AK36+AU36+BE36+BO36+BY36+CI36+CS36+DC36+DM36) -> 0 | E36: =SUM(G36+R36+AB36+AL36+AV36+BF36+BP36+BZ36+CJ36+CT36+DD36+DN36) -> 0 | F36: =SUM(I36+K36+M36+O36) -> 0 | G36: =G38/G37 -> 0 | H36: =G36/F36 -> #DIV/0! | J36: =G36/4 -> 0 | L36: =G36/4 -> 0 | N36: =G36/4 -> 0 | P36: =G36/4 -> 0 | Q36: =SUM(S36+U36+W36+Y36) -> 0 | R36: =R38/R37 -> 0 | T36: =R36/4 -> 0 | V36: =R36/4 -> 0 | X36: =R36/4 -> 0 | Z36: =R36/4 -> 0 | AA36: =SUM(AC36+AE36+AG36+AI36) -> 0 | AB36: =AB38/AB37 -> 0 | AD36: =AB36/4 -> 0 | AF36: =AB36/4 -> 0 | AH36: =AB36/4 -> 0 | AJ36: =AB36/4 -> 0 | AK36: =SUM(AM36+AO36+AQ36+AS36) -> 0 | AL36: =AL38/AL37 -> 0 | AN36: =AL36/4 -> 0 | AP36: =AL36/4 -> 0 | AR36: =AL36/4 -> 0 | AT36: =AL36/4 -> 0 | AU36: =SUM(AW36+AY36+BA36+BC36) -> 0 | AV36: =AV38/AV37 -> 0 | AX36: =AV36/4 -> 0 | AZ36: =AV36/4 -> 0 | BB36: =AV36/4 -> 0 | BD36: =AV36/4 -> 0 | BE36: =SUM(BG36+BI36+BK36+BM36) -> 0 | BF36: =BF38/BF37 -> 0 | BH36: =BF36/4 -> 0 | BJ36: =BF36/4 -> 0 | BL36: =BF36/4 -> 0 | BN36: =BF36/4 -> 0 | BO36: =SUM(BQ36+BS36+BU36+BW36) -> 0 | BP36: =BP38/BP37 -> 0 | BR36: =BP36/4 -> 0 | BT36: =BP36/4 -> 0 | BV36: =BP36/4 -> 0 | BX36: =BP36/4 -> 0 | BY36: =SUM(CA36+CC36+CE36+CG36) -> 0 | BZ36: =BZ38/BZ37 -> 0 | CB36: =BZ36/4 -> 0 | CD36: =BZ36/4 -> 0 | CF36: =BZ36/4 -> 0 | CH36: =BZ36/4 -> 0 | CI36: =SUM(CK36+CM36+CO36+CQ36) -> 0 | CJ36: =CJ38/CJ37 -> 0 | CL36: =CJ36/4 -> 0 | CN36: =CJ36/4 -> 0 | CP36: =CJ36/4 -> 0 | CR36: =CJ36/4 -> 0 | CS36: =SUM(CU36+CW36+CY36+DA36) -> 0 | CT36: =CT38/CT37 -> 0 | CV36: =CT36/4 -> 0 | CX36: =CT36/4 -> 0 | CZ36: =CT36/4 -> 0 | DB36: =CT36/4 -> 0 | DC36: =SUM(DE36+DG36+DI36+DK36) -> 0 | DD36: =DD38/DD37 -> 0 | DF36: =DD36/4 -> 0 | DH36: =DD36/4 -> 0 | DJ36: =DD36/4 -> 0 | DL36: =DD36/4 -> 0 | DM36: =SUM(DO36+DQ36+DS36+DU36) -> 0 | DN36: =DN38/DN37 -> 0 | DP36: =DN36/4 -> 0 | DR36: =DN36/4 -> 0 | DT36: =DN36/4 -> 0 | DV36: =DN36/4 -> 0
C37: % Conversão em Reunião agendada | D37: =D38/D36 -> #DIV/0! | E37: =E38/E36 -> #DIV/0! | F37: =F38/F36 -> #DIV/0! | G37: 0.4 | H37: - | I37: =I38/I36 -> #DIV/0! | J37: =G37 -> 0.4 | K37: =K38/K36 -> #DIV/0! | L37: =G37 -> 0.4 | M37: =M38/M36 -> #DIV/0! | N37: =G37 -> 0.4 | O37: =O38/O36 -> #DIV/0! | P37: =G37 -> 0.4 | Q37: =Q38/Q36 -> #DIV/0! | R37: 0.4 | S37: =S38/S36 -> #DIV/0! | T37: =R37 -> 0.4 | U37: =U38/U36 -> #DIV/0! | V37: =R37 -> 0.4 | W37: =W38/W36 -> #DIV/0! | X37: =R37 -> 0.4 | Y37: =Y38/Y36 -> #DIV/0! | Z37: =R37 -> 0.4 | AA37: =AA38/AA36 -> #DIV/0! | AB37: 0.4 | AC37: =AC38/AC36 -> #DIV/0! | AD37: =AB37 -> 0.4 | AE37: =AE38/AE36 -> #DIV/0! | AF37: =AB37 -> 0.4 | AG37: =AG38/AG36 -> #DIV/0! | AH37: =AB37 -> 0.4 | AI37: =AI38/AI36 -> #DIV/0! | AJ37: =AB37 -> 0.4 | AK37: =AK38/AK36 -> #DIV/0! | AL37: 0.4 | AM37: =AM38/AM36 -> #DIV/0! | AN37: =AL37 -> 0.4 | AO37: =AO38/AO36 -> #DIV/0! | AP37: =AL37 -> 0.4 | AQ37: =AQ38/AQ36 -> #DIV/0! | AR37: =AL37 -> 0.4 | AS37: =AS38/AS36 -> #DIV/0! | AT37: =AL37 -> 0.4 | AU37: =AU38/AU36 -> #DIV/0! | AV37: 0.4 | AW37: =AW38/AW36 -> #DIV/0! | AX37: =AV37 -> 0.4 | AY37: =AY38/AY36 -> #DIV/0! | AZ37: =AV37 -> 0.4 | BA37: =BA38/BA36 -> #DIV/0! | BB37: =AV37 -> 0.4 | BC37: =BC38/BC36 -> #DIV/0! | BD37: =AV37 -> 0.4 | BE37: =BE38/BE36 -> #DIV/0! | BF37: 0.3 | BG37: =BG38/BG36 -> #DIV/0! | BH37: =BF37 -> 0.3 | BI37: =BI38/BI36 -> #DIV/0! | BJ37: =BF37 -> 0.3 | BK37: =BK38/BK36 -> #DIV/0! | BL37: =BF37 -> 0.3 | BM37: =BM38/BM36 -> #DIV/0! | BN37: =BF37 -> 0.3 | BO37: =BO38/BO36 -> #DIV/0! | BP37: 0.4 | BQ37: =BQ38/BQ36 -> #DIV/0! | BR37: =BP37 -> 0.4 | BS37: =BS38/BS36 -> #DIV/0! | BT37: =BP37 -> 0.4 | BU37: =BU38/BU36 -> #DIV/0! | BV37: =BP37 -> 0.4 | BW37: =BW38/BW36 -> #DIV/0! | BX37: =BP37 -> 0.4 | BY37: =BY38/BY36 -> #DIV/0! | BZ37: 0.4 | CA37: =CA38/CA36 -> #DIV/0! | CB37: =BZ37 -> 0.4 | CC37: =CC38/CC36 -> #DIV/0! | CD37: =BZ37 -> 0.4 | CE37: =CE38/CE36 -> #DIV/0! | CF37: =BZ37 -> 0.4 | CG37: =CG38/CG36 -> #DIV/0! | CH37: =BZ37 -> 0.4 | CI37: =CI38/CI36 -> #DIV/0! | CJ37: 0.4 | CK37: =CK38/CK36 -> #DIV/0! | CL37: =CJ37 -> 0.4 | CM37: =CM38/CM36 -> #DIV/0! | CN37: =CJ37 -> 0.4 | CO37: =CO38/CO36 -> #DIV/0! | CP37: =CJ37 -> 0.4 | CQ37: =CQ38/CQ36 -> #DIV/0! | CR37: =CJ37 -> 0.4 | CS37: =CS38/CS36 -> #DIV/0! | CT37: 0.4 | CU37: =CU38/CU36 -> #DIV/0! | CV37: =CT37 -> 0.4 | CW37: =CW38/CW36 -> #DIV/0! | CX37: =CT37 -> 0.4 | CY37: =CY38/CY36 -> #DIV/0! | CZ37: =CT37 -> 0.4 | DA37: =DA38/DA36 -> #DIV/0! | DB37: =CT37 -> 0.4 | DC37: =DC38/DC36 -> #DIV/0! | DD37: 0.4 | DE37: =DE38/DE36 -> #DIV/0! | DF37: =DD37 -> 0.4 | DG37: =DG38/DG36 -> #DIV/0! | DH37: =DD37 -> 0.4 | DI37: =DI38/DI36 -> #DIV/0! | DJ37: =DD37 -> 0.4 | DK37: =DK38/DK36 -> #DIV/0! | DL37: =DD37 -> 0.4 | DM37: =DM38/DM36 -> #DIV/0! | DN37: 0.4 | DO37: =DO38/DO36 -> #DIV/0! | DP37: =DN37 -> 0.4 | DQ37: =DQ38/DQ36 -> #DIV/0! | DR37: =DN37 -> 0.4 | DS37: =DS38/DS36 -> #DIV/0! | DT37: =DN37 -> 0.4 | DU37: =DU38/DU36 -> #DIV/0! | DV37: =DN37 -> 0.4
C38: Total de reuniões agendadas | D38: =SUM(F38+Q38+AA38+AK38+AU38+BE38+BO38+BY38+CI38+CS38+DC38+DM38) -> 0 | E38: =SUM(G38+R38+AB38+AL38+AV38+BF38+BP38+BZ38+CJ38+CT38+DD38+DN38) -> 0 | F38: =SUM(I38+K38+M38+O38) -> 0 | G38: =G40/G39 -> 0 | H38: =G38/F38 -> #DIV/0! | J38: =G38/4 -> 0 | L38: =G38/4 -> 0 | N38: =G38/4 -> 0 | P38: =G38/4 -> 0 | Q38: =SUM(S38+U38+W38+Y38) -> 0 | R38: =R40/R39 -> 0 | T38: =R38/4 -> 0 | V38: =R38/4 -> 0 | X38: =R38/4 -> 0 | Z38: =R38/4 -> 0 | AA38: =SUM(AC38+AE38+AG38+AI38) -> 0 | AB38: =AB40/AB39 -> 0 | AD38: =AB38/4 -> 0 | AF38: =AB38/4 -> 0 | AH38: =AB38/4 -> 0 | AJ38: =AB38/4 -> 0 | AK38: =SUM(AM38+AO38+AQ38+AS38) -> 0 | AL38: =AL40/AL39 -> 0 | AN38: =AL38/4 -> 0 | AP38: =AL38/4 -> 0 | AR38: =AL38/4 -> 0 | AT38: =AL38/4 -> 0 | AU38: =SUM(AW38+AY38+BA38+BC38) -> 0 | AV38: =AV40/AV39 -> 0 | AX38: =AV38/4 -> 0 | AZ38: =AV38/4 -> 0 | BB38: =AV38/4 -> 0 | BD38: =AV38/4 -> 0 | BE38: =SUM(BG38+BI38+BK38+BM38) -> 0 | BF38: =BF40/BF39 -> 0 | BH38: =BF38/4 -> 0 | BJ38: =BF38/4 -> 0 | BL38: =BF38/4 -> 0 | BN38: =BF38/4 -> 0 | BO38: =SUM(BQ38+BS38+BU38+BW38) -> 0 | BP38: =BP40/BP39 -> 0 | BR38: =BP38/4 -> 0 | BT38: =BP38/4 -> 0 | BV38: =BP38/4 -> 0 | BX38: =BP38/4 -> 0 | BY38: =SUM(CA38+CC38+CE38+CG38) -> 0 | BZ38: =BZ40/BZ39 -> 0 | CB38: =BZ38/4 -> 0 | CD38: =BZ38/4 -> 0 | CF38: =BZ38/4 -> 0 | CH38: =BZ38/4 -> 0 | CI38: =SUM(CK38+CM38+CO38+CQ38) -> 0 | CJ38: =CJ40/CJ39 -> 0 | CL38: =CJ38/4 -> 0 | CN38: =CJ38/4 -> 0 | CP38: =CJ38/4 -> 0 | CR38: =CJ38/4 -> 0 | CS38: =SUM(CU38+CW38+CY38+DA38) -> 0 | CT38: =CT40/CT39 -> 0 | CV38: =CT38/4 -> 0 | CX38: =CT38/4 -> 0 | CZ38: =CT38/4 -> 0 | DB38: =CT38/4 -> 0 | DC38: =SUM(DE38+DG38+DI38+DK38) -> 0 | DD38: =DD40/DD39 -> 0 | DF38: =DD38/4 -> 0 | DH38: =DD38/4 -> 0 | DJ38: =DD38/4 -> 0 | DL38: =DD38/4 -> 0 | DM38: =SUM(DO38+DQ38+DS38+DU38) -> 0 | DN38: =DN40/DN39 -> 0 | DP38: =DN38/4 -> 0 | DR38: =DN38/4 -> 0 | DT38: =DN38/4 -> 0 | DV38: =DN38/4 -> 0
C39: % de reunião realizada | D39: =D40/D38 -> #DIV/0! | E39: =E40/E38 -> #DIV/0! | F39: =F40/F38 -> #DIV/0! | G39: 0.9 | H39: - | I39: =I40/I38 -> #DIV/0! | J39: =G39 -> 0.9 | K39: =K40/K38 -> #DIV/0! | L39: =G39 -> 0.9 | M39: =M40/M38 -> #DIV/0! | N39: =G39 -> 0.9 | O39: =O40/O38 -> #DIV/0! | P39: =G39 -> 0.9 | Q39: =Q40/Q38 -> #DIV/0! | R39: 0.9 | S39: =S40/S38 -> #DIV/0! | T39: =R39 -> 0.9 | U39: =U40/U38 -> #DIV/0! | V39: =R39 -> 0.9 | W39: =W40/W38 -> #DIV/0! | X39: =R39 -> 0.9 | Y39: =Y40/Y38 -> #DIV/0! | Z39: =R39 -> 0.9 | AA39: =AA40/AA38 -> #DIV/0! | AB39: 0.9 | AC39: =AC40/AC38 -> #DIV/0! | AD39: =AB39 -> 0.9 | AE39: =AE40/AE38 -> #DIV/0! | AF39: =AB39 -> 0.9 | AG39: =AG40/AG38 -> #DIV/0! | AH39: =AB39 -> 0.9 | AI39: =AI40/AI38 -> #DIV/0! | AJ39: =AB39 -> 0.9 | AK39: =AK40/AK38 -> #DIV/0! | AL39: 0.9 | AM39: =AM40/AM38 -> #DIV/0! | AN39: =AL39 -> 0.9 | AO39: =AO40/AO38 -> #DIV/0! | AP39: =AL39 -> 0.9 | AQ39: =AQ40/AQ38 -> #DIV/0! | AR39: =AL39 -> 0.9 | AS39: =AS40/AS38 -> #DIV/0! | AT39: =AL39 -> 0.9 | AU39: =AU40/AU38 -> #DIV/0! | AV39: 0.9 | AW39: =AW40/AW38 -> #DIV/0! | AX39: =AV39 -> 0.9 | AY39: =AY40/AY38 -> #DIV/0! | AZ39: =AV39 -> 0.9 | BA39: =BA40/BA38 -> #DIV/0! | BB39: =AV39 -> 0.9 | BC39: =BC40/BC38 -> #DIV/0! | BD39: =AV39 -> 0.9 | BE39: =BE40/BE38 -> #DIV/0! | BF39: 0.8 | BG39: =BG40/BG38 -> #DIV/0! | BH39: =BF39 -> 0.8 | BI39: =BI40/BI38 -> #DIV/0! | BJ39: =BF39 -> 0.8 | BK39: =BK40/BK38 -> #DIV/0! | BL39: =BF39 -> 0.8 | BM39: =BM40/BM38 -> #DIV/0! | BN39: =BF39 -> 0.8 | BO39: =BO40/BO38 -> #DIV/0! | BP39: 0.9 | BQ39: =BQ40/BQ38 -> #DIV/0! | BR39: =BP39 -> 0.9 | BS39: =BS40/BS38 -> #DIV/0! | BT39: =BP39 -> 0.9 | BU39: =BU40/BU38 -> #DIV/0! | BV39: =BP39 -> 0.9 | BW39: =BW40/BW38 -> #DIV/0! | BX39: =BP39 -> 0.9 | BY39: =BY40/BY38 -> #DIV/0! | BZ39: 0.9 | CA39: =CA40/CA38 -> #DIV/0! | CB39: =BZ39 -> 0.9 | CC39: =CC40/CC38 -> #DIV/0! | CD39: =BZ39 -> 0.9 | CE39: =CE40/CE38 -> #DIV/0! | CF39: =BZ39 -> 0.9 | CG39: =CG40/CG38 -> #DIV/0! | CH39: =BZ39 -> 0.9 | CI39: =CI40/CI38 -> #DIV/0! | CJ39: 0.9 | CK39: =CK40/CK38 -> #DIV/0! | CL39: =CJ39 -> 0.9 | CM39: =CM40/CM38 -> #DIV/0! | CN39: =CJ39 -> 0.9 | CO39: =CO40/CO38 -> #DIV/0! | CP39: =CJ39 -> 0.9 | CQ39: =CQ40/CQ38 -> #DIV/0! | CR39: =CJ39 -> 0.9 | CS39: =CS40/CS38 -> #DIV/0! | CT39: 0.9 | CU39: =CU40/CU38 -> #DIV/0! | CV39: =CT39 -> 0.9 | CW39: =CW40/CW38 -> #DIV/0! | CX39: =CT39 -> 0.9 | CY39: =CY40/CY38 -> #DIV/0! | CZ39: =CT39 -> 0.9 | DA39: =DA40/DA38 -> #DIV/0! | DB39: =CT39 -> 0.9 | DC39: =DC40/DC38 -> #DIV/0! | DD39: 0.9 | DE39: =DE40/DE38 -> #DIV/0! | DF39: =DD39 -> 0.9 | DG39: =DG40/DG38 -> #DIV/0! | DH39: =DD39 -> 0.9 | DI39: =DI40/DI38 -> #DIV/0! | DJ39: =DD39 -> 0.9 | DK39: =DK40/DK38 -> #DIV/0! | DL39: =DD39 -> 0.9 | DM39: =DM40/DM38 -> #DIV/0! | DN39: 0.9 | DO39: =DO40/DO38 -> #DIV/0! | DP39: =DN39 -> 0.9 | DQ39: =DQ40/DQ38 -> #DIV/0! | DR39: =DN39 -> 0.9 | DS39: =DS40/DS38 -> #DIV/0! | DT39: =DN39 -> 0.9 | DU39: =DU40/DU38 -> #DIV/0! | DV39: =DN39 -> 0.9
C40: Total de reuniões realizadas | D40: =SUM(F40+Q40+AA40+AK40+AU40+BE40+BO40+BY40+CI40+CS40+DC40+DM40) -> 0 | E40: =SUM(G40+R40+AB40+AL40+AV40+BF40+BP40+BZ40+CJ40+CT40+DD40+DN40) -> 0 | F40: =SUM(I40+K40+M40+O40) -> 0 | G40: =G42/G41 -> 0 | H40: =G40/F40 -> #DIV/0! | J40: =G40/4 -> 0 | L40: =G40/4 -> 0 | N40: =G40/4 -> 0 | P40: =G40/4 -> 0 | Q40: =SUM(S40+U40+W40+Y40) -> 0 | R40: =R42/R41 -> 0 | T40: =R40/4 -> 0 | V40: =R40/4 -> 0 | X40: =R40/4 -> 0 | Z40: =R40/4 -> 0 | AA40: =SUM(AC40+AE40+AG40+AI40) -> 0 | AB40: =AB42/AB41 -> 0 | AD40: =AB40/4 -> 0 | AF40: =AB40/4 -> 0 | AH40: =AB40/4 -> 0 | AJ40: =AB40/4 -> 0 | AK40: =SUM(AM40+AO40+AQ40+AS40) -> 0 | AL40: =AL42/AL41 -> 0 | AN40: =AL40/4 -> 0 | AP40: =AL40/4 -> 0 | AR40: =AL40/4 -> 0 | AT40: =AL40/4 -> 0 | AU40: =SUM(AW40+AY40+BA40+BC40) -> 0 | AV40: =AV42/AV41 -> 0 | AX40: =AV40/4 -> 0 | AZ40: =AV40/4 -> 0 | BB40: =AV40/4 -> 0 | BD40: =AV40/4 -> 0 | BE40: =SUM(BG40+BI40+BK40+BM40) -> 0 | BF40: =BF42/BF41 -> 0 | BH40: =BF40/4 -> 0 | BJ40: =BF40/4 -> 0 | BL40: =BF40/4 -> 0 | BN40: =BF40/4 -> 0 | BO40: =SUM(BQ40+BS40+BU40+BW40) -> 0 | BP40: =BP42/BP41 -> 0 | BR40: =BP40/4 -> 0 | BT40: =BP40/4 -> 0 | BV40: =BP40/4 -> 0 | BX40: =BP40/4 -> 0 | BY40: =SUM(CA40+CC40+CE40+CG40) -> 0 | BZ40: =BZ42/BZ41 -> 0 | CB40: =BZ40/4 -> 0 | CD40: =BZ40/4 -> 0 | CF40: =BZ40/4 -> 0 | CH40: =BZ40/4 -> 0 | CI40: =SUM(CK40+CM40+CO40+CQ40) -> 0 | CJ40: =CJ42/CJ41 -> 0 | CL40: =CJ40/4 -> 0 | CN40: =CJ40/4 -> 0 | CP40: =CJ40/4 -> 0 | CR40: =CJ40/4 -> 0 | CS40: =SUM(CU40+CW40+CY40+DA40) -> 0 | CT40: =CT42/CT41 -> 0 | CV40: =CT40/4 -> 0 | CX40: =CT40/4 -> 0 | CZ40: =CT40/4 -> 0 | DB40: =CT40/4 -> 0 | DC40: =SUM(DE40+DG40+DI40+DK40) -> 0 | DD40: =DD42/DD41 -> 0 | DF40: =DD40/4 -> 0 | DH40: =DD40/4 -> 0 | DJ40: =DD40/4 -> 0 | DL40: =DD40/4 -> 0 | DM40: =SUM(DO40+DQ40+DS40+DU40) -> 0 | DN40: =DN42/DN41 -> 0 | DP40: =DN40/4 -> 0 | DR40: =DN40/4 -> 0 | DT40: =DN40/4 -> 0 | DV40: =DN40/4 -> 0
C41: % de propostas apresentadas | D41: =D42/D40 -> #DIV/0! | E41: =E42/E40 -> #DIV/0! | F41: =F42/F40 -> #DIV/0! | G41: 0.7 | H41: - | I41: =I42/I40 -> #DIV/0! | J41: =G41 -> 0.7 | K41: =K42/K40 -> #DIV/0! | L41: =G41 -> 0.7 | M41: =M42/M40 -> #DIV/0! | N41: =G41 -> 0.7 | O41: =O42/O40 -> #DIV/0! | P41: =G41 -> 0.7 | Q41: =Q42/Q40 -> #DIV/0! | R41: 0.7 | S41: =S42/S40 -> #DIV/0! | T41: =R41 -> 0.7 | U41: =U42/U40 -> #DIV/0! | V41: =R41 -> 0.7 | W41: =W42/W40 -> #DIV/0! | X41: =R41 -> 0.7 | Y41: =Y42/Y40 -> #DIV/0! | Z41: =R41 -> 0.7 | AA41: =AA42/AA40 -> #DIV/0! | AB41: 0.7 | AC41: =AC42/AC40 -> #DIV/0! | AD41: =AB41 -> 0.7 | AE41: =AE42/AE40 -> #DIV/0! | AF41: =AB41 -> 0.7 | AG41: =AG42/AG40 -> #DIV/0! | AH41: =AB41 -> 0.7 | AI41: =AI42/AI40 -> #DIV/0! | AJ41: =AB41 -> 0.7 | AK41: =AK42/AK40 -> #DIV/0! | AL41: 0.7 | AM41: =AM42/AM40 -> #DIV/0! | AN41: =AL41 -> 0.7 | AO41: =AO42/AO40 -> #DIV/0! | AP41: =AL41 -> 0.7 | AQ41: =AQ42/AQ40 -> #DIV/0! | AR41: =AL41 -> 0.7 | AS41: =AS42/AS40 -> #DIV/0! | AT41: =AL41 -> 0.7 | AU41: =AU42/AU40 -> #DIV/0! | AV41: 0.7 | AW41: =AW42/AW40 -> #DIV/0! | AX41: =AV41 -> 0.7 | AY41: =AY42/AY40 -> #DIV/0! | AZ41: =AV41 -> 0.7 | BA41: =BA42/BA40 -> #DIV/0! | BB41: =AV41 -> 0.7 | BC41: =BC42/BC40 -> #DIV/0! | BD41: =AV41 -> 0.7 | BE41: =BE42/BE40 -> #DIV/0! | BF41: 0.7 | BG41: =BG42/BG40 -> #DIV/0! | BH41: =BF41 -> 0.7 | BI41: =BI42/BI40 -> #DIV/0! | BJ41: =BF41 -> 0.7 | BK41: =BK42/BK40 -> #DIV/0! | BL41: =BF41 -> 0.7 | BM41: =BM42/BM40 -> #DIV/0! | BN41: =BF41 -> 0.7 | BO41: =BO42/BO40 -> #DIV/0! | BP41: 0.7 | BQ41: =BQ42/BQ40 -> #DIV/0! | BR41: =BP41 -> 0.7 | BS41: =BS42/BS40 -> #DIV/0! | BT41: =BP41 -> 0.7 | BU41: =BU42/BU40 -> #DIV/0! | BV41: =BP41 -> 0.7 | BW41: =BW42/BW40 -> #DIV/0! | BX41: =BP41 -> 0.7 | BY41: =BY42/BY40 -> #DIV/0! | BZ41: 0.7 | CA41: =CA42/CA40 -> #DIV/0! | CB41: =BZ41 -> 0.7 | CC41: =CC42/CC40 -> #DIV/0! | CD41: =BZ41 -> 0.7 | CE41: =CE42/CE40 -> #DIV/0! | CF41: =BZ41 -> 0.7 | CG41: =CG42/CG40 -> #DIV/0! | CH41: =BZ41 -> 0.7 | CI41: =CI42/CI40 -> #DIV/0! | CJ41: 0.7 | CK41: =CK42/CK40 -> #DIV/0! | CL41: =CJ41 -> 0.7 | CM41: =CM42/CM40 -> #DIV/0! | CN41: =CJ41 -> 0.7 | CO41: =CO42/CO40 -> #DIV/0! | CP41: =CJ41 -> 0.7 | CQ41: =CQ42/CQ40 -> #DIV/0! | CR41: =CJ41 -> 0.7 | CS41: =CS42/CS40 -> #DIV/0! | CT41: 0.7 | CU41: =CU42/CU40 -> #DIV/0! | CV41: =CT41 -> 0.7 | CW41: =CW42/CW40 -> #DIV/0! | CX41: =CT41 -> 0.7 | CY41: =CY42/CY40 -> #DIV/0! | CZ41: =CT41 -> 0.7 | DA41: =DA42/DA40 -> #DIV/0! | DB41: =CT41 -> 0.7 | DC41: =DC42/DC40 -> #DIV/0! | DD41: 0.7 | DE41: =DE42/DE40 -> #DIV/0! | DF41: =DD41 -> 0.7 | DG41: =DG42/DG40 -> #DIV/0! | DH41: =DD41 -> 0.7 | DI41: =DI42/DI40 -> #DIV/0! | DJ41: =DD41 -> 0.7 | DK41: =DK42/DK40 -> #DIV/0! | DL41: =DD41 -> 0.7 | DM41: =DM42/DM40 -> #DIV/0! | DN41: 0.7 | DO41: =DO42/DO40 -> #DIV/0! | DP41: =DN41 -> 0.7 | DQ41: =DQ42/DQ40 -> #DIV/0! | DR41: =DN41 -> 0.7 | DS41: =DS42/DS40 -> #DIV/0! | DT41: =DN41 -> 0.7 | DU41: =DU42/DU40 -> #DIV/0! | DV41: =DN41 -> 0.7
C42: Total de propostas apresentadas | D42: =SUM(F42+Q42+AA42+AK42+AU42+BE42+BO42+BY42+CI42+CS42+DC42+DM42) -> 0 | E42: =SUM(G42+R42+AB42+AL42+AV42+BF42+BP42+BZ42+CJ42+CT42+DD42+DN42) -> 0 | F42: =SUM(I42+K42+M42+O42) -> 0 | G42: =G44/G43 -> 0 | H42: =G42/F42 -> #DIV/0! | J42: =G42/4 -> 0 | L42: =G42/4 -> 0 | N42: =G42/4 -> 0 | P42: =G42/4 -> 0 | Q42: =SUM(S42+U42+W42+Y42) -> 0 | R42: =R44/R43 -> 0 | T42: =R42/4 -> 0 | V42: =R42/4 -> 0 | X42: =R42/4 -> 0 | Z42: =R42/4 -> 0 | AA42: =SUM(AC42+AE42+AG42+AI42) -> 0 | AB42: =AB44/AB43 -> 0 | AD42: =AB42/4 -> 0 | AF42: =AB42/4 -> 0 | AH42: =AB42/4 -> 0 | AJ42: =AB42/4 -> 0 | AK42: =SUM(AM42+AO42+AQ42+AS42) -> 0 | AL42: =AL44/AL43 -> 0 | AN42: =AL42/4 -> 0 | AP42: =AL42/4 -> 0 | AR42: =AL42/4 -> 0 | AT42: =AL42/4 -> 0 | AU42: =SUM(AW42+AY42+BA42+BC42) -> 0 | AV42: =AV44/AV43 -> 0 | AX42: =AV42/4 -> 0 | AZ42: =AV42/4 -> 0 | BB42: =AV42/4 -> 0 | BD42: =AV42/4 -> 0 | BE42: =SUM(BG42+BI42+BK42+BM42) -> 0 | BF42: =BF44/BF43 -> 0 | BH42: =BF42/4 -> 0 | BJ42: =BF42/4 -> 0 | BL42: =BF42/4 -> 0 | BN42: =BF42/4 -> 0 | BO42: =SUM(BQ42+BS42+BU42+BW42) -> 0 | BP42: =BP44/BP43 -> 0 | BR42: =BP42/4 -> 0 | BT42: =BP42/4 -> 0 | BV42: =BP42/4 -> 0 | BX42: =BP42/4 -> 0 | BY42: =SUM(CA42+CC42+CE42+CG42) -> 0 | BZ42: =BZ44/BZ43 -> 0 | CB42: =BZ42/4 -> 0 | CD42: =BZ42/4 -> 0 | CF42: =BZ42/4 -> 0 | CH42: =BZ42/4 -> 0 | CI42: =SUM(CK42+CM42+CO42+CQ42) -> 0 | CJ42: =CJ44/CJ43 -> 0 | CL42: =CJ42/4 -> 0 | CN42: =CJ42/4 -> 0 | CP42: =CJ42/4 -> 0 | CR42: =CJ42/4 -> 0 | CS42: =SUM(CU42+CW42+CY42+DA42) -> 0 | CT42: =CT44/CT43 -> 0 | CV42: =CT42/4 -> 0 | CX42: =CT42/4 -> 0 | CZ42: =CT42/4 -> 0 | DB42: =CT42/4 -> 0 | DC42: =SUM(DE42+DG42+DI42+DK42) -> 0 | DD42: =DD44/DD43 -> 0 | DF42: =DD42/4 -> 0 | DH42: =DD42/4 -> 0 | DJ42: =DD42/4 -> 0 | DL42: =DD42/4 -> 0 | DM42: =SUM(DO42+DQ42+DS42+DU42) -> 0 | DN42: =DN44/DN43 -> 0 | DP42: =DN42/4 -> 0 | DR42: =DN42/4 -> 0 | DT42: =DN42/4 -> 0 | DV42: =DN42/4 -> 0
C43: % de fechamento | D43: =D44/D42 -> #DIV/0! | E43: =E44/E42 -> #DIV/0! | F43: =F44/F42 -> #DIV/0! | G43: 0.4 | H43: - | I43: =I44/I42 -> #DIV/0! | J43: =G43 -> 0.4 | K43: =K44/K42 -> #DIV/0! | L43: =G43 -> 0.4 | M43: =M44/M42 -> #DIV/0! | N43: =G43 -> 0.4 | O43: =O44/O42 -> #DIV/0! | P43: =G43 -> 0.4 | Q43: =Q44/Q42 -> #DIV/0! | R43: 0.4 | S43: =S44/S42 -> #DIV/0! | T43: =R43 -> 0.4 | U43: =U44/U42 -> #DIV/0! | V43: =R43 -> 0.4 | W43: =W44/W42 -> #DIV/0! | X43: =R43 -> 0.4 | Y43: =Y44/Y42 -> #DIV/0! | Z43: =R43 -> 0.4 | AA43: =AA44/AA42 -> #DIV/0! | AB43: 0.4 | AC43: =AC44/AC42 -> #DIV/0! | AD43: =AB43 -> 0.4 | AE43: =AE44/AE42 -> #DIV/0! | AF43: =AB43 -> 0.4 | AG43: =AG44/AG42 -> #DIV/0! | AH43: =AB43 -> 0.4 | AI43: =AI44/AI42 -> #DIV/0! | AJ43: =AB43 -> 0.4 | AK43: =AK44/AK42 -> #DIV/0! | AL43: 0.4 | AM43: =AM44/AM42 -> #DIV/0! | AN43: =AL43 -> 0.4 | AO43: =AO44/AO42 -> #DIV/0! | AP43: =AL43 -> 0.4 | AQ43: =AQ44/AQ42 -> #DIV/0! | AR43: =AL43 -> 0.4 | AS43: =AS44/AS42 -> #DIV/0! | AT43: =AL43 -> 0.4 | AU43: =AU44/AU42 -> #DIV/0! | AV43: 0.4 | AW43: =AW44/AW42 -> #DIV/0! | AX43: =AV43 -> 0.4 | AY43: =AY44/AY42 -> #DIV/0! | AZ43: =AV43 -> 0.4 | BA43: =BA44/BA42 -> #DIV/0! | BB43: =AV43 -> 0.4 | BC43: =BC44/BC42 -> #DIV/0! | BD43: =AV43 -> 0.4 | BE43: =BE44/BE42 -> #DIV/0! | BF43: 0.4 | BG43: =BG44/BG42 -> #DIV/0! | BH43: =BF43 -> 0.4 | BI43: =BI44/BI42 -> #DIV/0! | BJ43: =BF43 -> 0.4 | BK43: =BK44/BK42 -> #DIV/0! | BL43: =BF43 -> 0.4 | BM43: =BM44/BM42 -> #DIV/0! | BN43: =BF43 -> 0.4 | BO43: =BO44/BO42 -> #DIV/0! | BP43: 0.4 | BQ43: =BQ44/BQ42 -> #DIV/0! | BR43: =BP43 -> 0.4 | BS43: =BS44/BS42 -> #DIV/0! | BT43: =BP43 -> 0.4 | BU43: =BU44/BU42 -> #DIV/0! | BV43: =BP43 -> 0.4 | BW43: =BW44/BW42 -> #DIV/0! | BX43: =BP43 -> 0.4 | BY43: =BY44/BY42 -> #DIV/0! | BZ43: 0.4 | CA43: =CA44/CA42 -> #DIV/0! | CB43: =BZ43 -> 0.4 | CC43: =CC44/CC42 -> #DIV/0! | CD43: =BZ43 -> 0.4 | CE43: =CE44/CE42 -> #DIV/0! | CF43: =BZ43 -> 0.4 | CG43: =CG44/CG42 -> #DIV/0! | CH43: =BZ43 -> 0.4 | CI43: =CI44/CI42 -> #DIV/0! | CJ43: 0.4 | CK43: =CK44/CK42 -> #DIV/0! | CL43: =CJ43 -> 0.4 | CM43: =CM44/CM42 -> #DIV/0! | CN43: =CJ43 -> 0.4 | CO43: =CO44/CO42 -> #DIV/0! | CP43: =CJ43 -> 0.4 | CQ43: =CQ44/CQ42 -> #DIV/0! | CR43: =CJ43 -> 0.4 | CS43: =CS44/CS42 -> #DIV/0! | CT43: 0.4 | CU43: =CU44/CU42 -> #DIV/0! | CV43: =CT43 -> 0.4 | CW43: =CW44/CW42 -> #DIV/0! | CX43: =CT43 -> 0.4 | CY43: =CY44/CY42 -> #DIV/0! | CZ43: =CT43 -> 0.4 | DA43: =DA44/DA42 -> #DIV/0! | DB43: =CT43 -> 0.4 | DC43: =DC44/DC42 -> #DIV/0! | DD43: 0.4 | DE43: =DE44/DE42 -> #DIV/0! | DF43: =DD43 -> 0.4 | DG43: =DG44/DG42 -> #DIV/0! | DH43: =DD43 -> 0.4 | DI43: =DI44/DI42 -> #DIV/0! | DJ43: =DD43 -> 0.4 | DK43: =DK44/DK42 -> #DIV/0! | DL43: =DD43 -> 0.4 | DM43: =DM44/DM42 -> #DIV/0! | DN43: 0.4 | DO43: =DO44/DO42 -> #DIV/0! | DP43: =DN43 -> 0.4 | DQ43: =DQ44/DQ42 -> #DIV/0! | DR43: =DN43 -> 0.4 | DS43: =DS44/DS42 -> #DIV/0! | DT43: =DN43 -> 0.4 | DU43: =DU44/DU42 -> #DIV/0! | DV43: =DN43 -> 0.4
C44: Total de propostas fechadas | D44: =SUM(F44+Q44+AA44+AK44+AU44+BE44+BO44+BY44+CI44+CS44+DC44+DM44) -> 0 | E44: =SUM(G44+R44+AB44+AL44+AV44+BF44+BP44+BZ44+CJ44+CT44+DD44+DN44) -> 0 | F44: =SUM(I44+K44+M44+O44) -> 0 | G44: ='Dados da Operação'!H28 -> 0 | H44: =G44/F44 -> #DIV/0! | J44: =G44/4 -> 0 | L44: =G44/4 -> 0 | N44: =G44/4 -> 0 | P44: =G44/4 -> 0 | Q44: =SUM(S44+U44+W44+Y44) -> 0 | R44: ='Dados da Operação'!H37 -> 0 | T44: =R44/4 -> 0 | V44: =R44/4 -> 0 | X44: =R44/4 -> 0 | Z44: =R44/4 -> 0 | AA44: =SUM(AC44+AE44+AG44+AI44) -> 0 | AB44: ='Dados da Operação'!H46 -> 0 | AD44: =AB44/4 -> 0 | AF44: =AB44/4 -> 0 | AH44: =AB44/4 -> 0 | AJ44: =AB44/4 -> 0 | AK44: =SUM(AM44+AO44+AQ44+AS44) -> 0 | AL44: ='Dados da Operação'!H55 -> 0 | AN44: =AL44/4 -> 0 | AP44: =AL44/4 -> 0 | AR44: =AL44/4 -> 0 | AT44: =AL44/4 -> 0 | AU44: =SUM(AW44+AY44+BA44+BC44) -> 0 | AV44: ='Dados da Operação'!H64 -> 0 | AX44: =AV44/4 -> 0 | AZ44: =AV44/4 -> 0 | BB44: =AV44/4 -> 0 | BD44: =AV44/4 -> 0 | BE44: =SUM(BG44+BI44+BK44+BM44) -> 0 | BF44: ='Dados da Operação'!H73 -> 0 | BH44: =BF44/4 -> 0 | BJ44: =BF44/4 -> 0 | BL44: =BF44/4 -> 0 | BN44: =BF44/4 -> 0 | BO44: =SUM(BQ44+BS44+BU44+BW44) -> 0 | BP44: ='Dados da Operação'!H82 -> 0 | BR44: =BP44/4 -> 0 | BT44: =BP44/4 -> 0 | BV44: =BP44/4 -> 0 | BX44: =BP44/4 -> 0 | BY44: =SUM(CA44+CC44+CE44+CG44) -> 0 | BZ44: ='Dados da Operação'!H91 -> 0 | CB44: =BZ44/4 -> 0 | CD44: =BZ44/4 -> 0 | CF44: =BZ44/4 -> 0 | CH44: =BZ44/4 -> 0 | CI44: =SUM(CK44+CM44+CO44+CQ44) -> 0 | CJ44: ='Dados da Operação'!H100 -> 0 | CL44: =CJ44/4 -> 0 | CN44: =CJ44/4 -> 0 | CP44: =CJ44/4 -> 0 | CR44: =CJ44/4 -> 0 | CS44: =SUM(CU44+CW44+CY44+DA44) -> 0 | CT44: ='Dados da Operação'!H109 -> 0 | CV44: =CT44/4 -> 0 | CX44: =CT44/4 -> 0 | CZ44: =CT44/4 -> 0 | DB44: =CT44/4 -> 0 | DC44: =SUM(DE44+DG44+DI44+DK44) -> 0 | DD44: ='Dados da Operação'!H118 -> 0 | DF44: =DD44/4 -> 0 | DH44: =DD44/4 -> 0 | DJ44: =DD44/4 -> 0 | DL44: =DD44/4 -> 0 | DM44: =SUM(DO44+DQ44+DS44+DU44) -> 0 | DN44: ='Dados da Operação'!H127 -> 0 | DP44: =DN44/4 -> 0 | DR44: =DN44/4 -> 0 | DT44: =DN44/4 -> 0 | DV44: =DN44/4 -> 0
C45: Total de faturamento | D45: =SUM(F45+Q45+AA45+AK45+AU45+BE45+BO45+BY45+CI45+CS45+DC45+DM45) -> 0 | E45: =SUM(G45+R45+AB45+AL45+AV45+BF45+BP45+BZ45+CJ45+CT45+DD45+DN45) -> 0 | F45: =SUM(I45+K45+M45+O45) -> 0 | G45: ='Dados da Operação'!G28 -> 0 | H45: =G45/F45 -> #DIV/0! | J45: =G45/4 -> 0 | L45: =G45/4 -> 0 | N45: =G45/4 -> 0 | P45: =G45/4 -> 0 | Q45: =SUM(S45+U45+W45+Y45) -> 0 | R45: ='Dados da Operação'!G37 -> 0 | T45: =R45/4 -> 0 | V45: =R45/4 -> 0 | X45: =R45/4 -> 0 | Z45: =R45/4 -> 0 | AA45: =SUM(AC45+AE45+AG45+AI45) -> 0 | AB45: ='Dados da Operação'!G46 -> 0 | AD45: =AB45/4 -> 0 | AF45: =AB45/4 -> 0 | AH45: =AB45/4 -> 0 | AJ45: =AB45/4 -> 0 | AK45: =SUM(AM45+AO45+AQ45+AS45) -> 0 | AL45: ='Dados da Operação'!G55 -> 0 | AN45: =AL45/4 -> 0 | AP45: =AL45/4 -> 0 | AR45: =AL45/4 -> 0 | AT45: =AL45/4 -> 0 | AU45: =SUM(AW45+AY45+BA45+BC45) -> 0 | AV45: ='Dados da Operação'!G64 -> 0 | AX45: =AV45/4 -> 0 | AZ45: =AV45/4 -> 0 | BB45: =AV45/4 -> 0 | BD45: =AV45/4 -> 0 | BE45: =SUM(BG45+BI45+BK45+BM45) -> 0 | BF45: ='Dados da Operação'!G73 -> 0 | BH45: =BF45/4 -> 0 | BJ45: =BF45/4 -> 0 | BL45: =BF45/4 -> 0 | BN45: =BF45/4 -> 0 | BO45: =SUM(BQ45+BS45+BU45+BW45) -> 0 | BP45: ='Dados da Operação'!G82 -> 0 | BR45: =BP45/4 -> 0 | BT45: =BP45/4 -> 0 | BV45: =BP45/4 -> 0 | BX45: =BP45/4 -> 0 | BY45: =SUM(CA45+CC45+CE45+CG45) -> 0 | BZ45: ='Dados da Operação'!G91 -> 0 | CB45: =BZ45/4 -> 0 | CD45: =BZ45/4 -> 0 | CF45: =BZ45/4 -> 0 | CH45: =BZ45/4 -> 0 | CI45: =SUM(CK45+CM45+CO45+CQ45) -> 0 | CJ45: ='Dados da Operação'!G100 -> 0 | CL45: =CJ45/4 -> 0 | CN45: =CJ45/4 -> 0 | CP45: =CJ45/4 -> 0 | CR45: =CJ45/4 -> 0 | CS45: =SUM(CU45+CW45+CY45+DA45) -> 0 | CT45: ='Dados da Operação'!G109 -> 0 | CV45: =CT45/4 -> 0 | CX45: =CT45/4 -> 0 | CZ45: =CT45/4 -> 0 | DB45: =CT45/4 -> 0 | DC45: =SUM(DE45+DG45+DI45+DK45) -> 0 | DD45: ='Dados da Operação'!G118 -> 0 | DF45: =DD45/4 -> 0 | DH45: =DD45/4 -> 0 | DJ45: =DD45/4 -> 0 | DL45: =DD45/4 -> 0 | DM45: =SUM(DO45+DQ45+DS45+DU45) -> 0 | DN45: ='Dados da Operação'!G127 -> 0 | DP45: =DN45/4 -> 0 | DR45: =DN45/4 -> 0 | DT45: =DN45/4 -> 0 | DV45: =DN45/4 -> 0
C46: Ticket médio | D46: =D45/D44 -> #DIV/0! | E46: =E45/E44 -> #DIV/0! | F46: =F45/F44 -> #DIV/0! | G46: ='Dados da Operação'!$C$5 -> 2500 | H46: =G46/F46 -> #DIV/0! | I46: =I45/I44 -> #DIV/0! | J46: =G46 -> 2500 | K46: =K45/K44 -> #DIV/0! | L46: =G46 -> 2500 | M46: =M45/M44 -> #DIV/0! | N46: =G46 -> 2500 | O46: =O45/O44 -> #DIV/0! | P46: =G46 -> 2500 | Q46: =Q45/Q44 -> #DIV/0! | R46: ='Dados da Operação'!$C$5 -> 2500 | S46: =S45/S44 -> #DIV/0! | T46: =R46 -> 2500 | U46: =U45/U44 -> #DIV/0! | V46: =R46 -> 2500 | W46: =W45/W44 -> #DIV/0! | X46: =R46 -> 2500 | Y46: =Y45/Y44 -> #DIV/0! | Z46: =R46 -> 2500 | AA46: =AA45/AA44 -> #DIV/0! | AB46: ='Dados da Operação'!$C$5 -> 2500 | AC46: =AC45/AC44 -> #DIV/0! | AD46: =AB46 -> 2500 | AE46: =AE45/AE44 -> #DIV/0! | AF46: =AB46 -> 2500 | AG46: =AG45/AG44 -> #DIV/0! | AH46: =AB46 -> 2500 | AI46: =AI45/AI44 -> #DIV/0! | AJ46: =AB46 -> 2500 | AK46: =AK45/AK44 -> #DIV/0! | AL46: ='Dados da Operação'!$C$5 -> 2500 | AM46: =AM45/AM44 -> #DIV/0! | AN46: =AL46 -> 2500 | AO46: =AO45/AO44 -> #DIV/0! | AP46: =AL46 -> 2500 | AQ46: =AQ45/AQ44 -> #DIV/0! | AR46: =AL46 -> 2500 | AS46: =AS45/AS44 -> #DIV/0! | AT46: =AL46 -> 2500 | AU46: =AU45/AU44 -> #DIV/0! | AV46: ='Dados da Operação'!$C$5 -> 2500 | AW46: =AW45/AW44 -> #DIV/0! | AX46: =AV46 -> 2500 | AY46: =AY45/AY44 -> #DIV/0! | AZ46: =AV46 -> 2500 | BA46: =BA45/BA44 -> #DIV/0! | BB46: =AV46 -> 2500 | BC46: =BC45/BC44 -> #DIV/0! | BD46: =AV46 -> 2500 | BE46: =BE45/BE44 -> #DIV/0! | BF46: ='Dados da Operação'!$C$5 -> 2500 | BG46: =BG45/BG44 -> #DIV/0! | BH46: =BF46 -> 2500 | BI46: =BI45/BI44 -> #DIV/0! | BJ46: =BF46 -> 2500 | BK46: =BK45/BK44 -> #DIV/0! | BL46: =BF46 -> 2500 | BM46: =BM45/BM44 -> #DIV/0! | BN46: =BF46 -> 2500 | BO46: =BO45/BO44 -> #DIV/0! | BP46: ='Dados da Operação'!$C$5 -> 2500 | BQ46: =BQ45/BQ44 -> #DIV/0! | BR46: =BP46 -> 2500 | BS46: =BS45/BS44 -> #DIV/0! | BT46: =BP46 -> 2500 | BU46: =BU45/BU44 -> #DIV/0! | BV46: =BP46 -> 2500 | BW46: =BW45/BW44 -> #DIV/0! | BX46: =BP46 -> 2500 | BY46: =BY45/BY44 -> #DIV/0! | BZ46: ='Dados da Operação'!$C$5 -> 2500 | CA46: =CA45/CA44 -> #DIV/0! | CB46: =BZ46 -> 2500 | CC46: =CC45/CC44 -> #DIV/0! | CD46: =BZ46 -> 2500 | CE46: =CE45/CE44 -> #DIV/0! | CF46: =BZ46 -> 2500 | CG46: =CG45/CG44 -> #DIV/0! | CH46: =BZ46 -> 2500 | CI46: =CI45/CI44 -> #DIV/0! | CJ46: ='Dados da Operação'!$C$5 -> 2500 | CK46: =CK45/CK44 -> #DIV/0! | CL46: =CJ46 -> 2500 | CM46: =CM45/CM44 -> #DIV/0! | CN46: =CJ46 -> 2500 | CO46: =CO45/CO44 -> #DIV/0! | CP46: =CJ46 -> 2500 | CQ46: =CQ45/CQ44 -> #DIV/0! | CR46: =CJ46 -> 2500 | CS46: =CS45/CS44 -> #DIV/0! | CT46: ='Dados da Operação'!$C$5 -> 2500 | CU46: =CU45/CU44 -> #DIV/0! | CV46: =CT46 -> 2500 | CW46: =CW45/CW44 -> #DIV/0! | CX46: =CT46 -> 2500 | CY46: =CY45/CY44 -> #DIV/0! | CZ46: =CT46 -> 2500 | DA46: =DA45/DA44 -> #DIV/0! | DB46: =CT46 -> 2500 | DC46: =DC45/DC44 -> #DIV/0! | DD46: ='Dados da Operação'!$C$5 -> 2500 | DE46: =DE45/DE44 -> #DIV/0! | DF46: =DD46 -> 2500 | DG46: =DG45/DG44 -> #DIV/0! | DH46: =DD46 -> 2500 | DI46: =DI45/DI44 -> #DIV/0! | DJ46: =DD46 -> 2500 | DK46: =DK45/DK44 -> #DIV/0! | DL46: =DD46 -> 2500 | DM46: =DM45/DM44 -> #DIV/0! | DN46: ='Dados da Operação'!$C$5 -> 2500 | DO46: =DO45/DO44 -> #DIV/0! | DP46: =DN46 -> 2500 | DQ46: =DQ45/DQ44 -> #DIV/0! | DR46: =DN46 -> 2500 | DS46: =DS45/DS44 -> #DIV/0! | DT46: =DN46 -> 2500 | DU46: =DU45/DU44 -> #DIV/0! | DV46: =DN46 -> 2500
B48: RECUPERAÇÃO | C48: Total de cadências abertas | D48: =SUM(F48+Q48+AA48+AK48+AU48+BE48+BO48+BY48+CI48+CS48+DC48+DM48) -> 0 | E48: =SUM(G48+R48+AB48+AL48+AV48+BF48+BP48+BZ48+CJ48+CT48+DD48+DN48) -> 0 | F48: =SUM(I48+K48+M48+O48) -> 0 | G48: =G50/G49 -> 0 | H48: =F48/G48 -> #DIV/0! | J48: =G48/4 -> 0 | L48: =G48/4 -> 0 | N48: =G48/4 -> 0 | P48: =G48/4 -> 0 | Q48: =SUM(S48+U48+W48+Y48) -> 0 | R48: =R50/R49 -> 0 | T48: =R48/4 -> 0 | V48: =R48/4 -> 0 | X48: =R48/4 -> 0 | Z48: =R48/4 -> 0 | AA48: =SUM(AC48+AE48+AG48+AI48) -> 0 | AB48: =AB50/AB49 -> 0 | AD48: =AB48/4 -> 0 | AF48: =AB48/4 -> 0 | AH48: =AB48/4 -> 0 | AJ48: =AB48/4 -> 0 | AK48: =SUM(AM48+AO48+AQ48+AS48) -> 0 | AL48: =AL50/AL49 -> 0 | AN48: =AL48/4 -> 0 | AP48: =AL48/4 -> 0 | AR48: =AL48/4 -> 0 | AT48: =AL48/4 -> 0 | AU48: =SUM(AW48+AY48+BA48+BC48) -> 0 | AV48: =AV50/AV49 -> 0 | AX48: =AV48/4 -> 0 | AZ48: =AV48/4 -> 0 | BB48: =AV48/4 -> 0 | BD48: =AV48/4 -> 0 | BE48: =SUM(BG48+BI48+BK48+BM48) -> 0 | BF48: =BF50/BF49 -> 0 | BH48: =BF48/4 -> 0 | BJ48: =BF48/4 -> 0 | BL48: =BF48/4 -> 0 | BN48: =BF48/4 -> 0 | BO48: =SUM(BQ48+BS48+BU48+BW48) -> 0 | BP48: =BP50/BP49 -> 0 | BR48: =BP48/4 -> 0 | BT48: =BP48/4 -> 0 | BV48: =BP48/4 -> 0 | BX48: =BP48/4 -> 0 | BY48: =SUM(CA48+CC48+CE48+CG48) -> 0 | BZ48: =BZ50/BZ49 -> 0 | CB48: =BZ48/4 -> 0 | CD48: =BZ48/4 -> 0 | CF48: =BZ48/4 -> 0 | CH48: =BZ48/4 -> 0 | CI48: =SUM(CK48+CM48+CO48+CQ48) -> 0 | CJ48: =CJ50/CJ49 -> 0 | CL48: =CJ48/4 -> 0 | CN48: =CJ48/4 -> 0 | CP48: =CJ48/4 -> 0 | CR48: =CJ48/4 -> 0 | CS48: =SUM(CU48+CW48+CY48+DA48) -> 0 | CT48: =CT50/CT49 -> 0 | CV48: =CT48/4 -> 0 | CX48: =CT48/4 -> 0 | CZ48: =CT48/4 -> 0 | DB48: =CT48/4 -> 0 | DC48: =SUM(DE48+DG48+DI48+DK48) -> 0 | DD48: =DD50/DD49 -> 0 | DF48: =DD48/4 -> 0 | DH48: =DD48/4 -> 0 | DJ48: =DD48/4 -> 0 | DL48: =DD48/4 -> 0 | DM48: =SUM(DO48+DQ48+DS48+DU48) -> 0 | DN48: =DN50/DN49 -> 0 | DP48: =DN48/4 -> 0 | DR48: =DN48/4 -> 0 | DT48: =DN48/4 -> 0 | DV48: =DN48/4 -> 0
C49: % Conversão em Lead Conectado | D49: =D50/D48 -> #DIV/0! | E49: =E50/E48 -> #DIV/0! | F49: =F50/F48 -> #DIV/0! | G49: 0.6 | H49: - | I49: =I50/I48 -> #DIV/0! | J49: =G49 -> 0.6 | K49: =K50/K48 -> #DIV/0! | L49: =G49 -> 0.6 | M49: =M50/M48 -> #DIV/0! | N49: =G49 -> 0.6 | O49: =O50/O48 -> #DIV/0! | P49: =G49 -> 0.6 | Q49: =Q50/Q48 -> #DIV/0! | R49: 0.6 | S49: =S50/S48 -> #DIV/0! | T49: =R49 -> 0.6 | U49: =U50/U48 -> #DIV/0! | V49: =R49 -> 0.6 | W49: =W50/W48 -> #DIV/0! | X49: =R49 -> 0.6 | Y49: =Y50/Y48 -> #DIV/0! | Z49: =R49 -> 0.6 | AA49: =AA50/AA48 -> #DIV/0! | AB49: 0.6 | AC49: =AC50/AC48 -> #DIV/0! | AD49: =AB49 -> 0.6 | AE49: =AE50/AE48 -> #DIV/0! | AF49: =AB49 -> 0.6 | AG49: =AG50/AG48 -> #DIV/0! | AH49: =AB49 -> 0.6 | AI49: =AI50/AI48 -> #DIV/0! | AJ49: =AB49 -> 0.6 | AK49: =AK50/AK48 -> #DIV/0! | AL49: 0.6 | AM49: =AM50/AM48 -> #DIV/0! | AN49: =AL49 -> 0.6 | AO49: =AO50/AO48 -> #DIV/0! | AP49: =AL49 -> 0.6 | AQ49: =AQ50/AQ48 -> #DIV/0! | AR49: =AL49 -> 0.6 | AS49: =AS50/AS48 -> #DIV/0! | AT49: =AL49 -> 0.6 | AU49: =AU50/AU48 -> #DIV/0! | AV49: 0.6 | AW49: =AW50/AW48 -> #DIV/0! | AX49: =AV49 -> 0.6 | AY49: =AY50/AY48 -> #DIV/0! | AZ49: =AV49 -> 0.6 | BA49: =BA50/BA48 -> #DIV/0! | BB49: =AV49 -> 0.6 | BC49: =BC50/BC48 -> #DIV/0! | BD49: =AV49 -> 0.6 | BE49: =BE50/BE48 -> #DIV/0! | BF49: 0.6 | BG49: =BG50/BG48 -> #DIV/0! | BH49: =BF49 -> 0.6 | BI49: =BI50/BI48 -> #DIV/0! | BJ49: =BF49 -> 0.6 | BK49: =BK50/BK48 -> #DIV/0! | BL49: =BF49 -> 0.6 | BM49: =BM50/BM48 -> #DIV/0! | BN49: =BF49 -> 0.6 | BO49: =BO50/BO48 -> #DIV/0! | BP49: 0.6 | BQ49: =BQ50/BQ48 -> #DIV/0! | BR49: =BP49 -> 0.6 | BS49: =BS50/BS48 -> #DIV/0! | BT49: =BP49 -> 0.6 | BU49: =BU50/BU48 -> #DIV/0! | BV49: =BP49 -> 0.6 | BW49: =BW50/BW48 -> #DIV/0! | BX49: =BP49 -> 0.6 | BY49: =BY50/BY48 -> #DIV/0! | BZ49: 0.6 | CA49: =CA50/CA48 -> #DIV/0! | CB49: =BZ49 -> 0.6 | CC49: =CC50/CC48 -> #DIV/0! | CD49: =BZ49 -> 0.6 | CE49: =CE50/CE48 -> #DIV/0! | CF49: =BZ49 -> 0.6 | CG49: =CG50/CG48 -> #DIV/0! | CH49: =BZ49 -> 0.6 | CI49: =CI50/CI48 -> #DIV/0! | CJ49: 0.6 | CK49: =CK50/CK48 -> #DIV/0! | CL49: =CJ49 -> 0.6 | CM49: =CM50/CM48 -> #DIV/0! | CN49: =CJ49 -> 0.6 | CO49: =CO50/CO48 -> #DIV/0! | CP49: =CJ49 -> 0.6 | CQ49: =CQ50/CQ48 -> #DIV/0! | CR49: =CJ49 -> 0.6 | CS49: =CS50/CS48 -> #DIV/0! | CT49: 0.6 | CU49: =CU50/CU48 -> #DIV/0! | CV49: =CT49 -> 0.6 | CW49: =CW50/CW48 -> #DIV/0! | CX49: =CT49 -> 0.6 | CY49: =CY50/CY48 -> #DIV/0! | CZ49: =CT49 -> 0.6 | DA49: =DA50/DA48 -> #DIV/0! | DB49: =CT49 -> 0.6 | DC49: =DC50/DC48 -> #DIV/0! | DD49: 0.6 | DE49: =DE50/DE48 -> #DIV/0! | DF49: =DD49 -> 0.6 | DG49: =DG50/DG48 -> #DIV/0! | DH49: =DD49 -> 0.6 | DI49: =DI50/DI48 -> #DIV/0! | DJ49: =DD49 -> 0.6 | DK49: =DK50/DK48 -> #DIV/0! | DL49: =DD49 -> 0.6 | DM49: =DM50/DM48 -> #DIV/0! | DN49: 0.6 | DO49: =DO50/DO48 -> #DIV/0! | DP49: =DN49 -> 0.6 | DQ49: =DQ50/DQ48 -> #DIV/0! | DR49: =DN49 -> 0.6 | DS49: =DS50/DS48 -> #DIV/0! | DT49: =DN49 -> 0.6 | DU49: =DU50/DU48 -> #DIV/0! | DV49: =DN49 -> 0.6
C50: Total de leads conectados | D50: =SUM(F50+Q50+AA50+AK50+AU50+BE50+BO50+BY50+CI50+CS50+DC50+DM50) -> 0 | E50: =SUM(G50+R50+AB50+AL50+AV50+BF50+BP50+BZ50+CJ50+CT50+DD50+DN50) -> 0 | F50: =SUM(I50+K50+M50+O50) -> 0 | G50: =G52/G51 -> 0 | H50: =G50/F50 -> #DIV/0! | J50: =G50/4 -> 0 | L50: =G50/4 -> 0 | N50: =G50/4 -> 0 | P50: =G50/4 -> 0 | Q50: =SUM(S50+U50+W50+Y50) -> 0 | R50: =R52/R51 -> 0 | T50: =R50/4 -> 0 | V50: =R50/4 -> 0 | X50: =R50/4 -> 0 | Z50: =R50/4 -> 0 | AA50: =SUM(AC50+AE50+AG50+AI50) -> 0 | AB50: =AB52/AB51 -> 0 | AD50: =AB50/4 -> 0 | AF50: =AB50/4 -> 0 | AH50: =AB50/4 -> 0 | AJ50: =AB50/4 -> 0 | AK50: =SUM(AM50+AO50+AQ50+AS50) -> 0 | AL50: =AL52/AL51 -> 0 | AN50: =AL50/4 -> 0 | AP50: =AL50/4 -> 0 | AR50: =AL50/4 -> 0 | AT50: =AL50/4 -> 0 | AU50: =SUM(AW50+AY50+BA50+BC50) -> 0 | AV50: =AV52/AV51 -> 0 | AX50: =AV50/4 -> 0 | AZ50: =AV50/4 -> 0 | BB50: =AV50/4 -> 0 | BD50: =AV50/4 -> 0 | BE50: =SUM(BG50+BI50+BK50+BM50) -> 0 | BF50: =BF52/BF51 -> 0 | BH50: =BF50/4 -> 0 | BJ50: =BF50/4 -> 0 | BL50: =BF50/4 -> 0 | BN50: =BF50/4 -> 0 | BO50: =SUM(BQ50+BS50+BU50+BW50) -> 0 | BP50: =BP52/BP51 -> 0 | BR50: =BP50/4 -> 0 | BT50: =BP50/4 -> 0 | BV50: =BP50/4 -> 0 | BX50: =BP50/4 -> 0 | BY50: =SUM(CA50+CC50+CE50+CG50) -> 0 | BZ50: =BZ52/BZ51 -> 0 | CB50: =BZ50/4 -> 0 | CD50: =BZ50/4 -> 0 | CF50: =BZ50/4 -> 0 | CH50: =BZ50/4 -> 0 | CI50: =SUM(CK50+CM50+CO50+CQ50) -> 0 | CJ50: =CJ52/CJ51 -> 0 | CL50: =CJ50/4 -> 0 | CN50: =CJ50/4 -> 0 | CP50: =CJ50/4 -> 0 | CR50: =CJ50/4 -> 0 | CS50: =SUM(CU50+CW50+CY50+DA50) -> 0 | CT50: =CT52/CT51 -> 0 | CV50: =CT50/4 -> 0 | CX50: =CT50/4 -> 0 | CZ50: =CT50/4 -> 0 | DB50: =CT50/4 -> 0 | DC50: =SUM(DE50+DG50+DI50+DK50) -> 0 | DD50: =DD52/DD51 -> 0 | DF50: =DD50/4 -> 0 | DH50: =DD50/4 -> 0 | DJ50: =DD50/4 -> 0 | DL50: =DD50/4 -> 0 | DM50: =SUM(DO50+DQ50+DS50+DU50) -> 0 | DN50: =DN52/DN51 -> 0 | DP50: =DN50/4 -> 0 | DR50: =DN50/4 -> 0 | DT50: =DN50/4 -> 0 | DV50: =DN50/4 -> 0
C51: % Conversão em Reunião agendada | D51: =D52/D50 -> #DIV/0! | E51: =E52/E50 -> #DIV/0! | F51: =F52/F50 -> #DIV/0! | G51: 0.4 | H51: - | I51: =I52/I50 -> #DIV/0! | J51: =G51 -> 0.4 | K51: =K52/K50 -> #DIV/0! | L51: =G51 -> 0.4 | M51: =M52/M50 -> #DIV/0! | N51: =G51 -> 0.4 | O51: =O52/O50 -> #DIV/0! | P51: =G51 -> 0.4 | Q51: =Q52/Q50 -> #DIV/0! | R51: 0.4 | S51: =S52/S50 -> #DIV/0! | T51: =R51 -> 0.4 | U51: =U52/U50 -> #DIV/0! | V51: =R51 -> 0.4 | W51: =W52/W50 -> #DIV/0! | X51: =R51 -> 0.4 | Y51: =Y52/Y50 -> #DIV/0! | Z51: =R51 -> 0.4 | AA51: =AA52/AA50 -> #DIV/0! | AB51: 0.4 | AC51: =AC52/AC50 -> #DIV/0! | AD51: =AB51 -> 0.4 | AE51: =AE52/AE50 -> #DIV/0! | AF51: =AB51 -> 0.4 | AG51: =AG52/AG50 -> #DIV/0! | AH51: =AB51 -> 0.4 | AI51: =AI52/AI50 -> #DIV/0! | AJ51: =AB51 -> 0.4 | AK51: =AK52/AK50 -> #DIV/0! | AL51: 0.4 | AM51: =AM52/AM50 -> #DIV/0! | AN51: =AL51 -> 0.4 | AO51: =AO52/AO50 -> #DIV/0! | AP51: =AL51 -> 0.4 | AQ51: =AQ52/AQ50 -> #DIV/0! | AR51: =AL51 -> 0.4 | AS51: =AS52/AS50 -> #DIV/0! | AT51: =AL51 -> 0.4 | AU51: =AU52/AU50 -> #DIV/0! | AV51: 0.4 | AW51: =AW52/AW50 -> #DIV/0! | AX51: =AV51 -> 0.4 | AY51: =AY52/AY50 -> #DIV/0! | AZ51: =AV51 -> 0.4 | BA51: =BA52/BA50 -> #DIV/0! | BB51: =AV51 -> 0.4 | BC51: =BC52/BC50 -> #DIV/0! | BD51: =AV51 -> 0.4 | BE51: =BE52/BE50 -> #DIV/0! | BF51: 0.4 | BG51: =BG52/BG50 -> #DIV/0! | BH51: =BF51 -> 0.4 | BI51: =BI52/BI50 -> #DIV/0! | BJ51: =BF51 -> 0.4 | BK51: =BK52/BK50 -> #DIV/0! | BL51: =BF51 -> 0.4 | BM51: =BM52/BM50 -> #DIV/0! | BN51: =BF51 -> 0.4 | BO51: =BO52/BO50 -> #DIV/0! | BP51: 0.4 | BQ51: =BQ52/BQ50 -> #DIV/0! | BR51: =BP51 -> 0.4 | BS51: =BS52/BS50 -> #DIV/0! | BT51: =BP51 -> 0.4 | BU51: =BU52/BU50 -> #DIV/0! | BV51: =BP51 -> 0.4 | BW51: =BW52/BW50 -> #DIV/0! | BX51: =BP51 -> 0.4 | BY51: =BY52/BY50 -> #DIV/0! | BZ51: 0.4 | CA51: =CA52/CA50 -> #DIV/0! | CB51: =BZ51 -> 0.4 | CC51: =CC52/CC50 -> #DIV/0! | CD51: =BZ51 -> 0.4 | CE51: =CE52/CE50 -> #DIV/0! | CF51: =BZ51 -> 0.4 | CG51: =CG52/CG50 -> #DIV/0! | CH51: =BZ51 -> 0.4 | CI51: =CI52/CI50 -> #DIV/0! | CJ51: 0.4 | CK51: =CK52/CK50 -> #DIV/0! | CL51: =CJ51 -> 0.4 | CM51: =CM52/CM50 -> #DIV/0! | CN51: =CJ51 -> 0.4 | CO51: =CO52/CO50 -> #DIV/0! | CP51: =CJ51 -> 0.4 | CQ51: =CQ52/CQ50 -> #DIV/0! | CR51: =CJ51 -> 0.4 | CS51: =CS52/CS50 -> #DIV/0! | CT51: 0.4 | CU51: =CU52/CU50 -> #DIV/0! | CV51: =CT51 -> 0.4 | CW51: =CW52/CW50 -> #DIV/0! | CX51: =CT51 -> 0.4 | CY51: =CY52/CY50 -> #DIV/0! | CZ51: =CT51 -> 0.4 | DA51: =DA52/DA50 -> #DIV/0! | DB51: =CT51 -> 0.4 | DC51: =DC52/DC50 -> #DIV/0! | DD51: 0.4 | DE51: =DE52/DE50 -> #DIV/0! | DF51: =DD51 -> 0.4 | DG51: =DG52/DG50 -> #DIV/0! | DH51: =DD51 -> 0.4 | DI51: =DI52/DI50 -> #DIV/0! | DJ51: =DD51 -> 0.4 | DK51: =DK52/DK50 -> #DIV/0! | DL51: =DD51 -> 0.4 | DM51: =DM52/DM50 -> #DIV/0! | DN51: 0.4 | DO51: =DO52/DO50 -> #DIV/0! | DP51: =DN51 -> 0.4 | DQ51: =DQ52/DQ50 -> #DIV/0! | DR51: =DN51 -> 0.4 | DS51: =DS52/DS50 -> #DIV/0! | DT51: =DN51 -> 0.4 | DU51: =DU52/DU50 -> #DIV/0! | DV51: =DN51 -> 0.4
C52: Total de reuniões agendadas | D52: =SUM(F52+Q52+AA52+AK52+AU52+BE52+BO52+BY52+CI52+CS52+DC52+DM52) -> 0 | E52: =SUM(G52+R52+AB52+AL52+AV52+BF52+BP52+BZ52+CJ52+CT52+DD52+DN52) -> 0 | F52: =SUM(I52+K52+M52+O52) -> 0 | G52: =G54/G53 -> 0 | H52: =G52/F52 -> #DIV/0! | J52: =G52/4 -> 0 | L52: =G52/4 -> 0 | N52: =G52/4 -> 0 | P52: =G52/4 -> 0 | Q52: =SUM(S52+U52+W52+Y52) -> 0 | R52: =R54/R53 -> 0 | T52: =R52/4 -> 0 | V52: =R52/4 -> 0 | X52: =R52/4 -> 0 | Z52: =R52/4 -> 0 | AA52: =SUM(AC52+AE52+AG52+AI52) -> 0 | AB52: =AB54/AB53 -> 0 | AD52: =AB52/4 -> 0 | AF52: =AB52/4 -> 0 | AH52: =AB52/4 -> 0 | AJ52: =AB52/4 -> 0 | AK52: =SUM(AM52+AO52+AQ52+AS52) -> 0 | AL52: =AL54/AL53 -> 0 | AN52: =AL52/4 -> 0 | AP52: =AL52/4 -> 0 | AR52: =AL52/4 -> 0 | AT52: =AL52/4 -> 0 | AU52: =SUM(AW52+AY52+BA52+BC52) -> 0 | AV52: =AV54/AV53 -> 0 | AX52: =AV52/4 -> 0 | AZ52: =AV52/4 -> 0 | BB52: =AV52/4 -> 0 | BD52: =AV52/4 -> 0 | BE52: =SUM(BG52+BI52+BK52+BM52) -> 0 | BF52: =BF54/BF53 -> 0 | BH52: =BF52/4 -> 0 | BJ52: =BF52/4 -> 0 | BL52: =BF52/4 -> 0 | BN52: =BF52/4 -> 0 | BO52: =SUM(BQ52+BS52+BU52+BW52) -> 0 | BP52: =BP54/BP53 -> 0 | BR52: =BP52/4 -> 0 | BT52: =BP52/4 -> 0 | BV52: =BP52/4 -> 0 | BX52: =BP52/4 -> 0 | BY52: =SUM(CA52+CC52+CE52+CG52) -> 0 | BZ52: =BZ54/BZ53 -> 0 | CB52: =BZ52/4 -> 0 | CD52: =BZ52/4 -> 0 | CF52: =BZ52/4 -> 0 | CH52: =BZ52/4 -> 0 | CI52: =SUM(CK52+CM52+CO52+CQ52) -> 0 | CJ52: =CJ54/CJ53 -> 0 | CL52: =CJ52/4 -> 0 | CN52: =CJ52/4 -> 0 | CP52: =CJ52/4 -> 0 | CR52: =CJ52/4 -> 0 | CS52: =SUM(CU52+CW52+CY52+DA52) -> 0 | CT52: =CT54/CT53 -> 0 | CV52: =CT52/4 -> 0 | CX52: =CT52/4 -> 0 | CZ52: =CT52/4 -> 0 | DB52: =CT52/4 -> 0 | DC52: =SUM(DE52+DG52+DI52+DK52) -> 0 | DD52: =DD54/DD53 -> 0 | DF52: =DD52/4 -> 0 | DH52: =DD52/4 -> 0 | DJ52: =DD52/4 -> 0 | DL52: =DD52/4 -> 0 | DM52: =SUM(DO52+DQ52+DS52+DU52) -> 0 | DN52: =DN54/DN53 -> 0 | DP52: =DN52/4 -> 0 | DR52: =DN52/4 -> 0 | DT52: =DN52/4 -> 0 | DV52: =DN52/4 -> 0
C53: % de reunião realizada | D53: =D54/D52 -> #DIV/0! | E53: =E54/E52 -> #DIV/0! | F53: =F54/F52 -> #DIV/0! | G53: 0.9 | H53: - | I53: =I54/I52 -> #DIV/0! | J53: =G53 -> 0.9 | K53: =K54/K52 -> #DIV/0! | L53: =G53 -> 0.9 | M53: =M54/M52 -> #DIV/0! | N53: =G53 -> 0.9 | O53: =O54/O52 -> #DIV/0! | P53: =G53 -> 0.9 | Q53: =Q54/Q52 -> #DIV/0! | R53: 0.9 | S53: =S54/S52 -> #DIV/0! | T53: =R53 -> 0.9 | U53: =U54/U52 -> #DIV/0! | V53: =R53 -> 0.9 | W53: =W54/W52 -> #DIV/0! | X53: =R53 -> 0.9 | Y53: =Y54/Y52 -> #DIV/0! | Z53: =R53 -> 0.9 | AA53: =AA54/AA52 -> #DIV/0! | AB53: 0.9 | AC53: =AC54/AC52 -> #DIV/0! | AD53: =AB53 -> 0.9 | AE53: =AE54/AE52 -> #DIV/0! | AF53: =AB53 -> 0.9 | AG53: =AG54/AG52 -> #DIV/0! | AH53: =AB53 -> 0.9 | AI53: =AI54/AI52 -> #DIV/0! | AJ53: =AB53 -> 0.9 | AK53: =AK54/AK52 -> #DIV/0! | AL53: 0.9 | AM53: =AM54/AM52 -> #DIV/0! | AN53: =AL53 -> 0.9 | AO53: =AO54/AO52 -> #DIV/0! | AP53: =AL53 -> 0.9 | AQ53: =AQ54/AQ52 -> #DIV/0! | AR53: =AL53 -> 0.9 | AS53: =AS54/AS52 -> #DIV/0! | AT53: =AL53 -> 0.9 | AU53: =AU54/AU52 -> #DIV/0! | AV53: 0.9 | AW53: =AW54/AW52 -> #DIV/0! | AX53: =AV53 -> 0.9 | AY53: =AY54/AY52 -> #DIV/0! | AZ53: =AV53 -> 0.9 | BA53: =BA54/BA52 -> #DIV/0! | BB53: =AV53 -> 0.9 | BC53: =BC54/BC52 -> #DIV/0! | BD53: =AV53 -> 0.9 | BE53: =BE54/BE52 -> #DIV/0! | BF53: 0.9 | BG53: =BG54/BG52 -> #DIV/0! | BH53: =BF53 -> 0.9 | BI53: =BI54/BI52 -> #DIV/0! | BJ53: =BF53 -> 0.9 | BK53: =BK54/BK52 -> #DIV/0! | BL53: =BF53 -> 0.9 | BM53: =BM54/BM52 -> #DIV/0! | BN53: =BF53 -> 0.9 | BO53: =BO54/BO52 -> #DIV/0! | BP53: 0.9 | BQ53: =BQ54/BQ52 -> #DIV/0! | BR53: =BP53 -> 0.9 | BS53: =BS54/BS52 -> #DIV/0! | BT53: =BP53 -> 0.9 | BU53: =BU54/BU52 -> #DIV/0! | BV53: =BP53 -> 0.9 | BW53: =BW54/BW52 -> #DIV/0! | BX53: =BP53 -> 0.9 | BY53: =BY54/BY52 -> #DIV/0! | BZ53: 0.9 | CA53: =CA54/CA52 -> #DIV/0! | CB53: =BZ53 -> 0.9 | CC53: =CC54/CC52 -> #DIV/0! | CD53: =BZ53 -> 0.9 | CE53: =CE54/CE52 -> #DIV/0! | CF53: =BZ53 -> 0.9 | CG53: =CG54/CG52 -> #DIV/0! | CH53: =BZ53 -> 0.9 | CI53: =CI54/CI52 -> #DIV/0! | CJ53: 0.9 | CK53: =CK54/CK52 -> #DIV/0! | CL53: =CJ53 -> 0.9 | CM53: =CM54/CM52 -> #DIV/0! | CN53: =CJ53 -> 0.9 | CO53: =CO54/CO52 -> #DIV/0! | CP53: =CJ53 -> 0.9 | CQ53: =CQ54/CQ52 -> #DIV/0! | CR53: =CJ53 -> 0.9 | CS53: =CS54/CS52 -> #DIV/0! | CT53: 0.9 | CU53: =CU54/CU52 -> #DIV/0! | CV53: =CT53 -> 0.9 | CW53: =CW54/CW52 -> #DIV/0! | CX53: =CT53 -> 0.9 | CY53: =CY54/CY52 -> #DIV/0! | CZ53: =CT53 -> 0.9 | DA53: =DA54/DA52 -> #DIV/0! | DB53: =CT53 -> 0.9 | DC53: =DC54/DC52 -> #DIV/0! | DD53: 0.9 | DE53: =DE54/DE52 -> #DIV/0! | DF53: =DD53 -> 0.9 | DG53: =DG54/DG52 -> #DIV/0! | DH53: =DD53 -> 0.9 | DI53: =DI54/DI52 -> #DIV/0! | DJ53: =DD53 -> 0.9 | DK53: =DK54/DK52 -> #DIV/0! | DL53: =DD53 -> 0.9 | DM53: =DM54/DM52 -> #DIV/0! | DN53: 0.9 | DO53: =DO54/DO52 -> #DIV/0! | DP53: =DN53 -> 0.9 | DQ53: =DQ54/DQ52 -> #DIV/0! | DR53: =DN53 -> 0.9 | DS53: =DS54/DS52 -> #DIV/0! | DT53: =DN53 -> 0.9 | DU53: =DU54/DU52 -> #DIV/0! | DV53: =DN53 -> 0.9
C54: Total de reuniões realizadas | D54: =SUM(F54+Q54+AA54+AK54+AU54+BE54+BO54+BY54+CI54+CS54+DC54+DM54) -> 0 | E54: =SUM(G54+R54+AB54+AL54+AV54+BF54+BP54+BZ54+CJ54+CT54+DD54+DN54) -> 0 | F54: =SUM(I54+K54+M54+O54) -> 0 | G54: =G56/G55 -> 0 | H54: =G54/F54 -> #DIV/0! | J54: =G54/4 -> 0 | L54: =G54/4 -> 0 | N54: =G54/4 -> 0 | P54: =G54/4 -> 0 | Q54: =SUM(S54+U54+W54+Y54) -> 0 | R54: =R56/R55 -> 0 | T54: =R54/4 -> 0 | V54: =R54/4 -> 0 | X54: =R54/4 -> 0 | Z54: =R54/4 -> 0 | AA54: =SUM(AC54+AE54+AG54+AI54) -> 0 | AB54: =AB56/AB55 -> 0 | AD54: =AB54/4 -> 0 | AF54: =AB54/4 -> 0 | AH54: =AB54/4 -> 0 | AJ54: =AB54/4 -> 0 | AK54: =SUM(AM54+AO54+AQ54+AS54) -> 0 | AL54: =AL56/AL55 -> 0 | AN54: =AL54/4 -> 0 | AP54: =AL54/4 -> 0 | AR54: =AL54/4 -> 0 | AT54: =AL54/4 -> 0 | AU54: =SUM(AW54+AY54+BA54+BC54) -> 0 | AV54: =AV56/AV55 -> 0 | AX54: =AV54/4 -> 0 | AZ54: =AV54/4 -> 0 | BB54: =AV54/4 -> 0 | BD54: =AV54/4 -> 0 | BE54: =SUM(BG54+BI54+BK54+BM54) -> 0 | BF54: =BF56/BF55 -> 0 | BH54: =BF54/4 -> 0 | BJ54: =BF54/4 -> 0 | BL54: =BF54/4 -> 0 | BN54: =BF54/4 -> 0 | BO54: =SUM(BQ54+BS54+BU54+BW54) -> 0 | BP54: =BP56/BP55 -> 0 | BR54: =BP54/4 -> 0 | BT54: =BP54/4 -> 0 | BV54: =BP54/4 -> 0 | BX54: =BP54/4 -> 0 | BY54: =SUM(CA54+CC54+CE54+CG54) -> 0 | BZ54: =BZ56/BZ55 -> 0 | CB54: =BZ54/4 -> 0 | CD54: =BZ54/4 -> 0 | CF54: =BZ54/4 -> 0 | CH54: =BZ54/4 -> 0 | CI54: =SUM(CK54+CM54+CO54+CQ54) -> 0 | CJ54: =CJ56/CJ55 -> 0 | CL54: =CJ54/4 -> 0 | CN54: =CJ54/4 -> 0 | CP54: =CJ54/4 -> 0 | CR54: =CJ54/4 -> 0 | CS54: =SUM(CU54+CW54+CY54+DA54) -> 0 | CT54: =CT56/CT55 -> 0 | CV54: =CT54/4 -> 0 | CX54: =CT54/4 -> 0 | CZ54: =CT54/4 -> 0 | DB54: =CT54/4 -> 0 | DC54: =SUM(DE54+DG54+DI54+DK54) -> 0 | DD54: =DD56/DD55 -> 0 | DF54: =DD54/4 -> 0 | DH54: =DD54/4 -> 0 | DJ54: =DD54/4 -> 0 | DL54: =DD54/4 -> 0 | DM54: =SUM(DO54+DQ54+DS54+DU54) -> 0 | DN54: =DN56/DN55 -> 0 | DP54: =DN54/4 -> 0 | DR54: =DN54/4 -> 0 | DT54: =DN54/4 -> 0 | DV54: =DN54/4 -> 0
C55: % de propostas apresentadas | D55: =D56/D54 -> #DIV/0! | E55: =E56/E54 -> #DIV/0! | F55: =F56/F54 -> #DIV/0! | G55: 0.7 | H55: - | I55: =I56/I54 -> #DIV/0! | J55: =G55 -> 0.7 | K55: =K56/K54 -> #DIV/0! | L55: =G55 -> 0.7 | M55: =M56/M54 -> #DIV/0! | N55: =G55 -> 0.7 | O55: =O56/O54 -> #DIV/0! | P55: =G55 -> 0.7 | Q55: =Q56/Q54 -> #DIV/0! | R55: 0.7 | S55: =S56/S54 -> #DIV/0! | T55: =R55 -> 0.7 | U55: =U56/U54 -> #DIV/0! | V55: =R55 -> 0.7 | W55: =W56/W54 -> #DIV/0! | X55: =R55 -> 0.7 | Y55: =Y56/Y54 -> #DIV/0! | Z55: =R55 -> 0.7 | AA55: =AA56/AA54 -> #DIV/0! | AB55: 0.7 | AC55: =AC56/AC54 -> #DIV/0! | AD55: =AB55 -> 0.7 | AE55: =AE56/AE54 -> #DIV/0! | AF55: =AB55 -> 0.7 | AG55: =AG56/AG54 -> #DIV/0! | AH55: =AB55 -> 0.7 | AI55: =AI56/AI54 -> #DIV/0! | AJ55: =AB55 -> 0.7 | AK55: =AK56/AK54 -> #DIV/0! | AL55: 0.7 | AM55: =AM56/AM54 -> #DIV/0! | AN55: =AL55 -> 0.7 | AO55: =AO56/AO54 -> #DIV/0! | AP55: =AL55 -> 0.7 | AQ55: =AQ56/AQ54 -> #DIV/0! | AR55: =AL55 -> 0.7 | AS55: =AS56/AS54 -> #DIV/0! | AT55: =AL55 -> 0.7 | AU55: =AU56/AU54 -> #DIV/0! | AV55: 0.7 | AW55: =AW56/AW54 -> #DIV/0! | AX55: =AV55 -> 0.7 | AY55: =AY56/AY54 -> #DIV/0! | AZ55: =AV55 -> 0.7 | BA55: =BA56/BA54 -> #DIV/0! | BB55: =AV55 -> 0.7 | BC55: =BC56/BC54 -> #DIV/0! | BD55: =AV55 -> 0.7 | BE55: =BE56/BE54 -> #DIV/0! | BF55: 0.7 | BG55: =BG56/BG54 -> #DIV/0! | BH55: =BF55 -> 0.7 | BI55: =BI56/BI54 -> #DIV/0! | BJ55: =BF55 -> 0.7 | BK55: =BK56/BK54 -> #DIV/0! | BL55: =BF55 -> 0.7 | BM55: =BM56/BM54 -> #DIV/0! | BN55: =BF55 -> 0.7 | BO55: =BO56/BO54 -> #DIV/0! | BP55: 0.7 | BQ55: =BQ56/BQ54 -> #DIV/0! | BR55: =BP55 -> 0.7 | BS55: =BS56/BS54 -> #DIV/0! | BT55: =BP55 -> 0.7 | BU55: =BU56/BU54 -> #DIV/0! | BV55: =BP55 -> 0.7 | BW55: =BW56/BW54 -> #DIV/0! | BX55: =BP55 -> 0.7 | BY55: =BY56/BY54 -> #DIV/0! | BZ55: 0.7 | CA55: =CA56/CA54 -> #DIV/0! | CB55: =BZ55 -> 0.7 | CC55: =CC56/CC54 -> #DIV/0! | CD55: =BZ55 -> 0.7 | CE55: =CE56/CE54 -> #DIV/0! | CF55: =BZ55 -> 0.7 | CG55: =CG56/CG54 -> #DIV/0! | CH55: =BZ55 -> 0.7 | CI55: =CI56/CI54 -> #DIV/0! | CJ55: 0.7 | CK55: =CK56/CK54 -> #DIV/0! | CL55: =CJ55 -> 0.7 | CM55: =CM56/CM54 -> #DIV/0! | CN55: =CJ55 -> 0.7 | CO55: =CO56/CO54 -> #DIV/0! | CP55: =CJ55 -> 0.7 | CQ55: =CQ56/CQ54 -> #DIV/0! | CR55: =CJ55 -> 0.7 | CS55: =CS56/CS54 -> #DIV/0! | CT55: 0.7 | CU55: =CU56/CU54 -> #DIV/0! | CV55: =CT55 -> 0.7 | CW55: =CW56/CW54 -> #DIV/0! | CX55: =CT55 -> 0.7 | CY55: =CY56/CY54 -> #DIV/0! | CZ55: =CT55 -> 0.7 | DA55: =DA56/DA54 -> #DIV/0! | DB55: =CT55 -> 0.7 | DC55: =DC56/DC54 -> #DIV/0! | DD55: 0.7 | DE55: =DE56/DE54 -> #DIV/0! | DF55: =DD55 -> 0.7 | DG55: =DG56/DG54 -> #DIV/0! | DH55: =DD55 -> 0.7 | DI55: =DI56/DI54 -> #DIV/0! | DJ55: =DD55 -> 0.7 | DK55: =DK56/DK54 -> #DIV/0! | DL55: =DD55 -> 0.7 | DM55: =DM56/DM54 -> #DIV/0! | DN55: 0.7 | DO55: =DO56/DO54 -> #DIV/0! | DP55: =DN55 -> 0.7 | DQ55: =DQ56/DQ54 -> #DIV/0! | DR55: =DN55 -> 0.7 | DS55: =DS56/DS54 -> #DIV/0! | DT55: =DN55 -> 0.7 | DU55: =DU56/DU54 -> #DIV/0! | DV55: =DN55 -> 0.7
C56: Total de propostas apresentadas | D56: =SUM(F56+Q56+AA56+AK56+AU56+BE56+BO56+BY56+CI56+CS56+DC56+DM56) -> 0 | E56: =SUM(G56+R56+AB56+AL56+AV56+BF56+BP56+BZ56+CJ56+CT56+DD56+DN56) -> 0 | F56: =SUM(I56+K56+M56+O56) -> 0 | G56: =G58/G57 -> 0 | H56: =G56/F56 -> #DIV/0! | J56: =G56/4 -> 0 | L56: =G56/4 -> 0 | N56: =G56/4 -> 0 | P56: =G56/4 -> 0 | Q56: =SUM(S56+U56+W56+Y56) -> 0 | R56: =R58/R57 -> 0 | T56: =R56/4 -> 0 | V56: =R56/4 -> 0 | X56: =R56/4 -> 0 | Z56: =R56/4 -> 0 | AA56: =SUM(AC56+AE56+AG56+AI56) -> 0 | AB56: =AB58/AB57 -> 0 | AD56: =AB56/4 -> 0 | AF56: =AB56/4 -> 0 | AH56: =AB56/4 -> 0 | AJ56: =AB56/4 -> 0 | AK56: =SUM(AM56+AO56+AQ56+AS56) -> 0 | AL56: =AL58/AL57 -> 0 | AN56: =AL56/4 -> 0 | AP56: =AL56/4 -> 0 | AR56: =AL56/4 -> 0 | AT56: =AL56/4 -> 0 | AU56: =SUM(AW56+AY56+BA56+BC56) -> 0 | AV56: =AV58/AV57 -> 0 | AX56: =AV56/4 -> 0 | AZ56: =AV56/4 -> 0 | BB56: =AV56/4 -> 0 | BD56: =AV56/4 -> 0 | BE56: =SUM(BG56+BI56+BK56+BM56) -> 0 | BF56: =BF58/BF57 -> 0 | BH56: =BF56/4 -> 0 | BJ56: =BF56/4 -> 0 | BL56: =BF56/4 -> 0 | BN56: =BF56/4 -> 0 | BO56: =SUM(BQ56+BS56+BU56+BW56) -> 0 | BP56: =BP58/BP57 -> 0 | BR56: =BP56/4 -> 0 | BT56: =BP56/4 -> 0 | BV56: =BP56/4 -> 0 | BX56: =BP56/4 -> 0 | BY56: =SUM(CA56+CC56+CE56+CG56) -> 0 | BZ56: =BZ58/BZ57 -> 0 | CB56: =BZ56/4 -> 0 | CD56: =BZ56/4 -> 0 | CF56: =BZ56/4 -> 0 | CH56: =BZ56/4 -> 0 | CI56: =SUM(CK56+CM56+CO56+CQ56) -> 0 | CJ56: =CJ58/CJ57 -> 0 | CL56: =CJ56/4 -> 0 | CN56: =CJ56/4 -> 0 | CP56: =CJ56/4 -> 0 | CR56: =CJ56/4 -> 0 | CS56: =SUM(CU56+CW56+CY56+DA56) -> 0 | CT56: =CT58/CT57 -> 0 | CV56: =CT56/4 -> 0 | CX56: =CT56/4 -> 0 | CZ56: =CT56/4 -> 0 | DB56: =CT56/4 -> 0 | DC56: =SUM(DE56+DG56+DI56+DK56) -> 0 | DD56: =DD58/DD57 -> 0 | DF56: =DD56/4 -> 0 | DH56: =DD56/4 -> 0 | DJ56: =DD56/4 -> 0 | DL56: =DD56/4 -> 0 | DM56: =SUM(DO56+DQ56+DS56+DU56) -> 0 | DN56: =DN58/DN57 -> 0 | DP56: =DN56/4 -> 0 | DR56: =DN56/4 -> 0 | DT56: =DN56/4 -> 0 | DV56: =DN56/4 -> 0
C57: % de fechamento | D57: =D58/D56 -> #DIV/0! | E57: =E58/E56 -> #DIV/0! | F57: =F58/F56 -> #DIV/0! | G57: 0.4 | H57: - | I57: =I58/I56 -> #DIV/0! | J57: =G57 -> 0.4 | K57: =K58/K56 -> #DIV/0! | L57: =G57 -> 0.4 | M57: =M58/M56 -> #DIV/0! | N57: =G57 -> 0.4 | O57: =O58/O56 -> #DIV/0! | P57: =G57 -> 0.4 | Q57: =Q58/Q56 -> #DIV/0! | R57: 0.4 | S57: =S58/S56 -> #DIV/0! | T57: =R57 -> 0.4 | U57: =U58/U56 -> #DIV/0! | V57: =R57 -> 0.4 | W57: =W58/W56 -> #DIV/0! | X57: =R57 -> 0.4 | Y57: =Y58/Y56 -> #DIV/0! | Z57: =R57 -> 0.4 | AA57: =AA58/AA56 -> #DIV/0! | AB57: 0.4 | AC57: =AC58/AC56 -> #DIV/0! | AD57: =AB57 -> 0.4 | AE57: =AE58/AE56 -> #DIV/0! | AF57: =AB57 -> 0.4 | AG57: =AG58/AG56 -> #DIV/0! | AH57: =AB57 -> 0.4 | AI57: =AI58/AI56 -> #DIV/0! | AJ57: =AB57 -> 0.4 | AK57: =AK58/AK56 -> #DIV/0! | AL57: 0.4 | AM57: =AM58/AM56 -> #DIV/0! | AN57: =AL57 -> 0.4 | AO57: =AO58/AO56 -> #DIV/0! | AP57: =AL57 -> 0.4 | AQ57: =AQ58/AQ56 -> #DIV/0! | AR57: =AL57 -> 0.4 | AS57: =AS58/AS56 -> #DIV/0! | AT57: =AL57 -> 0.4 | AU57: =AU58/AU56 -> #DIV/0! | AV57: 0.4 | AW57: =AW58/AW56 -> #DIV/0! | AX57: =AV57 -> 0.4 | AY57: =AY58/AY56 -> #DIV/0! | AZ57: =AV57 -> 0.4 | BA57: =BA58/BA56 -> #DIV/0! | BB57: =AV57 -> 0.4 | BC57: =BC58/BC56 -> #DIV/0! | BD57: =AV57 -> 0.4 | BE57: =BE58/BE56 -> #DIV/0! | BF57: 0.4 | BG57: =BG58/BG56 -> #DIV/0! | BH57: =BF57 -> 0.4 | BI57: =BI58/BI56 -> #DIV/0! | BJ57: =BF57 -> 0.4 | BK57: =BK58/BK56 -> #DIV/0! | BL57: =BF57 -> 0.4 | BM57: =BM58/BM56 -> #DIV/0! | BN57: =BF57 -> 0.4 | BO57: =BO58/BO56 -> #DIV/0! | BP57: 0.4 | BQ57: =BQ58/BQ56 -> #DIV/0! | BR57: =BP57 -> 0.4 | BS57: =BS58/BS56 -> #DIV/0! | BT57: =BP57 -> 0.4 | BU57: =BU58/BU56 -> #DIV/0! | BV57: =BP57 -> 0.4 | BW57: =BW58/BW56 -> #DIV/0! | BX57: =BP57 -> 0.4 | BY57: =BY58/BY56 -> #DIV/0! | BZ57: 0.4 | CA57: =CA58/CA56 -> #DIV/0! | CB57: =BZ57 -> 0.4 | CC57: =CC58/CC56 -> #DIV/0! | CD57: =BZ57 -> 0.4 | CE57: =CE58/CE56 -> #DIV/0! | CF57: =BZ57 -> 0.4 | CG57: =CG58/CG56 -> #DIV/0! | CH57: =BZ57 -> 0.4 | CI57: =CI58/CI56 -> #DIV/0! | CJ57: 0.4 | CK57: =CK58/CK56 -> #DIV/0! | CL57: =CJ57 -> 0.4 | CM57: =CM58/CM56 -> #DIV/0! | CN57: =CJ57 -> 0.4 | CO57: =CO58/CO56 -> #DIV/0! | CP57: =CJ57 -> 0.4 | CQ57: =CQ58/CQ56 -> #DIV/0! | CR57: =CJ57 -> 0.4 | CS57: =CS58/CS56 -> #DIV/0! | CT57: 0.4 | CU57: =CU58/CU56 -> #DIV/0! | CV57: =CT57 -> 0.4 | CW57: =CW58/CW56 -> #DIV/0! | CX57: =CT57 -> 0.4 | CY57: =CY58/CY56 -> #DIV/0! | CZ57: =CT57 -> 0.4 | DA57: =DA58/DA56 -> #DIV/0! | DB57: =CT57 -> 0.4 | DC57: =DC58/DC56 -> #DIV/0! | DD57: 0.4 | DE57: =DE58/DE56 -> #DIV/0! | DF57: =DD57 -> 0.4 | DG57: =DG58/DG56 -> #DIV/0! | DH57: =DD57 -> 0.4 | DI57: =DI58/DI56 -> #DIV/0! | DJ57: =DD57 -> 0.4 | DK57: =DK58/DK56 -> #DIV/0! | DL57: =DD57 -> 0.4 | DM57: =DM58/DM56 -> #DIV/0! | DN57: 0.4 | DO57: =DO58/DO56 -> #DIV/0! | DP57: =DN57 -> 0.4 | DQ57: =DQ58/DQ56 -> #DIV/0! | DR57: =DN57 -> 0.4 | DS57: =DS58/DS56 -> #DIV/0! | DT57: =DN57 -> 0.4 | DU57: =DU58/DU56 -> #DIV/0! | DV57: =DN57 -> 0.4
C58: Total de propostas fechadas | D58: =SUM(F58+Q58+AA58+AK58+AU58+BE58+BO58+BY58+CI58+CS58+DC58+DM58) -> 0 | E58: =SUM(G58+R58+AB58+AL58+AV58+BF58+BP58+BZ58+CJ58+CT58+DD58+DN58) -> 0 | F58: =SUM(I58+K58+M58+O58) -> 0 | G58: ='Dados da Operação'!H29 -> 0 | H58: =G58/F58 -> #DIV/0! | J58: =G58/4 -> 0 | L58: =G58/4 -> 0 | N58: =G58/4 -> 0 | P58: =G58/4 -> 0 | Q58: =SUM(S58+U58+W58+Y58) -> 0 | R58: ='Dados da Operação'!H38 -> 0 | T58: =R58/4 -> 0 | V58: =R58/4 -> 0 | X58: =R58/4 -> 0 | Z58: =R58/4 -> 0 | AA58: =SUM(AC58+AE58+AG58+AI58) -> 0 | AB58: ='Dados da Operação'!H47 -> 0 | AD58: =AB58/4 -> 0 | AF58: =AB58/4 -> 0 | AH58: =AB58/4 -> 0 | AJ58: =AB58/4 -> 0 | AK58: =SUM(AM58+AO58+AQ58+AS58) -> 0 | AL58: ='Dados da Operação'!H56 -> 0 | AN58: =AL58/4 -> 0 | AP58: =AL58/4 -> 0 | AR58: =AL58/4 -> 0 | AT58: =AL58/4 -> 0 | AU58: =SUM(AW58+AY58+BA58+BC58) -> 0 | AV58: ='Dados da Operação'!H65 -> 0 | AX58: =AV58/4 -> 0 | AZ58: =AV58/4 -> 0 | BB58: =AV58/4 -> 0 | BD58: =AV58/4 -> 0 | BE58: =SUM(BG58+BI58+BK58+BM58) -> 0 | BF58: ='Dados da Operação'!H74 -> 0 | BH58: =BF58/4 -> 0 | BJ58: =BF58/4 -> 0 | BL58: =BF58/4 -> 0 | BN58: =BF58/4 -> 0 | BO58: =SUM(BQ58+BS58+BU58+BW58) -> 0 | BP58: ='Dados da Operação'!H83 -> 0 | BR58: =BP58/4 -> 0 | BT58: =BP58/4 -> 0 | BV58: =BP58/4 -> 0 | BX58: =BP58/4 -> 0 | BY58: =SUM(CA58+CC58+CE58+CG58) -> 0 | BZ58: ='Dados da Operação'!H92 -> 0 | CB58: =BZ58/4 -> 0 | CD58: =BZ58/4 -> 0 | CF58: =BZ58/4 -> 0 | CH58: =BZ58/4 -> 0 | CI58: =SUM(CK58+CM58+CO58+CQ58) -> 0 | CJ58: ='Dados da Operação'!H101 -> 0 | CL58: =CJ58/4 -> 0 | CN58: =CJ58/4 -> 0 | CP58: =CJ58/4 -> 0 | CR58: =CJ58/4 -> 0 | CS58: =SUM(CU58+CW58+CY58+DA58) -> 0 | CT58: ='Dados da Operação'!H110 -> 0 | CV58: =CT58/4 -> 0 | CX58: =CT58/4 -> 0 | CZ58: =CT58/4 -> 0 | DB58: =CT58/4 -> 0 | DC58: =SUM(DE58+DG58+DI58+DK58) -> 0 | DD58: ='Dados da Operação'!H119 -> 0 | DF58: =DD58/4 -> 0 | DH58: =DD58/4 -> 0 | DJ58: =DD58/4 -> 0 | DL58: =DD58/4 -> 0 | DM58: =SUM(DO58+DQ58+DS58+DU58) -> 0 | DN58: ='Dados da Operação'!H128 -> 0 | DP58: =DN58/4 -> 0 | DR58: =DN58/4 -> 0 | DT58: =DN58/4 -> 0 | DV58: =DN58/4 -> 0
C59: Total de faturamento | D59: =SUM(F59+Q59+AA59+AK59+AU59+BE59+BO59+BY59+CI59+CS59+DC59+DM59) -> 0 | E59: =SUM(G59+R59+AB59+AL59+AV59+BF59+BP59+BZ59+CJ59+CT59+DD59+DN59) -> 0 | F59: =SUM(I59+K59+M59+O59) -> 0 | G59: ='Dados da Operação'!G29 -> 0 | H59: =G59/F59 -> #DIV/0! | J59: =G59/4 -> 0 | L59: =G59/4 -> 0 | N59: =G59/4 -> 0 | P59: =G59/4 -> 0 | Q59: =SUM(S59+U59+W59+Y59) -> 0 | R59: ='Dados da Operação'!G38 -> 0 | T59: =R59/4 -> 0 | V59: =R59/4 -> 0 | X59: =R59/4 -> 0 | Z59: =R59/4 -> 0 | AA59: =SUM(AC59+AE59+AG59+AI59) -> 0 | AB59: ='Dados da Operação'!G47 -> 0 | AD59: =AB59/4 -> 0 | AF59: =AB59/4 -> 0 | AH59: =AB59/4 -> 0 | AJ59: =AB59/4 -> 0 | AK59: =SUM(AM59+AO59+AQ59+AS59) -> 0 | AL59: ='Dados da Operação'!G56 -> 0 | AN59: =AL59/4 -> 0 | AP59: =AL59/4 -> 0 | AR59: =AL59/4 -> 0 | AT59: =AL59/4 -> 0 | AU59: =SUM(AW59+AY59+BA59+BC59) -> 0 | AV59: ='Dados da Operação'!G65 -> 0 | AX59: =AV59/4 -> 0 | AZ59: =AV59/4 -> 0 | BB59: =AV59/4 -> 0 | BD59: =AV59/4 -> 0 | BE59: =SUM(BG59+BI59+BK59+BM59) -> 0 | BF59: ='Dados da Operação'!G74 -> 0 | BH59: =BF59/4 -> 0 | BJ59: =BF59/4 -> 0 | BL59: =BF59/4 -> 0 | BN59: =BF59/4 -> 0 | BO59: =SUM(BQ59+BS59+BU59+BW59) -> 0 | BP59: ='Dados da Operação'!G83 -> 0 | BR59: =BP59/4 -> 0 | BT59: =BP59/4 -> 0 | BV59: =BP59/4 -> 0 | BX59: =BP59/4 -> 0 | BY59: =SUM(CA59+CC59+CE59+CG59) -> 0 | BZ59: ='Dados da Operação'!G92 -> 0 | CB59: =BZ59/4 -> 0 | CD59: =BZ59/4 -> 0 | CF59: =BZ59/4 -> 0 | CH59: =BZ59/4 -> 0 | CI59: =SUM(CK59+CM59+CO59+CQ59) -> 0 | CJ59: ='Dados da Operação'!G101 -> 0 | CL59: =CJ59/4 -> 0 | CN59: =CJ59/4 -> 0 | CP59: =CJ59/4 -> 0 | CR59: =CJ59/4 -> 0 | CS59: =SUM(CU59+CW59+CY59+DA59) -> 0 | CT59: ='Dados da Operação'!G110 -> 0 | CV59: =CT59/4 -> 0 | CX59: =CT59/4 -> 0 | CZ59: =CT59/4 -> 0 | DB59: =CT59/4 -> 0 | DC59: =SUM(DE59+DG59+DI59+DK59) -> 0 | DD59: ='Dados da Operação'!G119 -> 0 | DF59: =DD59/4 -> 0 | DH59: =DD59/4 -> 0 | DJ59: =DD59/4 -> 0 | DL59: =DD59/4 -> 0 | DM59: =SUM(DO59+DQ59+DS59+DU59) -> 0 | DN59: ='Dados da Operação'!G128 -> 0 | DP59: =DN59/4 -> 0 | DR59: =DN59/4 -> 0 | DT59: =DN59/4 -> 0 | DV59: =DN59/4 -> 0
C60: Ticket médio | D60: =D59/D58 -> #DIV/0! | E60: =E59/E58 -> #DIV/0! | F60: =F59/F58 -> #DIV/0! | G60: ='Dados da Operação'!$C$5 -> 2500 | H60: =G60/F60 -> #DIV/0! | I60: =I59/I58 -> #DIV/0! | J60: =G60 -> 2500 | K60: =K59/K58 -> #DIV/0! | L60: =G60 -> 2500 | M60: =M59/M58 -> #DIV/0! | N60: =G60 -> 2500 | O60: =O59/O58 -> #DIV/0! | P60: =G60 -> 2500 | Q60: =Q59/Q58 -> #DIV/0! | R60: ='Dados da Operação'!$C$5 -> 2500 | S60: =S59/S58 -> #DIV/0! | T60: =R60 -> 2500 | U60: =U59/U58 -> #DIV/0! | V60: =R60 -> 2500 | W60: =W59/W58 -> #DIV/0! | X60: =R60 -> 2500 | Y60: =Y59/Y58 -> #DIV/0! | Z60: =R60 -> 2500 | AA60: =AA59/AA58 -> #DIV/0! | AB60: ='Dados da Operação'!$C$5 -> 2500 | AC60: =AC59/AC58 -> #DIV/0! | AD60: =AB60 -> 2500 | AE60: =AE59/AE58 -> #DIV/0! | AF60: =AB60 -> 2500 | AG60: =AG59/AG58 -> #DIV/0! | AH60: =AB60 -> 2500 | AI60: =AI59/AI58 -> #DIV/0! | AJ60: =AB60 -> 2500 | AK60: =AK59/AK58 -> #DIV/0! | AL60: ='Dados da Operação'!$C$5 -> 2500 | AM60: =AM59/AM58 -> #DIV/0! | AN60: =AL60 -> 2500 | AO60: =AO59/AO58 -> #DIV/0! | AP60: =AL60 -> 2500 | AQ60: =AQ59/AQ58 -> #DIV/0! | AR60: =AL60 -> 2500 | AS60: =AS59/AS58 -> #DIV/0! | AT60: =AL60 -> 2500 | AU60: =AU59/AU58 -> #DIV/0! | AV60: ='Dados da Operação'!$C$5 -> 2500 | AW60: =AW59/AW58 -> #DIV/0! | AX60: =AV60 -> 2500 | AY60: =AY59/AY58 -> #DIV/0! | AZ60: =AV60 -> 2500 | BA60: =BA59/BA58 -> #DIV/0! | BB60: =AV60 -> 2500 | BC60: =BC59/BC58 -> #DIV/0! | BD60: =AV60 -> 2500 | BE60: =BE59/BE58 -> #DIV/0! | BF60: ='Dados da Operação'!$C$5 -> 2500 | BG60: =BG59/BG58 -> #DIV/0! | BH60: =BF60 -> 2500 | BI60: =BI59/BI58 -> #DIV/0! | BJ60: =BF60 -> 2500 | BK60: =BK59/BK58 -> #DIV/0! | BL60: =BF60 -> 2500 | BM60: =BM59/BM58 -> #DIV/0! | BN60: =BF60 -> 2500 | BO60: =BO59/BO58 -> #DIV/0! | BP60: ='Dados da Operação'!$C$5 -> 2500 | BQ60: =BQ59/BQ58 -> #DIV/0! | BR60: =BP60 -> 2500 | BS60: =BS59/BS58 -> #DIV/0! | BT60: =BP60 -> 2500 | BU60: =BU59/BU58 -> #DIV/0! | BV60: =BP60 -> 2500 | BW60: =BW59/BW58 -> #DIV/0! | BX60: =BP60 -> 2500 | BY60: =BY59/BY58 -> #DIV/0! | BZ60: ='Dados da Operação'!$C$5 -> 2500 | CA60: =CA59/CA58 -> #DIV/0! | CB60: =BZ60 -> 2500 | CC60: =CC59/CC58 -> #DIV/0! | CD60: =BZ60 -> 2500 | CE60: =CE59/CE58 -> #DIV/0! | CF60: =BZ60 -> 2500 | CG60: =CG59/CG58 -> #DIV/0! | CH60: =BZ60 -> 2500 | CI60: =CI59/CI58 -> #DIV/0! | CJ60: ='Dados da Operação'!$C$5 -> 2500 | CK60: =CK59/CK58 -> #DIV/0! | CL60: =CJ60 -> 2500 | CM60: =CM59/CM58 -> #DIV/0! | CN60: =CJ60 -> 2500 | CO60: =CO59/CO58 -> #DIV/0! | CP60: =CJ60 -> 2500 | CQ60: =CQ59/CQ58 -> #DIV/0! | CR60: =CJ60 -> 2500 | CS60: =CS59/CS58 -> #DIV/0! | CT60: ='Dados da Operação'!$C$5 -> 2500 | CU60: =CU59/CU58 -> #DIV/0! | CV60: =CT60 -> 2500 | CW60: =CW59/CW58 -> #DIV/0! | CX60: =CT60 -> 2500 | CY60: =CY59/CY58 -> #DIV/0! | CZ60: =CT60 -> 2500 | DA60: =DA59/DA58 -> #DIV/0! | DB60: =CT60 -> 2500 | DC60: =DC59/DC58 -> #DIV/0! | DD60: ='Dados da Operação'!$C$5 -> 2500 | DE60: =DE59/DE58 -> #DIV/0! | DF60: =DD60 -> 2500 | DG60: =DG59/DG58 -> #DIV/0! | DH60: =DD60 -> 2500 | DI60: =DI59/DI58 -> #DIV/0! | DJ60: =DD60 -> 2500 | DK60: =DK59/DK58 -> #DIV/0! | DL60: =DD60 -> 2500 | DM60: =DM59/DM58 -> #DIV/0! | DN60: ='Dados da Operação'!$C$5 -> 2500 | DO60: =DO59/DO58 -> #DIV/0! | DP60: =DN60 -> 2500 | DQ60: =DQ59/DQ58 -> #DIV/0! | DR60: =DN60 -> 2500 | DS60: =DS59/DS58 -> #DIV/0! | DT60: =DN60 -> 2500 | DU60: =DU59/DU58 -> #DIV/0! | DV60: =DN60 -> 2500
B62: EXPANSÃO | C62: Total de cadências abertas | D62: =SUM(F62+Q62+AA62+AK62+AU62+BE62+BO62+BY62+CI62+CS62+DC62+DM62) -> 0 | E62: =SUM(G62+R62+AB62+AL62+AV62+BF62+BP62+BZ62+CJ62+CT62+DD62+DN62) -> 0 | F62: =SUM(I62+K62+M62+O62) -> 0 | G62: =G64/G63 -> 0 | H62: =F62/G62 -> #DIV/0! | J62: =G62/4 -> 0 | L62: =G62/4 -> 0 | N62: =G62/4 -> 0 | P62: =G62/4 -> 0 | Q62: =SUM(S62+U62+W62+Y62) -> 0 | R62: =R64/R63 -> 0 | T62: =R62/4 -> 0 | V62: =R62/4 -> 0 | X62: =R62/4 -> 0 | Z62: =R62/4 -> 0 | AA62: =SUM(AC62+AE62+AG62+AI62) -> 0 | AB62: =AB64/AB63 -> 0 | AD62: =AB62/4 -> 0 | AF62: =AB62/4 -> 0 | AH62: =AB62/4 -> 0 | AJ62: =AB62/4 -> 0 | AK62: =SUM(AM62+AO62+AQ62+AS62) -> 0 | AL62: =AL64/AL63 -> 0 | AN62: =AL62/4 -> 0 | AP62: =AL62/4 -> 0 | AR62: =AL62/4 -> 0 | AT62: =AL62/4 -> 0 | AU62: =SUM(AW62+AY62+BA62+BC62) -> 0 | AV62: =AV64/AV63 -> 0 | AX62: =AV62/4 -> 0 | AZ62: =AV62/4 -> 0 | BB62: =AV62/4 -> 0 | BD62: =AV62/4 -> 0 | BE62: =SUM(BG62+BI62+BK62+BM62) -> 0 | BF62: =BF64/BF63 -> 0 | BH62: =BF62/4 -> 0 | BJ62: =BF62/4 -> 0 | BL62: =BF62/4 -> 0 | BN62: =BF62/4 -> 0 | BO62: =SUM(BQ62+BS62+BU62+BW62) -> 0 | BP62: =BP64/BP63 -> 0 | BR62: =BP62/4 -> 0 | BT62: =BP62/4 -> 0 | BV62: =BP62/4 -> 0 | BX62: =BP62/4 -> 0 | BY62: =SUM(CA62+CC62+CE62+CG62) -> 0 | BZ62: =BZ64/BZ63 -> 0 | CB62: =BZ62/4 -> 0 | CD62: =BZ62/4 -> 0 | CF62: =BZ62/4 -> 0 | CH62: =BZ62/4 -> 0 | CI62: =SUM(CK62+CM62+CO62+CQ62) -> 0 | CJ62: =CJ64/CJ63 -> 0 | CL62: =CJ62/4 -> 0 | CN62: =CJ62/4 -> 0 | CP62: =CJ62/4 -> 0 | CR62: =CJ62/4 -> 0 | CS62: =SUM(CU62+CW62+CY62+DA62) -> 0 | CT62: =CT64/CT63 -> 0 | CV62: =CT62/4 -> 0 | CX62: =CT62/4 -> 0 | CZ62: =CT62/4 -> 0 | DB62: =CT62/4 -> 0 | DC62: =SUM(DE62+DG62+DI62+DK62) -> 0 | DD62: =DD64/DD63 -> 0 | DF62: =DD62/4 -> 0 | DH62: =DD62/4 -> 0 | DJ62: =DD62/4 -> 0 | DL62: =DD62/4 -> 0 | DM62: =SUM(DO62+DQ62+DS62+DU62) -> 0 | DN62: =DN64/DN63 -> 0 | DP62: =DN62/4 -> 0 | DR62: =DN62/4 -> 0 | DT62: =DN62/4 -> 0 | DV62: =DN62/4 -> 0
C63: % Conversão em Lead Conectado | D63: =D64/D62 -> #DIV/0! | E63: =E64/E62 -> #DIV/0! | F63: =F64/F62 -> #DIV/0! | G63: 0.6 | H63: - | I63: =I64/I62 -> #DIV/0! | J63: =G63 -> 0.6 | K63: =K64/K62 -> #DIV/0! | L63: =G63 -> 0.6 | M63: =M64/M62 -> #DIV/0! | N63: =G63 -> 0.6 | O63: =O64/O62 -> #DIV/0! | P63: =G63 -> 0.6 | Q63: =Q64/Q62 -> #DIV/0! | R63: 0.6 | S63: =S64/S62 -> #DIV/0! | T63: =R63 -> 0.6 | U63: =U64/U62 -> #DIV/0! | V63: =R63 -> 0.6 | W63: =W64/W62 -> #DIV/0! | X63: =R63 -> 0.6 | Y63: =Y64/Y62 -> #DIV/0! | Z63: =R63 -> 0.6 | AA63: =AA64/AA62 -> #DIV/0! | AB63: 0.6 | AC63: =AC64/AC62 -> #DIV/0! | AD63: =AB63 -> 0.6 | AE63: =AE64/AE62 -> #DIV/0! | AF63: =AB63 -> 0.6 | AG63: =AG64/AG62 -> #DIV/0! | AH63: =AB63 -> 0.6 | AI63: =AI64/AI62 -> #DIV/0! | AJ63: =AB63 -> 0.6 | AK63: =AK64/AK62 -> #DIV/0! | AL63: 0.6 | AM63: =AM64/AM62 -> #DIV/0! | AN63: =AL63 -> 0.6 | AO63: =AO64/AO62 -> #DIV/0! | AP63: =AL63 -> 0.6 | AQ63: =AQ64/AQ62 -> #DIV/0! | AR63: =AL63 -> 0.6 | AS63: =AS64/AS62 -> #DIV/0! | AT63: =AL63 -> 0.6 | AU63: =AU64/AU62 -> #DIV/0! | AV63: 0.6 | AW63: =AW64/AW62 -> #DIV/0! | AX63: =AV63 -> 0.6 | AY63: =AY64/AY62 -> #DIV/0! | AZ63: =AV63 -> 0.6 | BA63: =BA64/BA62 -> #DIV/0! | BB63: =AV63 -> 0.6 | BC63: =BC64/BC62 -> #DIV/0! | BD63: =AV63 -> 0.6 | BE63: =BE64/BE62 -> #DIV/0! | BF63: 0.6 | BG63: =BG64/BG62 -> #DIV/0! | BH63: =BF63 -> 0.6 | BI63: =BI64/BI62 -> #DIV/0! | BJ63: =BF63 -> 0.6 | BK63: =BK64/BK62 -> #DIV/0! | BL63: =BF63 -> 0.6 | BM63: =BM64/BM62 -> #DIV/0! | BN63: =BF63 -> 0.6 | BO63: =BO64/BO62 -> #DIV/0! | BP63: 0.6 | BQ63: =BQ64/BQ62 -> #DIV/0! | BR63: =BP63 -> 0.6 | BS63: =BS64/BS62 -> #DIV/0! | BT63: =BP63 -> 0.6 | BU63: =BU64/BU62 -> #DIV/0! | BV63: =BP63 -> 0.6 | BW63: =BW64/BW62 -> #DIV/0! | BX63: =BP63 -> 0.6 | BY63: =BY64/BY62 -> #DIV/0! | BZ63: 0.6 | CA63: =CA64/CA62 -> #DIV/0! | CB63: =BZ63 -> 0.6 | CC63: =CC64/CC62 -> #DIV/0! | CD63: =BZ63 -> 0.6 | CE63: =CE64/CE62 -> #DIV/0! | CF63: =BZ63 -> 0.6 | CG63: =CG64/CG62 -> #DIV/0! | CH63: =BZ63 -> 0.6 | CI63: =CI64/CI62 -> #DIV/0! | CJ63: 0.6 | CK63: =CK64/CK62 -> #DIV/0! | CL63: =CJ63 -> 0.6 | CM63: =CM64/CM62 -> #DIV/0! | CN63: =CJ63 -> 0.6 | CO63: =CO64/CO62 -> #DIV/0! | CP63: =CJ63 -> 0.6 | CQ63: =CQ64/CQ62 -> #DIV/0! | CR63: =CJ63 -> 0.6 | CS63: =CS64/CS62 -> #DIV/0! | CT63: 0.6 | CU63: =CU64/CU62 -> #DIV/0! | CV63: =CT63 -> 0.6 | CW63: =CW64/CW62 -> #DIV/0! | CX63: =CT63 -> 0.6 | CY63: =CY64/CY62 -> #DIV/0! | CZ63: =CT63 -> 0.6 | DA63: =DA64/DA62 -> #DIV/0! | DB63: =CT63 -> 0.6 | DC63: =DC64/DC62 -> #DIV/0! | DD63: 0.6 | DE63: =DE64/DE62 -> #DIV/0! | DF63: =DD63 -> 0.6 | DG63: =DG64/DG62 -> #DIV/0! | DH63: =DD63 -> 0.6 | DI63: =DI64/DI62 -> #DIV/0! | DJ63: =DD63 -> 0.6 | DK63: =DK64/DK62 -> #DIV/0! | DL63: =DD63 -> 0.6 | DM63: =DM64/DM62 -> #DIV/0! | DN63: 0.6 | DO63: =DO64/DO62 -> #DIV/0! | DP63: =DN63 -> 0.6 | DQ63: =DQ64/DQ62 -> #DIV/0! | DR63: =DN63 -> 0.6 | DS63: =DS64/DS62 -> #DIV/0! | DT63: =DN63 -> 0.6 | DU63: =DU64/DU62 -> #DIV/0! | DV63: =DN63 -> 0.6
C64: Total de leads conectados | D64: =SUM(F64+Q64+AA64+AK64+AU64+BE64+BO64+BY64+CI64+CS64+DC64+DM64) -> 0 | E64: =SUM(G64+R64+AB64+AL64+AV64+BF64+BP64+BZ64+CJ64+CT64+DD64+DN64) -> 0 | F64: =SUM(I64+K64+M64+O64) -> 0 | G64: =G66/G65 -> 0 | H64: =G64/F64 -> #DIV/0! | J64: =G64/4 -> 0 | L64: =G64/4 -> 0 | N64: =G64/4 -> 0 | P64: =G64/4 -> 0 | Q64: =SUM(S64+U64+W64+Y64) -> 0 | R64: =R66/R65 -> 0 | T64: =R64/4 -> 0 | V64: =R64/4 -> 0 | X64: =R64/4 -> 0 | Z64: =R64/4 -> 0 | AA64: =SUM(AC64+AE64+AG64+AI64) -> 0 | AB64: =AB66/AB65 -> 0 | AD64: =AB64/4 -> 0 | AF64: =AB64/4 -> 0 | AH64: =AB64/4 -> 0 | AJ64: =AB64/4 -> 0 | AK64: =SUM(AM64+AO64+AQ64+AS64) -> 0 | AL64: =AL66/AL65 -> 0 | AN64: =AL64/4 -> 0 | AP64: =AL64/4 -> 0 | AR64: =AL64/4 -> 0 | AT64: =AL64/4 -> 0 | AU64: =SUM(AW64+AY64+BA64+BC64) -> 0 | AV64: =AV66/AV65 -> 0 | AX64: =AV64/4 -> 0 | AZ64: =AV64/4 -> 0 | BB64: =AV64/4 -> 0 | BD64: =AV64/4 -> 0 | BE64: =SUM(BG64+BI64+BK64+BM64) -> 0 | BF64: =BF66/BF65 -> 0 | BH64: =BF64/4 -> 0 | BJ64: =BF64/4 -> 0 | BL64: =BF64/4 -> 0 | BN64: =BF64/4 -> 0 | BO64: =SUM(BQ64+BS64+BU64+BW64) -> 0 | BP64: =BP66/BP65 -> 0 | BR64: =BP64/4 -> 0 | BT64: =BP64/4 -> 0 | BV64: =BP64/4 -> 0 | BX64: =BP64/4 -> 0 | BY64: =SUM(CA64+CC64+CE64+CG64) -> 0 | BZ64: =BZ66/BZ65 -> 0 | CB64: =BZ64/4 -> 0 | CD64: =BZ64/4 -> 0 | CF64: =BZ64/4 -> 0 | CH64: =BZ64/4 -> 0 | CI64: =SUM(CK64+CM64+CO64+CQ64) -> 0 | CJ64: =CJ66/CJ65 -> 0 | CL64: =CJ64/4 -> 0 | CN64: =CJ64/4 -> 0 | CP64: =CJ64/4 -> 0 | CR64: =CJ64/4 -> 0 | CS64: =SUM(CU64+CW64+CY64+DA64) -> 0 | CT64: =CT66/CT65 -> 0 | CV64: =CT64/4 -> 0 | CX64: =CT64/4 -> 0 | CZ64: =CT64/4 -> 0 | DB64: =CT64/4 -> 0 | DC64: =SUM(DE64+DG64+DI64+DK64) -> 0 | DD64: =DD66/DD65 -> 0 | DF64: =DD64/4 -> 0 | DH64: =DD64/4 -> 0 | DJ64: =DD64/4 -> 0 | DL64: =DD64/4 -> 0 | DM64: =SUM(DO64+DQ64+DS64+DU64) -> 0 | DN64: =DN66/DN65 -> 0 | DP64: =DN64/4 -> 0 | DR64: =DN64/4 -> 0 | DT64: =DN64/4 -> 0 | DV64: =DN64/4 -> 0
C65: % Conversão em Reunião agendada | D65: =D66/D64 -> #DIV/0! | E65: =E66/E64 -> #DIV/0! | F65: =F66/F64 -> #DIV/0! | G65: 0.4 | H65: - | I65: =I66/I64 -> #DIV/0! | J65: =G65 -> 0.4 | K65: =K66/K64 -> #DIV/0! | L65: =G65 -> 0.4 | M65: =M66/M64 -> #DIV/0! | N65: =G65 -> 0.4 | O65: =O66/O64 -> #DIV/0! | P65: =G65 -> 0.4 | Q65: =Q66/Q64 -> #DIV/0! | R65: 0.4 | S65: =S66/S64 -> #DIV/0! | T65: =R65 -> 0.4 | U65: =U66/U64 -> #DIV/0! | V65: =R65 -> 0.4 | W65: =W66/W64 -> #DIV/0! | X65: =R65 -> 0.4 | Y65: =Y66/Y64 -> #DIV/0! | Z65: =R65 -> 0.4 | AA65: =AA66/AA64 -> #DIV/0! | AB65: 0.4 | AC65: =AC66/AC64 -> #DIV/0! | AD65: =AB65 -> 0.4 | AE65: =AE66/AE64 -> #DIV/0! | AF65: =AB65 -> 0.4 | AG65: =AG66/AG64 -> #DIV/0! | AH65: =AB65 -> 0.4 | AI65: =AI66/AI64 -> #DIV/0! | AJ65: =AB65 -> 0.4 | AK65: =AK66/AK64 -> #DIV/0! | AL65: 0.4 | AM65: =AM66/AM64 -> #DIV/0! | AN65: =AL65 -> 0.4 | AO65: =AO66/AO64 -> #DIV/0! | AP65: =AL65 -> 0.4 | AQ65: =AQ66/AQ64 -> #DIV/0! | AR65: =AL65 -> 0.4 | AS65: =AS66/AS64 -> #DIV/0! | AT65: =AL65 -> 0.4 | AU65: =AU66/AU64 -> #DIV/0! | AV65: 0.4 | AW65: =AW66/AW64 -> #DIV/0! | AX65: =AV65 -> 0.4 | AY65: =AY66/AY64 -> #DIV/0! | AZ65: =AV65 -> 0.4 | BA65: =BA66/BA64 -> #DIV/0! | BB65: =AV65 -> 0.4 | BC65: =BC66/BC64 -> #DIV/0! | BD65: =AV65 -> 0.4 | BE65: =BE66/BE64 -> #DIV/0! | BF65: 0.4 | BG65: =BG66/BG64 -> #DIV/0! | BH65: =BF65 -> 0.4 | BI65: =BI66/BI64 -> #DIV/0! | BJ65: =BF65 -> 0.4 | BK65: =BK66/BK64 -> #DIV/0! | BL65: =BF65 -> 0.4 | BM65: =BM66/BM64 -> #DIV/0! | BN65: =BF65 -> 0.4 | BO65: =BO66/BO64 -> #DIV/0! | BP65: 0.4 | BQ65: =BQ66/BQ64 -> #DIV/0! | BR65: =BP65 -> 0.4 | BS65: =BS66/BS64 -> #DIV/0! | BT65: =BP65 -> 0.4 | BU65: =BU66/BU64 -> #DIV/0! | BV65: =BP65 -> 0.4 | BW65: =BW66/BW64 -> #DIV/0! | BX65: =BP65 -> 0.4 | BY65: =BY66/BY64 -> #DIV/0! | BZ65: 0.4 | CA65: =CA66/CA64 -> #DIV/0! | CB65: =BZ65 -> 0.4 | CC65: =CC66/CC64 -> #DIV/0! | CD65: =BZ65 -> 0.4 | CE65: =CE66/CE64 -> #DIV/0! | CF65: =BZ65 -> 0.4 | CG65: =CG66/CG64 -> #DIV/0! | CH65: =BZ65 -> 0.4 | CI65: =CI66/CI64 -> #DIV/0! | CJ65: 0.4 | CK65: =CK66/CK64 -> #DIV/0! | CL65: =CJ65 -> 0.4 | CM65: =CM66/CM64 -> #DIV/0! | CN65: =CJ65 -> 0.4 | CO65: =CO66/CO64 -> #DIV/0! | CP65: =CJ65 -> 0.4 | CQ65: =CQ66/CQ64 -> #DIV/0! | CR65: =CJ65 -> 0.4 | CS65: =CS66/CS64 -> #DIV/0! | CT65: 0.4 | CU65: =CU66/CU64 -> #DIV/0! | CV65: =CT65 -> 0.4 | CW65: =CW66/CW64 -> #DIV/0! | CX65: =CT65 -> 0.4 | CY65: =CY66/CY64 -> #DIV/0! | CZ65: =CT65 -> 0.4 | DA65: =DA66/DA64 -> #DIV/0! | DB65: =CT65 -> 0.4 | DC65: =DC66/DC64 -> #DIV/0! | DD65: 0.4 | DE65: =DE66/DE64 -> #DIV/0! | DF65: =DD65 -> 0.4 | DG65: =DG66/DG64 -> #DIV/0! | DH65: =DD65 -> 0.4 | DI65: =DI66/DI64 -> #DIV/0! | DJ65: =DD65 -> 0.4 | DK65: =DK66/DK64 -> #DIV/0! | DL65: =DD65 -> 0.4 | DM65: =DM66/DM64 -> #DIV/0! | DN65: 0.4 | DO65: =DO66/DO64 -> #DIV/0! | DP65: =DN65 -> 0.4 | DQ65: =DQ66/DQ64 -> #DIV/0! | DR65: =DN65 -> 0.4 | DS65: =DS66/DS64 -> #DIV/0! | DT65: =DN65 -> 0.4 | DU65: =DU66/DU64 -> #DIV/0! | DV65: =DN65 -> 0.4
C66: Total de reuniões agendadas | D66: =SUM(F66+Q66+AA66+AK66+AU66+BE66+BO66+BY66+CI66+CS66+DC66+DM66) -> 0 | E66: =SUM(G66+R66+AB66+AL66+AV66+BF66+BP66+BZ66+CJ66+CT66+DD66+DN66) -> 0 | F66: =SUM(I66+K66+M66+O66) -> 0 | G66: =G68/G67 -> 0 | H66: =G66/F66 -> #DIV/0! | J66: =G66/4 -> 0 | L66: =G66/4 -> 0 | N66: =G66/4 -> 0 | P66: =G66/4 -> 0 | Q66: =SUM(S66+U66+W66+Y66) -> 0 | R66: =R68/R67 -> 0 | T66: =R66/4 -> 0 | V66: =R66/4 -> 0 | X66: =R66/4 -> 0 | Z66: =R66/4 -> 0 | AA66: =SUM(AC66+AE66+AG66+AI66) -> 0 | AB66: =AB68/AB67 -> 0 | AD66: =AB66/4 -> 0 | AF66: =AB66/4 -> 0 | AH66: =AB66/4 -> 0 | AJ66: =AB66/4 -> 0 | AK66: =SUM(AM66+AO66+AQ66+AS66) -> 0 | AL66: =AL68/AL67 -> 0 | AN66: =AL66/4 -> 0 | AP66: =AL66/4 -> 0 | AR66: =AL66/4 -> 0 | AT66: =AL66/4 -> 0 | AU66: =SUM(AW66+AY66+BA66+BC66) -> 0 | AV66: =AV68/AV67 -> 0 | AX66: =AV66/4 -> 0 | AZ66: =AV66/4 -> 0 | BB66: =AV66/4 -> 0 | BD66: =AV66/4 -> 0 | BE66: =SUM(BG66+BI66+BK66+BM66) -> 0 | BF66: =BF68/BF67 -> 0 | BH66: =BF66/4 -> 0 | BJ66: =BF66/4 -> 0 | BL66: =BF66/4 -> 0 | BN66: =BF66/4 -> 0 | BO66: =SUM(BQ66+BS66+BU66+BW66) -> 0 | BP66: =BP68/BP67 -> 0 | BR66: =BP66/4 -> 0 | BT66: =BP66/4 -> 0 | BV66: =BP66/4 -> 0 | BX66: =BP66/4 -> 0 | BY66: =SUM(CA66+CC66+CE66+CG66) -> 0 | BZ66: =BZ68/BZ67 -> 0 | CB66: =BZ66/4 -> 0 | CD66: =BZ66/4 -> 0 | CF66: =BZ66/4 -> 0 | CH66: =BZ66/4 -> 0 | CI66: =SUM(CK66+CM66+CO66+CQ66) -> 0 | CJ66: =CJ68/CJ67 -> 0 | CL66: =CJ66/4 -> 0 | CN66: =CJ66/4 -> 0 | CP66: =CJ66/4 -> 0 | CR66: =CJ66/4 -> 0 | CS66: =SUM(CU66+CW66+CY66+DA66) -> 0 | CT66: =CT68/CT67 -> 0 | CV66: =CT66/4 -> 0 | CX66: =CT66/4 -> 0 | CZ66: =CT66/4 -> 0 | DB66: =CT66/4 -> 0 | DC66: =SUM(DE66+DG66+DI66+DK66) -> 0 | DD66: =DD68/DD67 -> 0 | DF66: =DD66/4 -> 0 | DH66: =DD66/4 -> 0 | DJ66: =DD66/4 -> 0 | DL66: =DD66/4 -> 0 | DM66: =SUM(DO66+DQ66+DS66+DU66) -> 0 | DN66: =DN68/DN67 -> 0 | DP66: =DN66/4 -> 0 | DR66: =DN66/4 -> 0 | DT66: =DN66/4 -> 0 | DV66: =DN66/4 -> 0
C67: % de reunião realizada | D67: =D68/D66 -> #DIV/0! | E67: =E68/E66 -> #DIV/0! | F67: =F68/F66 -> #DIV/0! | G67: 0.9 | H67: - | I67: =I68/I66 -> #DIV/0! | J67: =G67 -> 0.9 | K67: =K68/K66 -> #DIV/0! | L67: =G67 -> 0.9 | M67: =M68/M66 -> #DIV/0! | N67: =G67 -> 0.9 | O67: =O68/O66 -> #DIV/0! | P67: =G67 -> 0.9 | Q67: =Q68/Q66 -> #DIV/0! | R67: 0.9 | S67: =S68/S66 -> #DIV/0! | T67: =R67 -> 0.9 | U67: =U68/U66 -> #DIV/0! | V67: =R67 -> 0.9 | W67: =W68/W66 -> #DIV/0! | X67: =R67 -> 0.9 | Y67: =Y68/Y66 -> #DIV/0! | Z67: =R67 -> 0.9 | AA67: =AA68/AA66 -> #DIV/0! | AB67: 0.9 | AC67: =AC68/AC66 -> #DIV/0! | AD67: =AB67 -> 0.9 | AE67: =AE68/AE66 -> #DIV/0! | AF67: =AB67 -> 0.9 | AG67: =AG68/AG66 -> #DIV/0! | AH67: =AB67 -> 0.9 | AI67: =AI68/AI66 -> #DIV/0! | AJ67: =AB67 -> 0.9 | AK67: =AK68/AK66 -> #DIV/0! | AL67: 0.9 | AM67: =AM68/AM66 -> #DIV/0! | AN67: =AL67 -> 0.9 | AO67: =AO68/AO66 -> #DIV/0! | AP67: =AL67 -> 0.9 | AQ67: =AQ68/AQ66 -> #DIV/0! | AR67: =AL67 -> 0.9 | AS67: =AS68/AS66 -> #DIV/0! | AT67: =AL67 -> 0.9 | AU67: =AU68/AU66 -> #DIV/0! | AV67: 0.9 | AW67: =AW68/AW66 -> #DIV/0! | AX67: =AV67 -> 0.9 | AY67: =AY68/AY66 -> #DIV/0! | AZ67: =AV67 -> 0.9 | BA67: =BA68/BA66 -> #DIV/0! | BB67: =AV67 -> 0.9 | BC67: =BC68/BC66 -> #DIV/0! | BD67: =AV67 -> 0.9 | BE67: =BE68/BE66 -> #DIV/0! | BF67: 0.9 | BG67: =BG68/BG66 -> #DIV/0! | BH67: =BF67 -> 0.9 | BI67: =BI68/BI66 -> #DIV/0! | BJ67: =BF67 -> 0.9 | BK67: =BK68/BK66 -> #DIV/0! | BL67: =BF67 -> 0.9 | BM67: =BM68/BM66 -> #DIV/0! | BN67: =BF67 -> 0.9 | BO67: =BO68/BO66 -> #DIV/0! | BP67: 0.9 | BQ67: =BQ68/BQ66 -> #DIV/0! | BR67: =BP67 -> 0.9 | BS67: =BS68/BS66 -> #DIV/0! | BT67: =BP67 -> 0.9 | BU67: =BU68/BU66 -> #DIV/0! | BV67: =BP67 -> 0.9 | BW67: =BW68/BW66 -> #DIV/0! | BX67: =BP67 -> 0.9 | BY67: =BY68/BY66 -> #DIV/0! | BZ67: 0.9 | CA67: =CA68/CA66 -> #DIV/0! | CB67: =BZ67 -> 0.9 | CC67: =CC68/CC66 -> #DIV/0! | CD67: =BZ67 -> 0.9 | CE67: =CE68/CE66 -> #DIV/0! | CF67: =BZ67 -> 0.9 | CG67: =CG68/CG66 -> #DIV/0! | CH67: =BZ67 -> 0.9 | CI67: =CI68/CI66 -> #DIV/0! | CJ67: 0.9 | CK67: =CK68/CK66 -> #DIV/0! | CL67: =CJ67 -> 0.9 | CM67: =CM68/CM66 -> #DIV/0! | CN67: =CJ67 -> 0.9 | CO67: =CO68/CO66 -> #DIV/0! | CP67: =CJ67 -> 0.9 | CQ67: =CQ68/CQ66 -> #DIV/0! | CR67: =CJ67 -> 0.9 | CS67: =CS68/CS66 -> #DIV/0! | CT67: 0.9 | CU67: =CU68/CU66 -> #DIV/0! | CV67: =CT67 -> 0.9 | CW67: =CW68/CW66 -> #DIV/0! | CX67: =CT67 -> 0.9 | CY67: =CY68/CY66 -> #DIV/0! | CZ67: =CT67 -> 0.9 | DA67: =DA68/DA66 -> #DIV/0! | DB67: =CT67 -> 0.9 | DC67: =DC68/DC66 -> #DIV/0! | DD67: 0.9 | DE67: =DE68/DE66 -> #DIV/0! | DF67: =DD67 -> 0.9 | DG67: =DG68/DG66 -> #DIV/0! | DH67: =DD67 -> 0.9 | DI67: =DI68/DI66 -> #DIV/0! | DJ67: =DD67 -> 0.9 | DK67: =DK68/DK66 -> #DIV/0! | DL67: =DD67 -> 0.9 | DM67: =DM68/DM66 -> #DIV/0! | DN67: 0.9 | DO67: =DO68/DO66 -> #DIV/0! | DP67: =DN67 -> 0.9 | DQ67: =DQ68/DQ66 -> #DIV/0! | DR67: =DN67 -> 0.9 | DS67: =DS68/DS66 -> #DIV/0! | DT67: =DN67 -> 0.9 | DU67: =DU68/DU66 -> #DIV/0! | DV67: =DN67 -> 0.9
C68: Total de reuniões realizadas | D68: =SUM(F68+Q68+AA68+AK68+AU68+BE68+BO68+BY68+CI68+CS68+DC68+DM68) -> 0 | E68: =SUM(G68+R68+AB68+AL68+AV68+BF68+BP68+BZ68+CJ68+CT68+DD68+DN68) -> 0 | F68: =SUM(I68+K68+M68+O68) -> 0 | G68: =G70/G69 -> 0 | H68: =G68/F68 -> #DIV/0! | J68: =G68/4 -> 0 | L68: =G68/4 -> 0 | N68: =G68/4 -> 0 | P68: =G68/4 -> 0 | Q68: =SUM(S68+U68+W68+Y68) -> 0 | R68: =R70/R69 -> 0 | T68: =R68/4 -> 0 | V68: =R68/4 -> 0 | X68: =R68/4 -> 0 | Z68: =R68/4 -> 0 | AA68: =SUM(AC68+AE68+AG68+AI68) -> 0 | AB68: =AB70/AB69 -> 0 | AD68: =AB68/4 -> 0 | AF68: =AB68/4 -> 0 | AH68: =AB68/4 -> 0 | AJ68: =AB68/4 -> 0 | AK68: =SUM(AM68+AO68+AQ68+AS68) -> 0 | AL68: =AL70/AL69 -> 0 | AN68: =AL68/4 -> 0 | AP68: =AL68/4 -> 0 | AR68: =AL68/4 -> 0 | AT68: =AL68/4 -> 0 | AU68: =SUM(AW68+AY68+BA68+BC68) -> 0 | AV68: =AV70/AV69 -> 0 | AX68: =AV68/4 -> 0 | AZ68: =AV68/4 -> 0 | BB68: =AV68/4 -> 0 | BD68: =AV68/4 -> 0 | BE68: =SUM(BG68+BI68+BK68+BM68) -> 0 | BF68: =BF70/BF69 -> 0 | BH68: =BF68/4 -> 0 | BJ68: =BF68/4 -> 0 | BL68: =BF68/4 -> 0 | BN68: =BF68/4 -> 0 | BO68: =SUM(BQ68+BS68+BU68+BW68) -> 0 | BP68: =BP70/BP69 -> 0 | BR68: =BP68/4 -> 0 | BT68: =BP68/4 -> 0 | BV68: =BP68/4 -> 0 | BX68: =BP68/4 -> 0 | BY68: =SUM(CA68+CC68+CE68+CG68) -> 0 | BZ68: =BZ70/BZ69 -> 0 | CB68: =BZ68/4 -> 0 | CD68: =BZ68/4 -> 0 | CF68: =BZ68/4 -> 0 | CH68: =BZ68/4 -> 0 | CI68: =SUM(CK68+CM68+CO68+CQ68) -> 0 | CJ68: =CJ70/CJ69 -> 0 | CL68: =CJ68/4 -> 0 | CN68: =CJ68/4 -> 0 | CP68: =CJ68/4 -> 0 | CR68: =CJ68/4 -> 0 | CS68: =SUM(CU68+CW68+CY68+DA68) -> 0 | CT68: =CT70/CT69 -> 0 | CV68: =CT68/4 -> 0 | CX68: =CT68/4 -> 0 | CZ68: =CT68/4 -> 0 | DB68: =CT68/4 -> 0 | DC68: =SUM(DE68+DG68+DI68+DK68) -> 0 | DD68: =DD70/DD69 -> 0 | DF68: =DD68/4 -> 0 | DH68: =DD68/4 -> 0 | DJ68: =DD68/4 -> 0 | DL68: =DD68/4 -> 0 | DM68: =SUM(DO68+DQ68+DS68+DU68) -> 0 | DN68: =DN70/DN69 -> 0 | DP68: =DN68/4 -> 0 | DR68: =DN68/4 -> 0 | DT68: =DN68/4 -> 0 | DV68: =DN68/4 -> 0
C69: % de propostas apresentadas | D69: =D70/D68 -> #DIV/0! | E69: =E70/E68 -> #DIV/0! | F69: =F70/F68 -> #DIV/0! | G69: 0.7 | H69: - | I69: =I70/I68 -> #DIV/0! | J69: =G69 -> 0.7 | K69: =K70/K68 -> #DIV/0! | L69: =G69 -> 0.7 | M69: =M70/M68 -> #DIV/0! | N69: =G69 -> 0.7 | O69: =O70/O68 -> #DIV/0! | P69: =G69 -> 0.7 | Q69: =Q70/Q68 -> #DIV/0! | R69: 0.7 | S69: =S70/S68 -> #DIV/0! | T69: =R69 -> 0.7 | U69: =U70/U68 -> #DIV/0! | V69: =R69 -> 0.7 | W69: =W70/W68 -> #DIV/0! | X69: =R69 -> 0.7 | Y69: =Y70/Y68 -> #DIV/0! | Z69: =R69 -> 0.7 | AA69: =AA70/AA68 -> #DIV/0! | AB69: 0.7 | AC69: =AC70/AC68 -> #DIV/0! | AD69: =AB69 -> 0.7 | AE69: =AE70/AE68 -> #DIV/0! | AF69: =AB69 -> 0.7 | AG69: =AG70/AG68 -> #DIV/0! | AH69: =AB69 -> 0.7 | AI69: =AI70/AI68 -> #DIV/0! | AJ69: =AB69 -> 0.7 | AK69: =AK70/AK68 -> #DIV/0! | AL69: 0.7 | AM69: =AM70/AM68 -> #DIV/0! | AN69: =AL69 -> 0.7 | AO69: =AO70/AO68 -> #DIV/0! | AP69: =AL69 -> 0.7 | AQ69: =AQ70/AQ68 -> #DIV/0! | AR69: =AL69 -> 0.7 | AS69: =AS70/AS68 -> #DIV/0! | AT69: =AL69 -> 0.7 | AU69: =AU70/AU68 -> #DIV/0! | AV69: 0.7 | AW69: =AW70/AW68 -> #DIV/0! | AX69: =AV69 -> 0.7 | AY69: =AY70/AY68 -> #DIV/0! | AZ69: =AV69 -> 0.7 | BA69: =BA70/BA68 -> #DIV/0! | BB69: =AV69 -> 0.7 | BC69: =BC70/BC68 -> #DIV/0! | BD69: =AV69 -> 0.7 | BE69: =BE70/BE68 -> #DIV/0! | BF69: 0.7 | BG69: =BG70/BG68 -> #DIV/0! | BH69: =BF69 -> 0.7 | BI69: =BI70/BI68 -> #DIV/0! | BJ69: =BF69 -> 0.7 | BK69: =BK70/BK68 -> #DIV/0! | BL69: =BF69 -> 0.7 | BM69: =BM70/BM68 -> #DIV/0! | BN69: =BF69 -> 0.7 | BO69: =BO70/BO68 -> #DIV/0! | BP69: 0.7 | BQ69: =BQ70/BQ68 -> #DIV/0! | BR69: =BP69 -> 0.7 | BS69: =BS70/BS68 -> #DIV/0! | BT69: =BP69 -> 0.7 | BU69: =BU70/BU68 -> #DIV/0! | BV69: =BP69 -> 0.7 | BW69: =BW70/BW68 -> #DIV/0! | BX69: =BP69 -> 0.7 | BY69: =BY70/BY68 -> #DIV/0! | BZ69: 0.7 | CA69: =CA70/CA68 -> #DIV/0! | CB69: =BZ69 -> 0.7 | CC69: =CC70/CC68 -> #DIV/0! | CD69: =BZ69 -> 0.7 | CE69: =CE70/CE68 -> #DIV/0! | CF69: =BZ69 -> 0.7 | CG69: =CG70/CG68 -> #DIV/0! | CH69: =BZ69 -> 0.7 | CI69: =CI70/CI68 -> #DIV/0! | CJ69: 0.7 | CK69: =CK70/CK68 -> #DIV/0! | CL69: =CJ69 -> 0.7 | CM69: =CM70/CM68 -> #DIV/0! | CN69: =CJ69 -> 0.7 | CO69: =CO70/CO68 -> #DIV/0! | CP69: =CJ69 -> 0.7 | CQ69: =CQ70/CQ68 -> #DIV/0! | CR69: =CJ69 -> 0.7 | CS69: =CS70/CS68 -> #DIV/0! | CT69: 0.7 | CU69: =CU70/CU68 -> #DIV/0! | CV69: =CT69 -> 0.7 | CW69: =CW70/CW68 -> #DIV/0! | CX69: =CT69 -> 0.7 | CY69: =CY70/CY68 -> #DIV/0! | CZ69: =CT69 -> 0.7 | DA69: =DA70/DA68 -> #DIV/0! | DB69: =CT69 -> 0.7 | DC69: =DC70/DC68 -> #DIV/0! | DD69: 0.7 | DE69: =DE70/DE68 -> #DIV/0! | DF69: =DD69 -> 0.7 | DG69: =DG70/DG68 -> #DIV/0! | DH69: =DD69 -> 0.7 | DI69: =DI70/DI68 -> #DIV/0! | DJ69: =DD69 -> 0.7 | DK69: =DK70/DK68 -> #DIV/0! | DL69: =DD69 -> 0.7 | DM69: =DM70/DM68 -> #DIV/0! | DN69: 0.7 | DO69: =DO70/DO68 -> #DIV/0! | DP69: =DN69 -> 0.7 | DQ69: =DQ70/DQ68 -> #DIV/0! | DR69: =DN69 -> 0.7 | DS69: =DS70/DS68 -> #DIV/0! | DT69: =DN69 -> 0.7 | DU69: =DU70/DU68 -> #DIV/0! | DV69: =DN69 -> 0.7
C70: Total de propostas apresentadas | D70: =SUM(F70+Q70+AA70+AK70+AU70+BE70+BO70+BY70+CI70+CS70+DC70+DM70) -> 0 | E70: =SUM(G70+R70+AB70+AL70+AV70+BF70+BP70+BZ70+CJ70+CT70+DD70+DN70) -> 0 | F70: =SUM(I70+K70+M70+O70) -> 0 | G70: =G72/G71 -> 0 | H70: =G70/F70 -> #DIV/0! | J70: =G70/4 -> 0 | L70: =G70/4 -> 0 | N70: =G70/4 -> 0 | P70: =G70/4 -> 0 | Q70: =SUM(S70+U70+W70+Y70) -> 0 | R70: =R72/R71 -> 0 | T70: =R70/4 -> 0 | V70: =R70/4 -> 0 | X70: =R70/4 -> 0 | Z70: =R70/4 -> 0 | AA70: =SUM(AC70+AE70+AG70+AI70) -> 0 | AB70: =AB72/AB71 -> 0 | AD70: =AB70/4 -> 0 | AF70: =AB70/4 -> 0 | AH70: =AB70/4 -> 0 | AJ70: =AB70/4 -> 0 | AK70: =SUM(AM70+AO70+AQ70+AS70) -> 0 | AL70: =AL72/AL71 -> 0 | AN70: =AL70/4 -> 0 | AP70: =AL70/4 -> 0 | AR70: =AL70/4 -> 0 | AT70: =AL70/4 -> 0 | AU70: =SUM(AW70+AY70+BA70+BC70) -> 0 | AV70: =AV72/AV71 -> 0 | AX70: =AV70/4 -> 0 | AZ70: =AV70/4 -> 0 | BB70: =AV70/4 -> 0 | BD70: =AV70/4 -> 0 | BE70: =SUM(BG70+BI70+BK70+BM70) -> 0 | BF70: =BF72/BF71 -> 0 | BH70: =BF70/4 -> 0 | BJ70: =BF70/4 -> 0 | BL70: =BF70/4 -> 0 | BN70: =BF70/4 -> 0 | BO70: =SUM(BQ70+BS70+BU70+BW70) -> 0 | BP70: =BP72/BP71 -> 0 | BR70: =BP70/4 -> 0 | BT70: =BP70/4 -> 0 | BV70: =BP70/4 -> 0 | BX70: =BP70/4 -> 0 | BY70: =SUM(CA70+CC70+CE70+CG70) -> 0 | BZ70: =BZ72/BZ71 -> 0 | CB70: =BZ70/4 -> 0 | CD70: =BZ70/4 -> 0 | CF70: =BZ70/4 -> 0 | CH70: =BZ70/4 -> 0 | CI70: =SUM(CK70+CM70+CO70+CQ70) -> 0 | CJ70: =CJ72/CJ71 -> 0 | CL70: =CJ70/4 -> 0 | CN70: =CJ70/4 -> 0 | CP70: =CJ70/4 -> 0 | CR70: =CJ70/4 -> 0 | CS70: =SUM(CU70+CW70+CY70+DA70) -> 0 | CT70: =CT72/CT71 -> 0 | CV70: =CT70/4 -> 0 | CX70: =CT70/4 -> 0 | CZ70: =CT70/4 -> 0 | DB70: =CT70/4 -> 0 | DC70: =SUM(DE70+DG70+DI70+DK70) -> 0 | DD70: =DD72/DD71 -> 0 | DF70: =DD70/4 -> 0 | DH70: =DD70/4 -> 0 | DJ70: =DD70/4 -> 0 | DL70: =DD70/4 -> 0 | DM70: =SUM(DO70+DQ70+DS70+DU70) -> 0 | DN70: =DN72/DN71 -> 0 | DP70: =DN70/4 -> 0 | DR70: =DN70/4 -> 0 | DT70: =DN70/4 -> 0 | DV70: =DN70/4 -> 0
C71: % de fechamento | D71: =D72/D70 -> #DIV/0! | E71: =E72/E70 -> #DIV/0! | F71: =F72/F70 -> #DIV/0! | G71: 0.4 | H71: - | I71: =I72/I70 -> #DIV/0! | J71: =G71 -> 0.4 | K71: =K72/K70 -> #DIV/0! | L71: =G71 -> 0.4 | M71: =M72/M70 -> #DIV/0! | N71: =G71 -> 0.4 | O71: =O72/O70 -> #DIV/0! | P71: =G71 -> 0.4 | Q71: =Q72/Q70 -> #DIV/0! | R71: 0.4 | S71: =S72/S70 -> #DIV/0! | T71: =R71 -> 0.4 | U71: =U72/U70 -> #DIV/0! | V71: =R71 -> 0.4 | W71: =W72/W70 -> #DIV/0! | X71: =R71 -> 0.4 | Y71: =Y72/Y70 -> #DIV/0! | Z71: =R71 -> 0.4 | AA71: =AA72/AA70 -> #DIV/0! | AB71: 0.4 | AC71: =AC72/AC70 -> #DIV/0! | AD71: =AB71 -> 0.4 | AE71: =AE72/AE70 -> #DIV/0! | AF71: =AB71 -> 0.4 | AG71: =AG72/AG70 -> #DIV/0! | AH71: =AB71 -> 0.4 | AI71: =AI72/AI70 -> #DIV/0! | AJ71: =AB71 -> 0.4 | AK71: =AK72/AK70 -> #DIV/0! | AL71: 0.4 | AM71: =AM72/AM70 -> #DIV/0! | AN71: =AL71 -> 0.4 | AO71: =AO72/AO70 -> #DIV/0! | AP71: =AL71 -> 0.4 | AQ71: =AQ72/AQ70 -> #DIV/0! | AR71: =AL71 -> 0.4 | AS71: =AS72/AS70 -> #DIV/0! | AT71: =AL71 -> 0.4 | AU71: =AU72/AU70 -> #DIV/0! | AV71: 0.4 | AW71: =AW72/AW70 -> #DIV/0! | AX71: =AV71 -> 0.4 | AY71: =AY72/AY70 -> #DIV/0! | AZ71: =AV71 -> 0.4 | BA71: =BA72/BA70 -> #DIV/0! | BB71: =AV71 -> 0.4 | BC71: =BC72/BC70 -> #DIV/0! | BD71: =AV71 -> 0.4 | BE71: =BE72/BE70 -> #DIV/0! | BF71: 0.4 | BG71: =BG72/BG70 -> #DIV/0! | BH71: =BF71 -> 0.4 | BI71: =BI72/BI70 -> #DIV/0! | BJ71: =BF71 -> 0.4 | BK71: =BK72/BK70 -> #DIV/0! | BL71: =BF71 -> 0.4 | BM71: =BM72/BM70 -> #DIV/0! | BN71: =BF71 -> 0.4 | BO71: =BO72/BO70 -> #DIV/0! | BP71: 0.4 | BQ71: =BQ72/BQ70 -> #DIV/0! | BR71: =BP71 -> 0.4 | BS71: =BS72/BS70 -> #DIV/0! | BT71: =BP71 -> 0.4 | BU71: =BU72/BU70 -> #DIV/0! | BV71: =BP71 -> 0.4 | BW71: =BW72/BW70 -> #DIV/0! | BX71: =BP71 -> 0.4 | BY71: =BY72/BY70 -> #DIV/0! | BZ71: 0.4 | CA71: =CA72/CA70 -> #DIV/0! | CB71: =BZ71 -> 0.4 | CC71: =CC72/CC70 -> #DIV/0! | CD71: =BZ71 -> 0.4 | CE71: =CE72/CE70 -> #DIV/0! | CF71: =BZ71 -> 0.4 | CG71: =CG72/CG70 -> #DIV/0! | CH71: =BZ71 -> 0.4 | CI71: =CI72/CI70 -> #DIV/0! | CJ71: 0.4 | CK71: =CK72/CK70 -> #DIV/0! | CL71: =CJ71 -> 0.4 | CM71: =CM72/CM70 -> #DIV/0! | CN71: =CJ71 -> 0.4 | CO71: =CO72/CO70 -> #DIV/0! | CP71: =CJ71 -> 0.4 | CQ71: =CQ72/CQ70 -> #DIV/0! | CR71: =CJ71 -> 0.4 | CS71: =CS72/CS70 -> #DIV/0! | CT71: 0.4 | CU71: =CU72/CU70 -> #DIV/0! | CV71: =CT71 -> 0.4 | CW71: =CW72/CW70 -> #DIV/0! | CX71: =CT71 -> 0.4 | CY71: =CY72/CY70 -> #DIV/0! | CZ71: =CT71 -> 0.4 | DA71: =DA72/DA70 -> #DIV/0! | DB71: =CT71 -> 0.4 | DC71: =DC72/DC70 -> #DIV/0! | DD71: 0.4 | DE71: =DE72/DE70 -> #DIV/0! | DF71: =DD71 -> 0.4 | DG71: =DG72/DG70 -> #DIV/0! | DH71: =DD71 -> 0.4 | DI71: =DI72/DI70 -> #DIV/0! | DJ71: =DD71 -> 0.4 | DK71: =DK72/DK70 -> #DIV/0! | DL71: =DD71 -> 0.4 | DM71: =DM72/DM70 -> #DIV/0! | DN71: 0.4 | DO71: =DO72/DO70 -> #DIV/0! | DP71: =DN71 -> 0.4 | DQ71: =DQ72/DQ70 -> #DIV/0! | DR71: =DN71 -> 0.4 | DS71: =DS72/DS70 -> #DIV/0! | DT71: =DN71 -> 0.4 | DU71: =DU72/DU70 -> #DIV/0! | DV71: =DN71 -> 0.4
C72: Total de propostas fechadas | D72: =SUM(F72+Q72+AA72+AK72+AU72+BE72+BO72+BY72+CI72+CS72+DC72+DM72) -> 0 | E72: =SUM(G72+R72+AB72+AL72+AV72+BF72+BP72+BZ72+CJ72+CT72+DD72+DN72) -> 0 | F72: =SUM(I72+K72+M72+O72) -> 0 | G72: ='Dados da Operação'!H30 -> 0 | H72: =G72/F72 -> #DIV/0! | J72: =G72/4 -> 0 | L72: =G72/4 -> 0 | N72: =G72/4 -> 0 | P72: =G72/4 -> 0 | Q72: =SUM(S72+U72+W72+Y72) -> 0 | R72: ='Dados da Operação'!H39 -> 0 | T72: =R72/4 -> 0 | V72: =R72/4 -> 0 | X72: =R72/4 -> 0 | Z72: =R72/4 -> 0 | AA72: =SUM(AC72+AE72+AG72+AI72) -> 0 | AB72: ='Dados da Operação'!H48 -> 0 | AD72: =AB72/4 -> 0 | AF72: =AB72/4 -> 0 | AH72: =AB72/4 -> 0 | AJ72: =AB72/4 -> 0 | AK72: =SUM(AM72+AO72+AQ72+AS72) -> 0 | AL72: ='Dados da Operação'!H57 -> 0 | AN72: =AL72/4 -> 0 | AP72: =AL72/4 -> 0 | AR72: =AL72/4 -> 0 | AT72: =AL72/4 -> 0 | AU72: =SUM(AW72+AY72+BA72+BC72) -> 0 | AV72: ='Dados da Operação'!H66 -> 0 | AX72: =AV72/4 -> 0 | AZ72: =AV72/4 -> 0 | BB72: =AV72/4 -> 0 | BD72: =AV72/4 -> 0 | BE72: =SUM(BG72+BI72+BK72+BM72) -> 0 | BF72: ='Dados da Operação'!H75 -> 0 | BH72: =BF72/4 -> 0 | BJ72: =BF72/4 -> 0 | BL72: =BF72/4 -> 0 | BN72: =BF72/4 -> 0 | BO72: =SUM(BQ72+BS72+BU72+BW72) -> 0 | BP72: ='Dados da Operação'!H84 -> 0 | BR72: =BP72/4 -> 0 | BT72: =BP72/4 -> 0 | BV72: =BP72/4 -> 0 | BX72: =BP72/4 -> 0 | BY72: =SUM(CA72+CC72+CE72+CG72) -> 0 | BZ72: ='Dados da Operação'!H93 -> 0 | CB72: =BZ72/4 -> 0 | CD72: =BZ72/4 -> 0 | CF72: =BZ72/4 -> 0 | CH72: =BZ72/4 -> 0 | CI72: =SUM(CK72+CM72+CO72+CQ72) -> 0 | CJ72: ='Dados da Operação'!H102 -> 0 | CL72: =CJ72/4 -> 0 | CN72: =CJ72/4 -> 0 | CP72: =CJ72/4 -> 0 | CR72: =CJ72/4 -> 0 | CS72: =SUM(CU72+CW72+CY72+DA72) -> 0 | CT72: ='Dados da Operação'!H111 -> 0 | CV72: =CT72/4 -> 0 | CX72: =CT72/4 -> 0 | CZ72: =CT72/4 -> 0 | DB72: =CT72/4 -> 0 | DC72: =SUM(DE72+DG72+DI72+DK72) -> 0 | DD72: ='Dados da Operação'!H120 -> 0 | DF72: =DD72/4 -> 0 | DH72: =DD72/4 -> 0 | DJ72: =DD72/4 -> 0 | DL72: =DD72/4 -> 0 | DM72: =SUM(DO72+DQ72+DS72+DU72) -> 0 | DN72: ='Dados da Operação'!H129 -> 0 | DP72: =DN72/4 -> 0 | DR72: =DN72/4 -> 0 | DT72: =DN72/4 -> 0 | DV72: =DN72/4 -> 0
C73: Total de faturamento | D73: =SUM(F73+Q73+AA73+AK73+AU73+BE73+BO73+BY73+CI73+CS73+DC73+DM73) -> 0 | E73: =SUM(G73+R73+AB73+AL73+AV73+BF73+BP73+BZ73+CJ73+CT73+DD73+DN73) -> 0 | F73: =SUM(I73+K73+M73+O73) -> 0 | G73: ='Dados da Operação'!G30 -> 0 | H73: =G73/F73 -> #DIV/0! | J73: =G73/4 -> 0 | L73: =G73/4 -> 0 | N73: =G73/4 -> 0 | P73: =G73/4 -> 0 | Q73: =SUM(S73+U73+W73+Y73) -> 0 | R73: ='Dados da Operação'!G39 -> 0 | T73: =R73/4 -> 0 | V73: =R73/4 -> 0 | X73: =R73/4 -> 0 | Z73: =R73/4 -> 0 | AA73: =SUM(AC73+AE73+AG73+AI73) -> 0 | AB73: ='Dados da Operação'!G48 -> 0 | AD73: =AB73/4 -> 0 | AF73: =AB73/4 -> 0 | AH73: =AB73/4 -> 0 | AJ73: =AB73/4 -> 0 | AK73: =SUM(AM73+AO73+AQ73+AS73) -> 0 | AL73: ='Dados da Operação'!G57 -> 0 | AN73: =AL73/4 -> 0 | AP73: =AL73/4 -> 0 | AR73: =AL73/4 -> 0 | AT73: =AL73/4 -> 0 | AU73: =SUM(AW73+AY73+BA73+BC73) -> 0 | AV73: ='Dados da Operação'!G66 -> 0 | AX73: =AV73/4 -> 0 | AZ73: =AV73/4 -> 0 | BB73: =AV73/4 -> 0 | BD73: =AV73/4 -> 0 | BE73: =SUM(BG73+BI73+BK73+BM73) -> 0 | BF73: ='Dados da Operação'!G75 -> 0 | BH73: =BF73/4 -> 0 | BJ73: =BF73/4 -> 0 | BL73: =BF73/4 -> 0 | BN73: =BF73/4 -> 0 | BO73: =SUM(BQ73+BS73+BU73+BW73) -> 0 | BP73: ='Dados da Operação'!G84 -> 0 | BR73: =BP73/4 -> 0 | BT73: =BP73/4 -> 0 | BV73: =BP73/4 -> 0 | BX73: =BP73/4 -> 0 | BY73: =SUM(CA73+CC73+CE73+CG73) -> 0 | BZ73: ='Dados da Operação'!G93 -> 0 | CB73: =BZ73/4 -> 0 | CD73: =BZ73/4 -> 0 | CF73: =BZ73/4 -> 0 | CH73: =BZ73/4 -> 0 | CI73: =SUM(CK73+CM73+CO73+CQ73) -> 0 | CJ73: ='Dados da Operação'!G102 -> 0 | CL73: =CJ73/4 -> 0 | CN73: =CJ73/4 -> 0 | CP73: =CJ73/4 -> 0 | CR73: =CJ73/4 -> 0 | CS73: =SUM(CU73+CW73+CY73+DA73) -> 0 | CT73: ='Dados da Operação'!G111 -> 0 | CV73: =CT73/4 -> 0 | CX73: =CT73/4 -> 0 | CZ73: =CT73/4 -> 0 | DB73: =CT73/4 -> 0 | DC73: =SUM(DE73+DG73+DI73+DK73) -> 0 | DD73: ='Dados da Operação'!G120 -> 0 | DF73: =DD73/4 -> 0 | DH73: =DD73/4 -> 0 | DJ73: =DD73/4 -> 0 | DL73: =DD73/4 -> 0 | DM73: =SUM(DO73+DQ73+DS73+DU73) -> 0 | DN73: ='Dados da Operação'!G129 -> 0 | DP73: =DN73/4 -> 0 | DR73: =DN73/4 -> 0 | DT73: =DN73/4 -> 0 | DV73: =DN73/4 -> 0
C74: Ticket médio | D74: =D73/D72 -> #DIV/0! | E74: =E73/E72 -> #DIV/0! | F74: =F73/F72 -> #DIV/0! | G74: ='Dados da Operação'!$C$5 -> 2500 | H74: =G74/F74 -> #DIV/0! | I74: =I73/I72 -> #DIV/0! | J74: =G74 -> 2500 | K74: =K73/K72 -> #DIV/0! | L74: =G74 -> 2500 | M74: =M73/M72 -> #DIV/0! | N74: =G74 -> 2500 | O74: =O73/O72 -> #DIV/0! | P74: =G74 -> 2500 | Q74: =Q73/Q72 -> #DIV/0! | R74: ='Dados da Operação'!$C$5 -> 2500 | S74: =S73/S72 -> #DIV/0! | T74: =R74 -> 2500 | U74: =U73/U72 -> #DIV/0! | V74: =R74 -> 2500 | W74: =W73/W72 -> #DIV/0! | X74: =R74 -> 2500 | Y74: =Y73/Y72 -> #DIV/0! | Z74: =R74 -> 2500 | AA74: =AA73/AA72 -> #DIV/0! | AB74: ='Dados da Operação'!$C$5 -> 2500 | AC74: =AC73/AC72 -> #DIV/0! | AD74: =AB74 -> 2500 | AE74: =AE73/AE72 -> #DIV/0! | AF74: =AB74 -> 2500 | AG74: =AG73/AG72 -> #DIV/0! | AH74: =AB74 -> 2500 | AI74: =AI73/AI72 -> #DIV/0! | AJ74: =AB74 -> 2500 | AK74: =AK73/AK72 -> #DIV/0! | AL74: ='Dados da Operação'!$C$5 -> 2500 | AM74: =AM73/AM72 -> #DIV/0! | AN74: =AL74 -> 2500 | AO74: =AO73/AO72 -> #DIV/0! | AP74: =AL74 -> 2500 | AQ74: =AQ73/AQ72 -> #DIV/0! | AR74: =AL74 -> 2500 | AS74: =AS73/AS72 -> #DIV/0! | AT74: =AL74 -> 2500 | AU74: =AU73/AU72 -> #DIV/0! | AV74: ='Dados da Operação'!$C$5 -> 2500 | AW74: =AW73/AW72 -> #DIV/0! | AX74: =AV74 -> 2500 | AY74: =AY73/AY72 -> #DIV/0! | AZ74: =AV74 -> 2500 | BA74: =BA73/BA72 -> #DIV/0! | BB74: =AV74 -> 2500 | BC74: =BC73/BC72 -> #DIV/0! | BD74: =AV74 -> 2500 | BE74: =BE73/BE72 -> #DIV/0! | BF74: ='Dados da Operação'!$C$5 -> 2500 | BG74: =BG73/BG72 -> #DIV/0! | BH74: =BF74 -> 2500 | BI74: =BI73/BI72 -> #DIV/0! | BJ74: =BF74 -> 2500 | BK74: =BK73/BK72 -> #DIV/0! | BL74: =BF74 -> 2500 | BM74: =BM73/BM72 -> #DIV/0! | BN74: =BF74 -> 2500 | BO74: =BO73/BO72 -> #DIV/0! | BP74: ='Dados da Operação'!$C$5 -> 2500 | BQ74: =BQ73/BQ72 -> #DIV/0! | BR74: =BP74 -> 2500 | BS74: =BS73/BS72 -> #DIV/0! | BT74: =BP74 -> 2500 | BU74: =BU73/BU72 -> #DIV/0! | BV74: =BP74 -> 2500 | BW74: =BW73/BW72 -> #DIV/0! | BX74: =BP74 -> 2500 | BY74: =BY73/BY72 -> #DIV/0! | BZ74: ='Dados da Operação'!$C$5 -> 2500 | CA74: =CA73/CA72 -> #DIV/0! | CB74: =BZ74 -> 2500 | CC74: =CC73/CC72 -> #DIV/0! | CD74: =BZ74 -> 2500 | CE74: =CE73/CE72 -> #DIV/0! | CF74: =BZ74 -> 2500 | CG74: =CG73/CG72 -> #DIV/0! | CH74: =BZ74 -> 2500 | CI74: =CI73/CI72 -> #DIV/0! | CJ74: ='Dados da Operação'!$C$5 -> 2500 | CK74: =CK73/CK72 -> #DIV/0! | CL74: =CJ74 -> 2500 | CM74: =CM73/CM72 -> #DIV/0! | CN74: =CJ74 -> 2500 | CO74: =CO73/CO72 -> #DIV/0! | CP74: =CJ74 -> 2500 | CQ74: =CQ73/CQ72 -> #DIV/0! | CR74: =CJ74 -> 2500 | CS74: =CS73/CS72 -> #DIV/0! | CT74: ='Dados da Operação'!$C$5 -> 2500 | CU74: =CU73/CU72 -> #DIV/0! | CV74: =CT74 -> 2500 | CW74: =CW73/CW72 -> #DIV/0! | CX74: =CT74 -> 2500 | CY74: =CY73/CY72 -> #DIV/0! | CZ74: =CT74 -> 2500 | DA74: =DA73/DA72 -> #DIV/0! | DB74: =CT74 -> 2500 | DC74: =DC73/DC72 -> #DIV/0! | DD74: ='Dados da Operação'!$C$5 -> 2500 | DE74: =DE73/DE72 -> #DIV/0! | DF74: =DD74 -> 2500 | DG74: =DG73/DG72 -> #DIV/0! | DH74: =DD74 -> 2500 | DI74: =DI73/DI72 -> #DIV/0! | DJ74: =DD74 -> 2500 | DK74: =DK73/DK72 -> #DIV/0! | DL74: =DD74 -> 2500 | DM74: =DM73/DM72 -> #DIV/0! | DN74: ='Dados da Operação'!$C$5 -> 2500 | DO74: =DO73/DO72 -> #DIV/0! | DP74: =DN74 -> 2500 | DQ74: =DQ73/DQ72 -> #DIV/0! | DR74: =DN74 -> 2500 | DS74: =DS73/DS72 -> #DIV/0! | DT74: =DN74 -> 2500 | DU74: =DU73/DU72 -> #DIV/0! | DV74: =DN74 -> 2500

Sheet KPIs e Projeções Meta Contabili
M2: BDR | Y2: 1
B3: KPIs | C3: Previsão | E3: 45299 | F3: 45303 | G3: 45306 | H3: 45310 | I3: 45313 | J3: 45317 | K3: 45320 | L3: 45322 | M3: BDR | Y3: Closer
C4: Meta | D4: KPIS | E4: Atingido | F4: Meta | G4: Atingido | H4: Meta | I4: Atingido | J4: Meta | K4: Atingido | L4: Meta | M4: Meta | N4: KPIS | Y4: Meta | Z4: KPIS
B5: Cadências abertas (contatos) | C5: =C7/D6 -> 1234.5679 | M5: =C5/Y2 -> 1234.5679
B6: % Conversão em Lead Conectado | C6: =C7/C5 -> 0.15 | D6: 0.15 | E6: =E7/E5 -> #DIV/0! | F6: =F7/F5 -> #DIV/0! | G6: =G7/G5 -> #DIV/0! | H6: =H7/H5 -> #DIV/0! | I6: =I7/I5 -> #DIV/0! | J6: =J7/J5 -> #DIV/0! | K6: =K7/K5 -> #DIV/0! | L6: =L7/L5 -> #DIV/0! | M6: =M7/M5 -> 0.15 | N6: 0.15
B7: Leads conectados | C7: =C9/D8 -> 185.18519 | M7: =C7/Y2 -> 185.18519
B8: % Conversão em Reunião agendada | C8: =C9/C7 -> 0.2 | D8: 0.2 | E8: =E9/E7 -> #DIV/0! | F8: =F9/F7 -> #DIV/0! | G8: =G9/G7 -> #DIV/0! | H8: =H9/H7 -> #DIV/0! | I8: =I9/I7 -> #DIV/0! | J8: =J9/J7 -> #DIV/0! | K8: =K9/K7 -> #DIV/0! | L8: =L9/L7 -> #DIV/0! | M8: =M9/M7 -> 0.2 | N8: 0.15
B9: Reunião agendada | C9: =C11/D10 -> 37.037037 | M9: =C9/Y2 -> 37.037037
B10: % de reunião realizada | C10: =C11/C9 -> 0.9 | D10: 0.9 | E10: =E11/E9 -> #DIV/0! | F10: =F11/F9 -> #DIV/0! | G10: =G11/G9 -> #DIV/0! | H10: =H11/H9 -> #DIV/0! | I10: =I11/I9 -> #DIV/0! | J10: =J11/J9 -> #DIV/0! | K10: =K11/K9 -> #DIV/0! | L10: =L11/L9 -> #DIV/0! | M10: =M11/M9 -> 0.9 | N10: 0.8
B11: Reunião realizada | C11: =C13/D12 -> 33.333333 | M11: =C11/Y2 -> 33.333333 | Y11: =C11 -> 33.333333
B12: % Conversão em Proposta | C12: =C13/C11 -> 0.6 | D12: 0.6 | E12: =E13/E11 -> #DIV/0! | F12: =F13/F11 -> #DIV/0! | G12: =G13/G11 -> #DIV/0! | H12: =H13/H11 -> #DIV/0! | I12: =I13/I11 -> #DIV/0! | J12: =J13/J11 -> #DIV/0! | K12: =K13/K11 -> #DIV/0! | L12: =L13/L11 -> #DIV/0! | Y12: =Y13/Y11 -> 0.6 | Z12: 1
B13: Propostas enviadas | C13: =C15/D14 -> 20 | Y13: =C13 -> 20
B14: % Conversão em Vendas | C14: =C15/C13 -> 0.35 | D14: 0.35 | E14: =E15/E13 -> #DIV/0! | F14: =F15/F13 -> #DIV/0! | G14: =G15/G13 -> #DIV/0! | H14: =H15/H13 -> #DIV/0! | I14: =I15/I13 -> #DIV/0! | J14: =J15/J13 -> #DIV/0! | K14: =K15/K13 -> #DIV/0! | L14: =L15/L13 -> #DIV/0! | Y14: =Y15/Y13 -> 0.35 | Z14: 0.25
B15: Volume de Vendas | C15: 7 | Y15: =C15 -> 7
B16: Total de Venda (R$) | C16: =B17*C15 -> 14000 | Y16: =AH17*Y15 -> 0
A17: ticketmédio | B17: 2000
B21: Crescimento Meta
B22: Indicadores - Projeção | C22: Janeiro | E22: 45299 | F22: 45303 | G22: 45306 | H22: 45310 | I22: 45313 | J22: 45317 | K22: 45320 | L22: 45322 | M22: Fevereiro | O22: 45323 | P22: 45324 | Q22: 45327 | R22: 45331 | S22: 45334 | T22: 45338 | U22: 45341 | V22: 45345 | W22: 45348 | X22: 45351 | Y22: Março | AA22: 45352 | AB22: 45359 | AC22: 45362 | AD22: 45366 | AE22: 45369 | AF22: 45373 | AG22: 45376 | AH22: 45382 | AI22: Abril | AK22: 45383 | AL22: 45389 | AM22: 45390 | AN22: 45396 | AO22: 45397 | AP22: 45403 | AQ22: 45404 | AR22: 45410 | AS22: 45411 | AT22: 45412 | AU22: Maio | AW22: 45413 | AY22: 45417 | BA22: 45424 | BC22: 45431 | BE22: 45438 | BG22: Junho | BI22: 45446 | BK22: 45453 | BM22: 45460 | BO22: 45467 | BQ22: 1° Semestre | BS22: Julho | BU22: Agosto | BW22: Setembro | BY22: 45187 | BZ22: 45191 | CA22: 45194 | CB22: 45198 | CC22: Outubro | CE22: 45201 | CF22: 45205 | CG22: 45208 | CH22: 45212 | CI22: 45215 | CJ22: 45219 | CK22: 45222 | CL22: 45226 | CM22: 45229 | CN22: 45230 | CO22: Novembro | CQ22: 45231 | CR22: 45233 | CS22: 45236 | CT22: 45240 | CU22: 45243 | CV22: 45247 | CW22: 45250 | CX22: 45254 | CY22: 45257 | CZ22: 45260 | DA22: Dezembro | DC22: 45261 | DD22: 45261 | DE22: 45264 | DF22: 45268 | DG22: 45271 | DH22: 45275 | DI22: 45278 | DJ22: 45282 | DK22: 45285 | DL22: 45289 | DM22: 2° Semestre | DO22: TOTAL
C23: Atingido | D23: Meta | E23: Atingido | F23: Meta | G23: Atingido | H23: Meta | I23: Atingido | J23: Meta | K23: Atingido | L23: Meta | M23: Atingido | N23: Meta | O23: Atingido | P23: Meta | Q23: Atingido | R23: Meta | S23: Atingido | T23: Meta | U23: Atingido | V23: Meta | W23: Atingido | X23: Meta | Y23: Atingido | Z23: Meta | AA23: Atingido | AB23: Meta | AC23: Atingido | AD23: Meta | AE23: Atingido | AF23: Meta | AG23: Atingido | AH23: Meta | AI23: Atingido | AJ23: Meta | AK23: Atingido | AL23: Meta | AM23: Atingido | AN23: Meta | AO23: Atingido | AP23: Meta | AQ23: Atingido | AR23: Meta | AS23: Atingido | AT23: Meta | AU23: Atingido | AV23: Meta | AW23: Atingido | AX23: Meta | AY23: Atingido | AZ23: Meta | BA23: Atingido | BB23: Meta | BC23: Atingido | BD23: Meta | BE23: Atingido | BF23: Meta | BG23: Atingido | BH23: Meta | BI23: Atingido | BJ23: Meta | BK23: Atingido | BL23: Meta | BM23: Atingido | BN23: Meta | BO23: Atingido | BP23: Meta | BQ23: Atingido | BR23: Meta | BS23: Atingido | BT23: Meta | BU23: Atingido | BV23: Meta | BW23: Atingido | BX23: Meta | BY23: Atingido | BZ23: Meta | CA23: Atingido | CB23: Meta | CC23: Atingido | CD23: Meta | CE23: Atingido | CF23: Meta | CG23: Atingido | CH23: Meta | CI23: Atingido | CJ23: Meta | CK23: Atingido | CL23: Meta | CM23: Atingido | CN23: Meta | CO23: Atingido | CP23: Meta | CQ23: Atingido | CR23: Meta | CS23: Atingido | CT23: Meta | CU23: Atingido | CV23: Meta | CW23: Atingido | CX23: Meta | CY23: Atingido | CZ23: Meta | DA23: Atingido | DB23: Meta | DC23: Atingido | DD23: Meta | DE23: Atingido | DF23: Meta | DG23: Atingido | DH23: Meta | DI23: Atingido | DJ23: Meta | DK23: Atingido | DL23: Meta | DM23: Atingido | DN23: Meta | DO23: Atingido | DP23: Meta
B24: Cadências abertas (contatos) | AU24: =AW24+AY24+BA24+BC24++BE24 -> 0 | AX24: =$AV$24/5 -> 0 | AZ24: =$AV$24/5 -> 0 | BB24: =$AV$24/5 -> 0 | BD24: =$AV$24/5 -> 0 | BF24: =$AV$24/5 -> 0 | BJ24: =$BH24/4 -> 0 | BL24: =$BH$24/4 -> 0 | BN24: =$BH$24/4 -> 0 | BP24: =$BH$24/4 -> 0 | BQ24: =SUM(W24,Y24,AA24,AG24,AS24,BE24) -> 0 | BR24: 175 | BT24: 529.10053 | BV24: 881.83422 | BX24: 1234.5679 | CD24: 1234.5679 | CP24: 1234.5679 | DB24: 1234.5679 | DM24: =SUM(BS24,BU24,BW24,CC24,CO24,DA24) -> 0 | DN24: =SUM(BT24,BV24,BX24,CD24,CP24,DB24) -> 6349.2063 | DO24: =SUM(BQ24,DM24) -> 0 | DP24: =SUM(BR24,DN24) -> 6524.2063
B25: % Conversão em Lead Conectado | C25: =C26/C24 -> #DIV/0! | D25: =D26/D24 -> #DIV/0! | E25: =E26/E24 -> #DIV/0! | F25: =F26/F24 -> #DIV/0! | G25: =G26/G24 -> #DIV/0! | H25: =H26/H24 -> #DIV/0! | I25: =I26/I24 -> #DIV/0! | J25: =J26/J24 -> #DIV/0! | ... DJ25: =DJ26/DJ24 -> #DIV/0! | DM25: =DM26/DM24 -> #DIV/0! | DN25: =DN26/DN24 -> 0.15 | DO25: =DO26/DO24 -> #DIV/0! | DP25: =DP26/DP24 -> 0.14597652
B26: Leads conectados | AU26: =AW26+AY26+BA26+BC26++BE26 -> 0 | AX26: =$AV26/5 -> 0 | AZ26: =$AV26/5 -> 0 | BB26: =$AV26/5 -> 0 | BD26: =$AV26/5 -> 0 | BF26: =$AV26/5 -> 0 | BJ26: =$BH26/4 -> 0 | BQ26: =SUM(W26,Y26,AA26,AG26,AS26,BE26) -> 0 | BR26: =SUM(D26,N26,Z26,AJ26,AV26,BH26) -> 0 | BT26: 79.365079 | BV26: 132.27513 | BX26: 185.18519 | CD26: 185.18519 | CP26: 185.18519 | DB26: 185.18519 | DM26: =SUM(BS26,BU26,BW26,CC26,CO26,DA26) -> 0 | DN26: =SUM(BT26,BV26,BX26,CD26,CP26,DB26) -> 952.38095 | DO26: =SUM(BQ26,DM26) -> 0 | DP26: =SUM(BR26,DN26) -> 952.38095
B27: % Conversão em Reunião agendada | C27: =C28/C26 -> #DIV/0! | D27: =D28/D26 -> #DIV/0! | E27: =E28/E26 -> #DIV/0! | F27: =F28/F26 -> #DIV/0! | G27: =G28/G26 -> #DIV/0! | H27: =H28/H26 -> #DIV/0! | I27: =I28/I26 -> #DIV/0! | J27: =J28/J26 -> #DIV/0! | ... DJ27: =DJ28/DJ26 -> #DIV/0! | DM27: =DM28/DM26 -> #DIV/0! | DN27: =DN28/DN26 -> 0.2 | DO27: =DO28/DO26 -> #DIV/0! | DP27: =DP28/DP26 -> 0.2
B28: Reunião agendada | AU28: =AW28+AY28+BA28+BC28++BE28 -> 0 | AX28: =$AV28/5 -> 0 | AZ28: =$AV28/5 -> 0 | BB28: =$AV28/5 -> 0 | BD28: =$AV28/5 -> 0 | BF28: =$AV28/5 -> 0 | BJ28: =$BH28/4 -> 0 | BQ28: =SUM(W28,Y28,AA28,AG28,AS28,BE28) -> 0 | BR28: =SUM(D28,N28,Z28,AJ28,AV28,BH28) -> 0 | BT28: 15.873016 | BV28: 26.455026 | BX28: 37.037037 | CD28: 37.037037 | CP28: 37.037037 | DB28: 37.037037 | DM28: =SUM(BS28,BU28,BW28,CC28,CO28,DA28) -> 0 | DN28: =SUM(BT28,BV28,BX28,CD28,CP28,DB28) -> 190.47619 | DO28: =SUM(BQ28,DM28) -> 0 | DP28: =SUM(BR28,DN28) -> 190.47619
B29: % de reunião realizada | C29: =C30/C28 -> #DIV/0! | D29: =D30/D28 -> #DIV/0! | E29: =E30/E28 -> #DIV/0! | F29: =F30/F28 -> #DIV/0! | G29: =G30/G28 -> #DIV/0! | H29: =H30/H28 -> #DIV/0! | I29: =I30/I28 -> #DIV/0! | J29: =J30/J28 -> #DIV/0! | ... DJ29: =DJ30/DJ28 -> #DIV/0! | DM29: =DM30/DM28 -> #DIV/0! | DN29: =DN30/DN28 -> 0.9 | DO29: =DO30/DO28 -> #DIV/0! | DP29: =DP30/DP28 -> 0.9
B30: Reunião realizada | E30: 49 | F30: 40 | AU30: =AW30+AY30+BA30+BC30++BE30 -> 0 | AX30: =$AV30/5 -> 0 | AZ30: =$AV30/5 -> 0 | BB30: =$AV30/5 -> 0 | BD30: =$AV30/5 -> 0 | BF30: =$AV30/5 -> 0 | BJ30: =$BH30/4 -> 0 | BQ30: =SUM(W30,Y30,AA30,AG30,AS30,BE30) -> 0 | BR30: =SUM(D30,N30,Z30,AJ30,AV30,BH30) -> 0 | BT30: 14.285714 | BV30: 23.809524 | BX30: 33.333333 | CD30: 33.333333 | CP30: 33.333333 | DB30: 33.333333 | DM30: =SUM(BS30,BU30,BW30,CC30,CO30,DA30) -> 0 | DN30: =SUM(BT30,BV30,BX30,CD30,CP30,DB30) -> 171.42857 | DO30: =SUM(BQ30,DM30) -> 0 | DP30: =SUM(BR30,DN30) -> 171.42857
B31: % Conversão em Proposta | C31: =C32/C30 -> #DIV/0! | D31: =D32/D30 -> #DIV/0! | E31: =E32/E30 -> 1 | F31: =F32/F30 -> 1 | G31: =G32/G30 -> #DIV/0! | H31: =H32/H30 -> #DIV/0! | I31: =I32/I30 -> #DIV/0! | J31: =J32/J30 -> #DIV/0! | ... DJ31: =DJ32/DJ30 -> #DIV/0! | DM31: =DM32/DM30 -> #DIV/0! | DN31: =DN32/DN30 -> 0.6 | DO31: =DO32/DO30 -> #DIV/0! | DP31: =DP32/DP30 -> 0.6
B32: Propostas enviadas | E32: 49 | F32: 40 | AX32: =$AV32/5 -> 0 | AZ32: =$AV32/5 -> 0 | BB32: =$AV32/5 -> 0 | BD32: =$AV32/5 -> 0 | BF32: =$AV32/5 -> 0 | BJ32: =$BH32/4 -> 0 | BQ32: =SUM(W32,Y32,AA32,AG32,AS32,BE32) -> 0 | BR32: =SUM(D32,N32,Z32,AJ32,AV32,BH32) -> 0 | BT32: 8.5714286 | BV32: 14.285714 | BX32: 20 | CD32: 20 | CP32: 20 | DB32: 20 | DM32: =SUM(BS32,BU32,BW32,CC32,CO32,DA32) -> 0 | DN32: =SUM(BT32,BV32,BX32,CD32,CP32,DB32) -> 102.85714 | DO32: =SUM(BQ32,DM32) -> 0 | DP32: =SUM(BR32,DN32) -> 102.85714
B33: % Conversão em Vendas | C33: =C34/C32 -> #DIV/0! | D33: =D34/D32 -> #DIV/0! | E33: =E34/E32 -> 0.10204082 | F33: =F34/F32 -> 0 | G33: =G34/G32 -> #DIV/0! | H33: =H34/H32 -> #DIV/0! | I33: =I34/I32 -> #DIV/0! | J33: =J34/J32 -> #DIV/0! | ... DJ33: =DJ34/DJ32 -> #DIV/0! | DM33: =DM34/DM32 -> #DIV/0! | DN33: =DN34/DN32 -> 0.35 | DO33: =DO34/DO32 -> #DIV/0! | DP33: =DP34/DP32 -> 0.35
B34: Volume de Vendas (contrato) | E34: 5 | AX34: =$AV34/5 -> 0 | AZ34: =$AV34/5 -> 0 | BB34: =$AV34/5 -> 0 | BD34: =$AV34/5 -> 0 | BF34: =$AV34/5 -> 0 | BJ34: =$BH34/4 -> 0 | BQ34: =SUM(W34,Y34,AA34,AG34,AS34,BE34) -> 0 | BR34: =SUM(D34,N34,Z34,AJ34,AV34,BH34) -> 0 | BT34: 3 | BV34: 5 | BX34: 7 | CD34: 7 | CP34: 7 | DB34: 7 | DM34: =SUM(BS34,BU34,BW34,CC34,CO34,DA34) -> 0 | DN34: =SUM(BT34,BV34,BX34,CD34,CP34,DB34) -> 36 | DO34: =SUM(BQ34,DM34) -> 0 | DP34: =SUM(BR34,DN34) -> 36
B35: Total de Venda (R$) | E35: 6831 | F35: 9000 | AV35: =AV34*$B$17 -> 0 | AX35: =$AV35/5 -> 0 | AZ35: =$AV35/5 -> 0 | BB35: =$AV35/5 -> 0 | BD35: =$AV35/5 -> 0 | BF35: =$AV35/5 -> 0 | BH35: =BH34*$B$17 -> 0 | BQ35: =SUM(W35,Y35,AA35,AG35,AS35,BE35) -> 0 | BR35: =BR34*$B$17 -> 0 | BT35: 6000 | BV35: 10000 | BX35: 14000 | CD35: 14000 | CP35: 14000 | DB35: 14000 | DM35: =SUM(BS35,BU35,BW35,CC35,CO35,DA35) -> 0 | DN35: =SUM(BT35,BV35,BX35,CD35,CP35,DB35) -> 72000 | DO35: =SUM(BQ35,DM35) -> 0 | DP35: =SUM(BR35,DN35) -> 72000

Sheet KPIs e Projeções Meta Tax
M2: BDR | Y2: 1
B3: KPIs | C3: Previsão | E3: 45299 | F3: 45303 | G3: 45306 | H3: 45310 | I3: 45313 | J3: 45317 | K3: 45320 | L3: 45322 | M3: BDR | Y3: Closer
C4: Meta | D4: KPIS | E4: Atingido | F4: Meta | G4: Atingido | H4: Meta | I4: Atingido | J4: Meta | K4: Atingido | L4: Meta | M4: Meta | N4: KPIS | Y4: Meta | Z4: KPIS
B5: Cadências abertas (contatos) | C5: =C7/D6 -> 176.36684 | M5: =C5/Y2 -> 176.36684
B6: % Conversão em Lead Conectado | C6: =C7/C5 -> 0.15 | D6: 0.15 | E6: =E7/E5 -> #DIV/0! | F6: =F7/F5 -> #DIV/0! | G6: =G7/G5 -> #DIV/0! | H6: =H7/H5 -> #DIV/0! | I6: =I7/I5 -> #DIV/0! | J6: =J7/J5 -> #DIV/0! | K6: =K7/K5 -> #DIV/0! | L6: =L7/L5 -> #DIV/0! | M6: =M7/M5 -> 0.15 | N6: 0.15
B7: Leads conectados | C7: =C9/D8 -> 26.455026 | M7: =C7/Y2 -> 26.455026
B8: % Conversão em Reunião agendada | C8: =C9/C7 -> 0.2 | D8: 0.2 | E8: =E9/E7 -> #DIV/0! | F8: =F9/F7 -> #DIV/0! | G8: =G9/G7 -> #DIV/0! | H8: =H9/H7 -> #DIV/0! | I8: =I9/I7 -> #DIV/0! | J8: =J9/J7 -> #DIV/0! | K8: =K9/K7 -> #DIV/0! | L8: =L9/L7 -> #DIV/0! | M8: =M9/M7 -> 0.2 | N8: 0.15
B9: Reunião agendada | C9: =C11/D10 -> 5.2910053 | M9: =C9/Y2 -> 5.2910053
B10: % de reunião realizada | C10: =C11/C9 -> 0.9 | D10: 0.9 | E10: =E11/E9 -> #DIV/0! | F10: =F11/F9 -> #DIV/0! | G10: =G11/G9 -> #DIV/0! | H10: =H11/H9 -> #DIV/0! | I10: =I11/I9 -> #DIV/0! | J10: =J11/J9 -> #DIV/0! | K10: =K11/K9 -> #DIV/0! | L10: =L11/L9 -> #DIV/0! | M10: =M11/M9 -> 0.9 | N10: 0.8
B11: Reunião realizada | C11: =C13/D12 -> 4.7619048 | M11: =C11/Y2 -> 4.7619048 | Y11: =C11 -> 4.7619048
B12: % Conversão em Proposta | C12: =C13/C11 -> 0.6 | D12: 0.6 | E12: =E13/E11 -> #DIV/0! | F12: =F13/F11 -> #DIV/0! | G12: =G13/G11 -> #DIV/0! | H12: =H13/H11 -> #DIV/0! | I12: =I13/I11 -> #DIV/0! | J12: =J13/J11 -> #DIV/0! | K12: =K13/K11 -> #DIV/0! | L12: =L13/L11 -> #DIV/0! | Y12: =Y13/Y11 -> 0.6 | Z12: 1
B13: Propostas enviadas | C13: =C15/D14 -> 2.8571429 | Y13: =C13 -> 2.8571429
B14: % Conversão em Vendas | C14: =C15/C13 -> 0.35 | D14: 0.35 | E14: =E15/E13 -> #DIV/0! | F14: =F15/F13 -> #DIV/0! | G14: =G15/G13 -> #DIV/0! | H14: =H15/H13 -> #DIV/0! | I14: =I15/I13 -> #DIV/0! | J14: =J15/J13 -> #DIV/0! | K14: =K15/K13 -> #DIV/0! | L14: =L15/L13 -> #DIV/0! | Y14: =Y15/Y13 -> 0.35 | Z14: 0.25
B15: Volume de Vendas | C15: 1 | Y15: =C15 -> 1
B16: Total de Venda (R$) | C16: =B17*C15 -> 20000 | Y16: =AH17*Y15 -> 0
A17: ticketmédio | B17: 20000
B21: Crescimento Meta
B22: Indicadores - Projeção | C22: Janeiro | E22: 45299 | F22: 45303 | G22: 45306 | H22: 45310 | I22: 45313 | J22: 45317 | K22: 45320 | L22: 45322 | M22: Fevereiro | O22: 45323 | P22: 45324 | Q22: 45327 | R22: 45331 | S22: 45334 | T22: 45338 | U22: 45341 | V22: 45345 | W22: 45348 | X22: 45351 | Y22: Março | AA22: 45352 | AB22: 45359 | AC22: 45362 | AD22: 45366 | AE22: 45369 | AF22: 45373 | AG22: 45376 | AH22: 45382 | AI22: Abril | AK22: 45383 | AL22: 45389 | AM22: 45390 | AN22: 45396 | AO22: 45397 | AP22: 45403 | AQ22: 45404 | AR22: 45410 | AS22: 45411 | AT22: 45412 | AU22: Maio | AW22: 45413 | AY22: 45417 | BA22: 45424 | BC22: 45431 | BE22: 45438 | BG22: Junho | BI22: 45446 | BK22: 45453 | BM22: 45460 | BO22: 45467 | BQ22: 1° Semestre | BS22: Julho | BU22: Agosto | BW22: Setembro | BY22: 45187 | BZ22: 45191 | CA22: 45194 | CB22: 45198 | CC22: Outubro | CE22: 45201 | CF22: 45205 | CG22: 45208 | CH22: 45212 | CI22: 45215 | CJ22: 45219 | CK22: 45222 | CL22: 45226 | CM22: 45229 | CN22: 45230 | CO22: Novembro | CQ22: 45231 | CR22: 45233 | CS22: 45236 | CT22: 45240 | CU22: 45243 | CV22: 45247 | CW22: 45250 | CX22: 45254 | CY22: 45257 | CZ22: 45260 | DA22: Dezembro | DC22: 45261 | DD22: 45261 | DE22: 45264 | DF22: 45268 | DG22: 45271 | DH22: 45275 | DI22: 45278 | DJ22: 45282 | DK22: 45285 | DL22: 45289 | DM22: 2° Semestre | DO22: TOTAL
C23: Atingido | D23: Meta | E23: Atingido | F23: Meta | G23: Atingido | H23: Meta | I23: Atingido | J23: Meta | K23: Atingido | L23: Meta | M23: Atingido | N23: Meta | O23: Atingido | P23: Meta | Q23: Atingido | R23: Meta | S23: Atingido | T23: Meta | U23: Atingido | V23: Meta | W23: Atingido | X23: Meta | Y23: Atingido | Z23: Meta | AA23: Atingido | AB23: Meta | AC23: Atingido | AD23: Meta | AE23: Atingido | AF23: Meta | AG23: Atingido | AH23: Meta | AI23: Atingido | AJ23: Meta | AK23: Atingido | AL23: Meta | AM23: Atingido | AN23: Meta | AO23: Atingido | AP23: Meta | AQ23: Atingido | AR23: Meta | AS23: Atingido | AT23: Meta | AU23: Atingido | AV23: Meta | AW23: Atingido | AX23: Meta | AY23: Atingido | AZ23: Meta | BA23: Atingido | BB23: Meta | BC23: Atingido | BD23: Meta | BE23: Atingido | BF23: Meta | BG23: Atingido | BH23: Meta | BI23: Atingido | BJ23: Meta | BK23: Atingido | BL23: Meta | BM23: Atingido | BN23: Meta | BO23: Atingido | BP23: Meta | BQ23: Atingido | BR23: Meta | BS23: Atingido | BT23: Meta | BU23: Atingido | BV23: Meta | BW23: Atingido | BX23: Meta | BY23: Atingido | BZ23: Meta | CA23: Atingido | CB23: Meta | CC23: Atingido | CD23: Meta | CE23: Atingido | CF23: Meta | CG23: Atingido | CH23: Meta | CI23: Atingido | CJ23: Meta | CK23: Atingido | CL23: Meta | CM23: Atingido | CN23: Meta | CO23: Atingido | CP23: Meta | CQ23: Atingido | CR23: Meta | CS23: Atingido | CT23: Meta | CU23: Atingido | CV23: Meta | CW23: Atingido | CX23: Meta | CY23: Atingido | CZ23: Meta | DA23: Atingido | DB23: Meta | DC23: Atingido | DD23: Meta | DE23: Atingido | DF23: Meta | DG23: Atingido | DH23: Meta | DI23: Atingido | DJ23: Meta | DK23: Atingido | DL23: Meta | DM23: Atingido | DN23: Meta | DO23: Atingido | DP23: Meta
B24: Cadências abertas (contatos) | AU24: =AW24+AY24+BA24+BC24++BE24 -> 0 | AX24: =$AV$24/5 -> 0 | AZ24: =$AV$24/5 -> 0 | BB24: =$AV$24/5 -> 0 | BD24: =$AV$24/5 -> 0 | BF24: =$AV$24/5 -> 0 | BJ24: =$BH24/4 -> 0 | BL24: =$BH$24/4 -> 0 | BN24: =$BH$24/4 -> 0 | BP24: =$BH$24/4 -> 0 | BQ24: =SUM(W24,Y24,AA24,AG24,AS24,BE24) -> 0 | BR24: 175 | BT24: 176.36684 | BV24: 176.36684 | BX24: 176.36684 | CD24: 176.36684 | CP24: 176.36684 | DB24: 176.36684 | DM24: =SUM(BS24,BU24,BW24,CC24,CO24,DA24) -> 0 | DN24: =SUM(BT24,BV24,BX24,CD24,CP24,DB24) -> 1058.2011 | DO24: =SUM(BQ24,DM24) -> 0 | DP24: =SUM(BR24,DN24) -> 1233.2011
B25: % Conversão em Lead Conectado | C25: =C26/C24 -> #DIV/0! | D25: =D26/D24 -> #DIV/0! | E25: =E26/E24 -> #DIV/0! | F25: =F26/F24 -> #DIV/0! | G25: =G26/G24 -> #DIV/0! | H25: =H26/H24 -> #DIV/0! | I25: =I26/I24 -> #DIV/0! | J25: =J26/J24 -> #DIV/0! | ... DJ25: =DJ26/DJ24 -> #DIV/0! | DM25: =DM26/DM24 -> #DIV/0! | DN25: =DN26/DN24 -> 0.15 | DO25: =DO26/DO24 -> #DIV/0! | DP25: =DP26/DP24 -> 0.12871393
B26: Leads conectados | AU26: =AW26+AY26+BA26+BC26++BE26 -> 0 | AX26: =$AV26/5 -> 0 | AZ26: =$AV26/5 -> 0 | BB26: =$AV26/5 -> 0 | BD26: =$AV26/5 -> 0 | BF26: =$AV26/5 -> 0 | BJ26: =$BH26/4 -> 0 | BQ26: =SUM(W26,Y26,AA26,AG26,AS26,BE26) -> 0 | BR26: =SUM(D26,N26,Z26,AJ26,AV26,BH26) -> 0 | BT26: 26.455026 | BV26: 26.455026 | BX26: 26.455026 | CD26: 26.455026 | CP26: 26.455026 | DB26: 26.455026 | DM26: =SUM(BS26,BU26,BW26,CC26,CO26,DA26) -> 0 | DN26: =SUM(BT26,BV26,BX26,CD26,CP26,DB26) -> 158.73016 | DO26: =SUM(BQ26,DM26) -> 0 | DP26: =SUM(BR26,DN26) -> 158.73016
B27: % Conversão em Reunião agendada | C27: =C28/C26 -> #DIV/0! | D27: =D28/D26 -> #DIV/0! | E27: =E28/E26 -> #DIV/0! | F27: =F28/F26 -> #DIV/0! | G27: =G28/G26 -> #DIV/0! | H27: =H28/H26 -> #DIV/0! | I27: =I28/I26 -> #DIV/0! | J27: =J28/J26 -> #DIV/0! | ... DJ27: =DJ28/DJ26 -> #DIV/0! | DM27: =DM28/DM26 -> #DIV/0! | DN27: =DN28/DN26 -> 0.2 | DO27: =DO28/DO26 -> #DIV/0! | DP27: =DP28/DP26 -> 0.2
B28: Reunião agendada | AU28: =AW28+AY28+BA28+BC28++BE28 -> 0 | AX28: =$AV28/5 -> 0 | AZ28: =$AV28/5 -> 0 | BB28: =$AV28/5 -> 0 | BD28: =$AV28/5 -> 0 | BF28: =$AV28/5 -> 0 | BJ28: =$BH28/4 -> 0 | BQ28: =SUM(W28,Y28,AA28,AG28,AS28,BE28) -> 0 | BR28: =SUM(D28,N28,Z28,AJ28,AV28,BH28) -> 0 | BT28: 5.2910053 | BV28: 5.2910053 | BX28: 5.2910053 | CD28: 5.2910053 | CP28: 5.2910053 | DB28: 5.2910053 | DM28: =SUM(BS28,BU28,BW28,CC28,CO28,DA28) -> 0 | DN28: =SUM(BT28,BV28,BX28,CD28,CP28,DB28) -> 31.746032 | DO28: =SUM(BQ28,DM28) -> 0 | DP28: =SUM(BR28,DN28) -> 31.746032
B29: % de reunião realizada | C29: =C30/C28 -> #DIV/0! | D29: =D30/D28 -> #DIV/0! | E29: =E30/E28 -> #DIV/0! | F29: =F30/F28 -> #DIV/0! | G29: =G30/G28 -> #DIV/0! | H29: =H30/H28 -> #DIV/0! | I29: =I30/I28 -> #DIV/0! | J29: =J30/J28 -> #DIV/0! | ... DJ29: =DJ30/DJ28 -> #DIV/0! | DM29: =DM30/DM28 -> #DIV/0! | DN29: =DN30/DN28 -> 0.9 | DO29: =DO30/DO28 -> #DIV/0! | DP29: =DP30/DP28 -> 0.9
B30: Reunião realizada | E30: 49 | F30: 40 | AU30: =AW30+AY30+BA30+BC30++BE30 -> 0 | AX30: =$AV30/5 -> 0 | AZ30: =$AV30/5 -> 0 | BB30: =$AV30/5 -> 0 | BD30: =$AV30/5 -> 0 | BF30: =$AV30/5 -> 0 | BJ30: =$BH30/4 -> 0 | BQ30: =SUM(W30,Y30,AA30,AG30,AS30,BE30) -> 0 | BR30: =SUM(D30,N30,Z30,AJ30,AV30,BH30) -> 0 | BT30: 4.7619048 | BV30: 4.7619048 | BX30: 4.7619048 | CD30: 4.7619048 | CP30: 4.7619048 | DB30: 4.7619048 | DM30: =SUM(BS30,BU30,BW30,CC30,CO30,DA30) -> 0 | DN30: =SUM(BT30,BV30,BX30,CD30,CP30,DB30) -> 28.571429 | DO30: =SUM(BQ30,DM30) -> 0 | DP30: =SUM(BR30,DN30) -> 28.571429
B31: % Conversão em Proposta | C31: =C32/C30 -> #DIV/0! | D31: =D32/D30 -> #DIV/0! | E31: =E32/E30 -> 1 | F31: =F32/F30 -> 1 | G31: =G32/G30 -> #DIV/0! | H31: =H32/H30 -> #DIV/0! | I31: =I32/I30 -> #DIV/0! | J31: =J32/J30 -> #DIV/0! | ... DJ31: =DJ32/DJ30 -> #DIV/0! | DM31: =DM32/DM30 -> #DIV/0! | DN31: =DN32/DN30 -> 0.6 | DO31: =DO32/DO30 -> #DIV/0! | DP31: =DP32/DP30 -> 0.6
B32: Propostas enviadas | E32: 49 | F32: 40 | AX32: =$AV32/5 -> 0 | AZ32: =$AV32/5 -> 0 | BB32: =$AV32/5 -> 0 | BD32: =$AV32/5 -> 0 | BF32: =$AV32/5 -> 0 | BJ32: =$BH32/4 -> 0 | BQ32: =SUM(W32,Y32,AA32,AG32,AS32,BE32) -> 0 | BR32: =SUM(D32,N32,Z32,AJ32,AV32,BH32) -> 0 | BT32: 2.8571429 | BV32: 2.8571429 | BX32: 2.8571429 | CD32: 2.8571429 | CP32: 2.8571429 | DB32: 2.8571429 | DM32: =SUM(BS32,BU32,BW32,CC32,CO32,DA32) -> 0 | DN32: =SUM(BT32,BV32,BX32,CD32,CP32,DB32) -> 17.142857 | DO32: =SUM(BQ32,DM32) -> 0 | DP32: =SUM(BR32,DN32) -> 17.142857
B33: % Conversão em Vendas | C33: =C34/C32 -> #DIV/0! | D33: =D34/D32 -> #DIV/0! | E33: =E34/E32 -> 0.10204082 | F33: =F34/F32 -> 0 | G33: =G34/G32 -> #DIV/0! | H33: =H34/H32 -> #DIV/0! | I33: =I34/I32 -> #DIV/0! | J33: =J34/J32 -> #DIV/0! | ... DJ33: =DJ34/DJ32 -> #DIV/0! | DM33: =DM34/DM32 -> #DIV/0! | DN33: =DN34/DN32 -> 0.35 | DO33: =DO34/DO32 -> #DIV/0! | DP33: =DP34/DP32 -> 0.35
B34: Volume de Vendas (contrato) | E34: 5 | AX34: =$AV34/5 -> 0 | AZ34: =$AV34/5 -> 0 | BB34: =$AV34/5 -> 0 | BD34: =$AV34/5 -> 0 | BF34: =$AV34/5 -> 0 | BJ34: =$BH34/4 -> 0 | BQ34: =SUM(W34,Y34,AA34,AG34,AS34,BE34) -> 0 | BR34: =SUM(D34,N34,Z34,AJ34,AV34,BH34) -> 0 | BT34: 1 | BV34: 1 | BX34: 1 | CD34: 1 | CP34: 1 | DB34: 1 | DM34: =SUM(BS34,BU34,BW34,CC34,CO34,DA34) -> 0 | DN34: =SUM(BT34,BV34,BX34,CD34,CP34,DB34) -> 6 | DO34: =SUM(BQ34,DM34) -> 0 | DP34: =SUM(BR34,DN34) -> 6
B35: Total de Venda (R$) | E35: 6831 | F35: 9000 | AV35: =AV34*$B$17 -> 0 | AX35: =$AV35/5 -> 0 | AZ35: =$AV35/5 -> 0 | BB35: =$AV35/5 -> 0 | BD35: =$AV35/5 -> 0 | BF35: =$AV35/5 -> 0 | BH35: =BH34*$B$17 -> 0 | BQ35: =SUM(W35,Y35,AA35,AG35,AS35,BE35) -> 0 | BR35: =BR34*$B$17 -> 0 | BT35: 20000 | BV35: 20000 | BX35: 20000 | CD35: 20000 | CP35: 20000 | DB35: 20000 | DM35: =SUM(BS35,BU35,BW35,CC35,CO35,DA35) -> 0 | DN35: =SUM(BT35,BV35,BX35,CD35,CP35,DB35) -> 120000 | DO35: =SUM(BQ35,DM35) -> 0 | DP35: =SUM(BR35,DN35) -> 120000
